Workbook

Sheet 24
B1: 证券代码 | C1: 发行人中文名称 | D1: 最新外评 | E1: 现金/存款 | F1: 不良生成率 | G1: 不良+关注 | H1: 关注类占比 | I1: 资产规模 | J1: 吸收存款 | K1: 不良贷款率 | L1: 拨备覆盖率 | M1: 资本充足率 | N1: 核心一级资本充足率 | O1: ROE(3年移动平均） | P1: 地产+建筑贷款/总贷款 | Q1: 对公活期存款/总存款 | R1: 同业资金/总负债 | S1: 对公活期存款+同业资金/总负债 | T1: 第一大股东 | U1: 第一大股东持股比例 | V1: 所在省 | W1: 所在地 | X1: 单一最大贷客户款占资本净额比例 | Y1: 最大十家客户贷款占资本净额比例 | Z1: 生息资产收益率 | AA1: 计息负债平均成本 | AB1: 净息差 | AC1: 成本收入比 | AD1: 非息收入占比
A2: 2024-06-30 | B2: 091506001.IB | C2: =IF([1]!b_info_issuer(B2)="0","",IFERROR([1]!b_info_issuer(B2),"")) -> 香港上海汇丰银行有限公司 | D2: =IF([1]!b_info_latestissurercreditrating(B2)="0","",IFERROR([1]!b_info_latestissurercreditrating(B2),"")) -> AAA | E2: =IFERROR(([1]!b_stm07_bs($B2,47,$A2,1,100000000))/[1]!b_stm07_bs($B2,109,$A2,1,100000000),"") | F2: =IFERROR(([1]!s_stmnote_bank_26($B2,$A2,1,100000000)-[1]!s_stmnote_bank_26($B2,#REF!,1,100000000)+#REF!)/[1]!s_stmnote_bank_1n($B2,#REF!,1,100000000),"") | G2: =IFERROR(H2+K2/100,"") | H2: =IFERROR([1]!s_stmnote_bank($B2,"34",$A2,100000000)/[1]!s_stmnote_bank_1n(B2,$A2,1,100000000),"") | I2: =[1]!b_stm07_bs(B2,74,$A2,1,100000000) -> 0 | J2: =[1]!b_stm07_bs(B2,109,$A2,1,100000000) -> 0 | K2: =[1]!s_stmnote_bank_5n(B2,$A2,1) -> 0 | L2: =[1]!s_stmnote_bank_23n(B2,$A2,1) -> 0 | M2: =[1]!s_stmnote_bank_capadequacyratio(B2,$A2,1) -> 0 | N2: =[1]!s_stmnote_bank_capadequacyratio_ct1(B2,$A2,1) -> 0 | O2: =IF(OR([1]!s_fa_roe(B2,20201231)="0",[1]!s_fa_roe(B2,20211231)="0",[1]!s_fa_roe(B2,20221231)="0"),"",IFERROR(([1]!s_fa_roe(B2,20221231)+[1]!s_fa_roe(B2,20201231)+[1]!s_fa_roe(B2,20211231))/3,"")) -> 0 | P2: =IFERROR(([1]!s_stmnote_bank_65(B2,$A2,1,2,4,100000000)+[1]!s_stmnote_bank_65(B2,$A2,1,2,6,100000000))/[1]!s_stmnote_bank_1n(B2,$A2,1,100000000),"") | Q2: =IFERROR([1]!s_stmnote_bank_614(B2,$A2,1,2,100000000)/[1]!s_stmnote_bank_647(B2,$A2,1,2,100000000),"") | R2: =IFERROR(([1]!b_stm07_bs(B2,104,$A2,1,100000000)+[1]!b_stm07_bs(B2,106,$A2,1,100000000)+[1]!b_stm07_bs(B2,76,$A2,1,100000000)+[1]!b_stm07_bs(B2,108,$A2,1,100000000)+[1]!b_stm07_bs(B2,95,$A2,1,100000000))/[1]!b_stm07_bs(B2,128,$A2,1,100000000),"") | S2: =IFERROR(([1]!s_stmnote_bank_614(B2,$A2,1,2,100000000)+[1]!b_stm07_bs(B2,104,$A2,1,100000000)+[1]!b_stm07_bs(B2,106,$A2,1,100000000)+[1]!b_stm07_bs(B2,76,$A2,1,100000000)+[1]!b_stm07_bs(B2,108,$A2,1,100000000)+[1]!b_stm07_bs(B2,95,$A2,1,100000000))/[1]!b_stm07_bs(B2,128,$A2,1,100000000),"") | T2: =[1]!b_issuer_shareholder(B2,"",1) -> 汇丰控股有限公司 | U2: =[1]!b_issuer_propofshareholder(B2,"",1) -> 100 | V2: =LEFT(C2,2) -> 香港 | W2: =[1]!s_info_city(B2) -> 香港特别行政区 | X2: =IF([1]!s_stmnote_bank_17n(B2,$A2,1)="0","",[1]!s_stmnote_bank_17n(B2,$A2,1)) -> 0 | Y2: =IF([1]!s_stmnote_bank_18n(B2,$A2,1)="0","",[1]!s_stmnote_bank_18n(B2,$A2,1)) -> 0 | Z2: =IF([1]!s_stmnote_bank_58(B2,$A2,1)="0","",[1]!s_stmnote_bank_58(B2,$A2,1)) -> 0 | AA2: =IF([1]!s_stmnote_bank_60(B2,$A2,1)="0","",[1]!s_stmnote_bank_60(B2,$A2,1)) -> 0 | AB2: =[1]!s_stmnote_bank_5444(B2,$A2,1) -> 0 | AC2: =[1]!s_stmnote_bank_129n($B2,$A2,1) -> 0 | AD2: =[1]!s_stmnote_bank_30(B2,$A2,1) -> 0
A3: 2024-06-30 | B3: 091506002.IB | C3: =IF([1]!b_info_issuer(B3)="0","",IFERROR([1]!b_info_issuer(B3),"")) -> 0 | D3: =IF([1]!b_info_latestissurercreditrating(B3)="0","",IFERROR([1]!b_info_latestissurercreditrating(B3),"")) -> 0 | E3: =IFERROR(([1]!b_stm07_bs($B3,47,$A3,1,100000000))/[1]!b_stm07_bs($B3,109,$A3,1,100000000),"") | F3: =IFERROR(([1]!s_stmnote_bank_26($B3,$A3,1,100000000)-[1]!s_stmnote_bank_26($B3,#REF!,1,100000000)+#REF!)/[1]!s_stmnote_bank_1n($B3,#REF!,1,100000000),"") | G3: =IFERROR(H3+K3/100,"") | H3: =IFERROR([1]!s_stmnote_bank($B3,"34",$A3,100000000)/[1]!s_stmnote_bank_1n(B3,$A3,1,100000000),"") | I3: =[1]!b_stm07_bs(B3,74,$A3,1,100000000) -> 0 | J3: =[1]!b_stm07_bs(B3,109,$A3,1,100000000) -> 0 | K3: =[1]!s_stmnote_bank_5n(B3,$A3,1) -> 0 | L3: =[1]!s_stmnote_bank_23n(B3,$A3,1) -> 0 | M3: =[1]!s_stmnote_bank_capadequacyratio(B3,$A3,1) -> 0 | N3: =[1]!s_stmnote_bank_capadequacyratio_ct1(B3,$A3,1) -> 0 | O3: =IF(OR([1]!s_fa_roe(B3,20201231)="0",[1]!s_fa_roe(B3,20211231)="0",[1]!s_fa_roe(B3,20221231)="0"),"",IFERROR(([1]!s_fa_roe(B3,20221231)+[1]!s_fa_roe(B3,20201231)+[1]!s_fa_roe(B3,20211231))/3,"")) -> 0 | P3: =IFERROR(([1]!s_stmnote_bank_65(B3,$A3,1,2,4,100000000)+[1]!s_stmnote_bank_65(B3,$A3,1,2,6,100000000))/[1]!s_stmnote_bank_1n(B3,$A3,1,100000000),"") | Q3: =IFERROR([1]!s_stmnote_bank_614(B3,$A3,1,2,100000000)/[1]!s_stmnote_bank_647(B3,$A3,1,2,100000000),"") | R3: =IFERROR(([1]!b_stm07_bs(B3,104,$A3,1,100000000)+[1]!b_stm07_bs(B3,106,$A3,1,100000000)+[1]!b_stm07_bs(B3,76,$A3,1,100000000)+[1]!b_stm07_bs(B3,108,$A3,1,100000000)+[1]!b_stm07_bs(B3,95,$A3,1,100000000))/[1]!b_stm07_bs(B3,128,$A3,1,100000000),"") | S3: =IFERROR(([1]!s_stmnote_bank_614(B3,$A3,1,2,100000000)+[1]!b_stm07_bs(B3,104,$A3,1,100000000)+[1]!b_stm07_bs(B3,106,$A3,1,100000000)+[1]!b_stm07_bs(B3,76,$A3,1,100000000)+[1]!b_stm07_bs(B3,108,$A3,1,100000000)+[1]!b_stm07_bs(B3,95,$A3,1,100000000))/[1]!b_stm07_bs(B3,128,$A3,1,100000000),"") | T3: =[1]!b_issuer_shareholder(B3,"",1) -> 0 | U3: =[1]!b_issuer_propofshareholder(B3,"",1) -> 0 | V3: =LEFT(C3,2) -> 0 | W3: =[1]!s_info_city(B3) -> 0 | X3: =IF([1]!s_stmnote_bank_17n(B3,$A3,1)="0","",[1]!s_stmnote_bank_17n(B3,$A3,1)) -> 0 | Y3: =IF([1]!s_stmnote_bank_18n(B3,$A3,1)="0","",[1]!s_stmnote_bank_18n(B3,$A3,1)) -> 0 | Z3: =IF([1]!s_stmnote_bank_58(B3,$A3,1)="0","",[1]!s_stmnote_bank_58(B3,$A3,1)) -> 0 | AA3: =IF([1]!s_stmnote_bank_60(B3,$A3,1)="0","",[1]!s_stmnote_bank_60(B3,$A3,1)) -> 0 | AB3: =[1]!s_stmnote_bank_5444(B3,$A3,1) -> 0 | AC3: =[1]!s_stmnote_bank_129n($B3,$A3,1) -> 0 | AD3: =[1]!s_stmnote_bank_30(B3,$A3,1) -> 0
A4: 2024-06-30 | B4: 091506003.IB | C4: =IF([1]!b_info_issuer(B4)="0","",IFERROR([1]!b_info_issuer(B4),"")) -> 0 | D4: =IF([1]!b_info_latestissurercreditrating(B4)="0","",IFERROR([1]!b_info_latestissurercreditrating(B4),"")) -> 0 | E4: =IFERROR(([1]!b_stm07_bs($B4,47,$A4,1,100000000))/[1]!b_stm07_bs($B4,109,$A4,1,100000000),"") | F4: =IFERROR(([1]!s_stmnote_bank_26($B4,$A4,1,100000000)-[1]!s_stmnote_bank_26($B4,#REF!,1,100000000)+#REF!)/[1]!s_stmnote_bank_1n($B4,#REF!,1,100000000),"") | G4: =IFERROR(H4+K4/100,"") | H4: =IFERROR([1]!s_stmnote_bank($B4,"34",$A4,100000000)/[1]!s_stmnote_bank_1n(B4,$A4,1,100000000),"") | I4: =[1]!b_stm07_bs(B4,74,$A4,1,100000000) -> 0 | J4: =[1]!b_stm07_bs(B4,109,$A4,1,100000000) -> 0 | K4: =[1]!s_stmnote_bank_5n(B4,$A4,1) -> 0 | L4: =[1]!s_stmnote_bank_23n(B4,$A4,1) -> 0 | M4: =[1]!s_stmnote_bank_capadequacyratio(B4,$A4,1) -> 0 | N4: =[1]!s_stmnote_bank_capadequacyratio_ct1(B4,$A4,1) -> 0 | O4: =IF(OR([1]!s_fa_roe(B4,20201231)="0",[1]!s_fa_roe(B4,20211231)="0",[1]!s_fa_roe(B4,20221231)="0"),"",IFERROR(([1]!s_fa_roe(B4,20221231)+[1]!s_fa_roe(B4,20201231)+[1]!s_fa_roe(B4,20211231))/3,"")) -> 0 | P4: =IFERROR(([1]!s_stmnote_bank_65(B4,$A4,1,2,4,100000000)+[1]!s_stmnote_bank_65(B4,$A4,1,2,6,100000000))/[1]!s_stmnote_bank_1n(B4,$A4,1,100000000),"") | Q4: =IFERROR([1]!s_stmnote_bank_614(B4,$A4,1,2,100000000)/[1]!s_stmnote_bank_647(B4,$A4,1,2,100000000),"") | R4: =IFERROR(([1]!b_stm07_bs(B4,104,$A4,1,100000000)+[1]!b_stm07_bs(B4,106,$A4,1,100000000)+[1]!b_stm07_bs(B4,76,$A4,1,100000000)+[1]!b_stm07_bs(B4,108,$A4,1,100000000)+[1]!b_stm07_bs(B4,95,$A4,1,100000000))/[1]!b_stm07_bs(B4,128,$A4,1,100000000),"") | S4: =IFERROR(([1]!s_stmnote_bank_614(B4,$A4,1,2,100000000)+[1]!b_stm07_bs(B4,104,$A4,1,100000000)+[1]!b_stm07_bs(B4,106,$A4,1,100000000)+[1]!b_stm07_bs(B4,76,$A4,1,100000000)+[1]!b_stm07_bs(B4,108,$A4,1,100000000)+[1]!b_stm07_bs(B4,95,$A4,1,100000000))/[1]!b_stm07_bs(B4,128,$A4,1,100000000),"") | T4: =[1]!b_issuer_shareholder(B4,"",1) -> 0 | U4: =[1]!b_issuer_propofshareholder(B4,"",1) -> 0 | V4: =LEFT(C4,2) -> 0 | W4: =[1]!s_info_city(B4) -> 0 | X4: =IF([1]!s_stmnote_bank_17n(B4,$A4,1)="0","",[1]!s_stmnote_bank_17n(B4,$A4,1)) -> 0 | Y4: =IF([1]!s_stmnote_bank_18n(B4,$A4,1)="0","",[1]!s_stmnote_bank_18n(B4,$A4,1)) -> 0 | Z4: =IF([1]!s_stmnote_bank_58(B4,$A4,1)="0","",[1]!s_stmnote_bank_58(B4,$A4,1)) -> 0 | AA4: =IF([1]!s_stmnote_bank_60(B4,$A4,1)="0","",[1]!s_stmnote_bank_60(B4,$A4,1)) -> 0 | AB4: =[1]!s_stmnote_bank_5444(B4,$A4,1) -> 0 | AC4: =[1]!s_stmnote_bank_129n($B4,$A4,1) -> 0 | AD4: =[1]!s_stmnote_bank_30(B4,$A4,1) -> 0
A5: 2024-06-30 | B5: 091506004.IB | C5: =IF([1]!b_info_issuer(B5)="0","",IFERROR([1]!b_info_issuer(B5),"")) -> 0 | D5: =IF([1]!b_info_latestissurercreditrating(B5)="0","",IFERROR([1]!b_info_latestissurercreditrating(B5),"")) -> 0 | E5: =IFERROR(([1]!b_stm07_bs($B5,47,$A5,1,100000000))/[1]!b_stm07_bs($B5,109,$A5,1,100000000),"") | F5: =IFERROR(([1]!s_stmnote_bank_26($B5,$A5,1,100000000)-[1]!s_stmnote_bank_26($B5,#REF!,1,100000000)+#REF!)/[1]!s_stmnote_bank_1n($B5,#REF!,1,100000000),"") | G5: =IFERROR(H5+K5/100,"") | H5: =IFERROR([1]!s_stmnote_bank($B5,"34",$A5,100000000)/[1]!s_stmnote_bank_1n(B5,$A5,1,100000000),"") | I5: =[1]!b_stm07_bs(B5,74,$A5,1,100000000) -> 0 | J5: =[1]!b_stm07_bs(B5,109,$A5,1,100000000) -> 0 | K5: =[1]!s_stmnote_bank_5n(B5,$A5,1) -> 0 | L5: =[1]!s_stmnote_bank_23n(B5,$A5,1) -> 0 | M5: =[1]!s_stmnote_bank_capadequacyratio(B5,$A5,1) -> 0 | N5: =[1]!s_stmnote_bank_capadequacyratio_ct1(B5,$A5,1) -> 0 | O5: =IF(OR([1]!s_fa_roe(B5,20201231)="0",[1]!s_fa_roe(B5,20211231)="0",[1]!s_fa_roe(B5,20221231)="0"),"",IFERROR(([1]!s_fa_roe(B5,20221231)+[1]!s_fa_roe(B5,20201231)+[1]!s_fa_roe(B5,20211231))/3,"")) -> 0 | P5: =IFERROR(([1]!s_stmnote_bank_65(B5,$A5,1,2,4,100000000)+[1]!s_stmnote_bank_65(B5,$A5,1,2,6,100000000))/[1]!s_stmnote_bank_1n(B5,$A5,1,100000000),"") | Q5: =IFERROR([1]!s_stmnote_bank_614(B5,$A5,1,2,100000000)/[1]!s_stmnote_bank_647(B5,$A5,1,2,100000000),"") | R5: =IFERROR(([1]!b_stm07_bs(B5,104,$A5,1,100000000)+[1]!b_stm07_bs(B5,106,$A5,1,100000000)+[1]!b_stm07_bs(B5,76,$A5,1,100000000)+[1]!b_stm07_bs(B5,108,$A5,1,100000000)+[1]!b_stm07_bs(B5,95,$A5,1,100000000))/[1]!b_stm07_bs(B5,128,$A5,1,100000000),"") | S5: =IFERROR(([1]!s_stmnote_bank_614(B5,$A5,1,2,100000000)+[1]!b_stm07_bs(B5,104,$A5,1,100000000)+[1]!b_stm07_bs(B5,106,$A5,1,100000000)+[1]!b_stm07_bs(B5,76,$A5,1,100000000)+[1]!b_stm07_bs(B5,108,$A5,1,100000000)+[1]!b_stm07_bs(B5,95,$A5,1,100000000))/[1]!b_stm07_bs(B5,128,$A5,1,100000000),"") | T5: =[1]!b_issuer_shareholder(B5,"",1) -> 0 | U5: =[1]!b_issuer_propofshareholder(B5,"",1) -> 0 | V5: =LEFT(C5,2) -> 0 | W5: =[1]!s_info_city(B5) -> 0 | X5: =IF([1]!s_stmnote_bank_17n(B5,$A5,1)="0","",[1]!s_stmnote_bank_17n(B5,$A5,1)) -> 0 | Y5: =IF([1]!s_stmnote_bank_18n(B5,$A5,1)="0","",[1]!s_stmnote_bank_18n(B5,$A5,1)) -> 0 | Z5: =IF([1]!s_stmnote_bank_58(B5,$A5,1)="0","",[1]!s_stmnote_bank_58(B5,$A5,1)) -> 0 | AA5: =IF([1]!s_stmnote_bank_60(B5,$A5,1)="0","",[1]!s_stmnote_bank_60(B5,$A5,1)) -> 0 | AB5: =[1]!s_stmnote_bank_5444(B5,$A5,1) -> 0 | AC5: =[1]!s_stmnote_bank_129n($B5,$A5,1) -> 0 | AD5: =[1]!s_stmnote_bank_30(B5,$A5,1) -> 0
A6: 2024-06-30 | B6: 091506005.IB | C6: =IF([1]!b_info_issuer(B6)="0","",IFERROR([1]!b_info_issuer(B6),"")) -> 0 | D6: =IF([1]!b_info_latestissurercreditrating(B6)="0","",IFERROR([1]!b_info_latestissurercreditrating(B6),"")) -> 0 | E6: =IFERROR(([1]!b_stm07_bs($B6,47,$A6,1,100000000))/[1]!b_stm07_bs($B6,109,$A6,1,100000000),"") | F6: =IFERROR(([1]!s_stmnote_bank_26($B6,$A6,1,100000000)-[1]!s_stmnote_bank_26($B6,#REF!,1,100000000)+#REF!)/[1]!s_stmnote_bank_1n($B6,#REF!,1,100000000),"") | G6: =IFERROR(H6+K6/100,"") | H6: =IFERROR([1]!s_stmnote_bank($B6,"34",$A6,100000000)/[1]!s_stmnote_bank_1n(B6,$A6,1,100000000),"") | I6: =[1]!b_stm07_bs(B6,74,$A6,1,100000000) -> 0 | J6: =[1]!b_stm07_bs(B6,109,$A6,1,100000000) -> 0 | K6: =[1]!s_stmnote_bank_5n(B6,$A6,1) -> 0 | L6: =[1]!s_stmnote_bank_23n(B6,$A6,1) -> 0 | M6: =[1]!s_stmnote_bank_capadequacyratio(B6,$A6,1) -> 0 | N6: =[1]!s_stmnote_bank_capadequacyratio_ct1(B6,$A6,1) -> 0 | O6: =IF(OR([1]!s_fa_roe(B6,20201231)="0",[1]!s_fa_roe(B6,20211231)="0",[1]!s_fa_roe(B6,20221231)="0"),"",IFERROR(([1]!s_fa_roe(B6,20221231)+[1]!s_fa_roe(B6,20201231)+[1]!s_fa_roe(B6,20211231))/3,"")) -> 0 | P6: =IFERROR(([1]!s_stmnote_bank_65(B6,$A6,1,2,4,100000000)+[1]!s_stmnote_bank_65(B6,$A6,1,2,6,100000000))/[1]!s_stmnote_bank_1n(B6,$A6,1,100000000),"") | Q6: =IFERROR([1]!s_stmnote_bank_614(B6,$A6,1,2,100000000)/[1]!s_stmnote_bank_647(B6,$A6,1,2,100000000),"") | R6: =IFERROR(([1]!b_stm07_bs(B6,104,$A6,1,100000000)+[1]!b_stm07_bs(B6,106,$A6,1,100000000)+[1]!b_stm07_bs(B6,76,$A6,1,100000000)+[1]!b_stm07_bs(B6,108,$A6,1,100000000)+[1]!b_stm07_bs(B6,95,$A6,1,100000000))/[1]!b_stm07_bs(B6,128,$A6,1,100000000),"") | S6: =IFERROR(([1]!s_stmnote_bank_614(B6,$A6,1,2,100000000)+[1]!b_stm07_bs(B6,104,$A6,1,100000000)+[1]!b_stm07_bs(B6,106,$A6,1,100000000)+[1]!b_stm07_bs(B6,76,$A6,1,100000000)+[1]!b_stm07_bs(B6,108,$A6,1,100000000)+[1]!b_stm07_bs(B6,95,$A6,1,100000000))/[1]!b_stm07_bs(B6,128,$A6,1,100000000),"") | T6: =[1]!b_issuer_shareholder(B6,"",1) -> 0 | U6: =[1]!b_issuer_propofshareholder(B6,"",1) -> 0 | V6: =LEFT(C6,2) -> 0 | W6: =[1]!s_info_city(B6) -> 0 | X6: =IF([1]!s_stmnote_bank_17n(B6,$A6,1)="0","",[1]!s_stmnote_bank_17n(B6,$A6,1)) -> 0 | Y6: =IF([1]!s_stmnote_bank_18n(B6,$A6,1)="0","",[1]!s_stmnote_bank_18n(B6,$A6,1)) -> 0 | Z6: =IF([1]!s_stmnote_bank_58(B6,$A6,1)="0","",[1]!s_stmnote_bank_58(B6,$A6,1)) -> 0 | AA6: =IF([1]!s_stmnote_bank_60(B6,$A6,1)="0","",[1]!s_stmnote_bank_60(B6,$A6,1)) -> 0 | AB6: =[1]!s_stmnote_bank_5444(B6,$A6,1) -> 0 | AC6: =[1]!s_stmnote_bank_129n($B6,$A6,1) -> 0 | AD6: =[1]!s_stmnote_bank_30(B6,$A6,1) -> 0
A7: 2024-06-30 | B7: 091506006.IB | C7: =IF([1]!b_info_issuer(B7)="0","",IFERROR([1]!b_info_issuer(B7),"")) -> 0 | D7: =IF([1]!b_info_latestissurercreditrating(B7)="0","",IFERROR([1]!b_info_latestissurercreditrating(B7),"")) -> 0 | E7: =IFERROR(([1]!b_stm07_bs($B7,47,$A7,1,100000000))/[1]!b_stm07_bs($B7,109,$A7,1,100000000),"") | F7: =IFERROR(([1]!s_stmnote_bank_26($B7,$A7,1,100000000)-[1]!s_stmnote_bank_26($B7,#REF!,1,100000000)+#REF!)/[1]!s_stmnote_bank_1n($B7,#REF!,1,100000000),"") | G7: =IFERROR(H7+K7/100,"") | H7: =IFERROR([1]!s_stmnote_bank($B7,"34",$A7,100000000)/[1]!s_stmnote_bank_1n(B7,$A7,1,100000000),"") | I7: =[1]!b_stm07_bs(B7,74,$A7,1,100000000) -> 0 | J7: =[1]!b_stm07_bs(B7,109,$A7,1,100000000) -> 0 | K7: =[1]!s_stmnote_bank_5n(B7,$A7,1) -> 0 | L7: =[1]!s_stmnote_bank_23n(B7,$A7,1) -> 0 | M7: =[1]!s_stmnote_bank_capadequacyratio(B7,$A7,1) -> 0 | N7: =[1]!s_stmnote_bank_capadequacyratio_ct1(B7,$A7,1) -> 0 | O7: =IF(OR([1]!s_fa_roe(B7,20201231)="0",[1]!s_fa_roe(B7,20211231)="0",[1]!s_fa_roe(B7,20221231)="0"),"",IFERROR(([1]!s_fa_roe(B7,20221231)+[1]!s_fa_roe(B7,20201231)+[1]!s_fa_roe(B7,20211231))/3,"")) -> 0 | P7: =IFERROR(([1]!s_stmnote_bank_65(B7,$A7,1,2,4,100000000)+[1]!s_stmnote_bank_65(B7,$A7,1,2,6,100000000))/[1]!s_stmnote_bank_1n(B7,$A7,1,100000000),"") | Q7: =IFERROR([1]!s_stmnote_bank_614(B7,$A7,1,2,100000000)/[1]!s_stmnote_bank_647(B7,$A7,1,2,100000000),"") | R7: =IFERROR(([1]!b_stm07_bs(B7,104,$A7,1,100000000)+[1]!b_stm07_bs(B7,106,$A7,1,100000000)+[1]!b_stm07_bs(B7,76,$A7,1,100000000)+[1]!b_stm07_bs(B7,108,$A7,1,100000000)+[1]!b_stm07_bs(B7,95,$A7,1,100000000))/[1]!b_stm07_bs(B7,128,$A7,1,100000000),"") | S7: =IFERROR(([1]!s_stmnote_bank_614(B7,$A7,1,2,100000000)+[1]!b_stm07_bs(B7,104,$A7,1,100000000)+[1]!b_stm07_bs(B7,106,$A7,1,100000000)+[1]!b_stm07_bs(B7,76,$A7,1,100000000)+[1]!b_stm07_bs(B7,108,$A7,1,100000000)+[1]!b_stm07_bs(B7,95,$A7,1,100000000))/[1]!b_stm07_bs(B7,128,$A7,1,100000000),"") | T7: =[1]!b_issuer_shareholder(B7,"",1) -> 0 | U7: =[1]!b_issuer_propofshareholder(B7,"",1) -> 0 | V7: =LEFT(C7,2) -> 0 | W7: =[1]!s_info_city(B7) -> 0 | X7: =IF([1]!s_stmnote_bank_17n(B7,$A7,1)="0","",[1]!s_stmnote_bank_17n(B7,$A7,1)) -> 0 | Y7: =IF([1]!s_stmnote_bank_18n(B7,$A7,1)="0","",[1]!s_stmnote_bank_18n(B7,$A7,1)) -> 0 | Z7: =IF([1]!s_stmnote_bank_58(B7,$A7,1)="0","",[1]!s_stmnote_bank_58(B7,$A7,1)) -> 0 | AA7: =IF([1]!s_stmnote_bank_60(B7,$A7,1)="0","",[1]!s_stmnote_bank_60(B7,$A7,1)) -> 0 | AB7: =[1]!s_stmnote_bank_5444(B7,$A7,1) -> 0 | AC7: =[1]!s_stmnote_bank_129n($B7,$A7,1) -> 0 | AD7: =[1]!s_stmnote_bank_30(B7,$A7,1) -> 0
A8: 2024-06-30 | B8: 091506007.IB | C8: =IF([1]!b_info_issuer(B8)="0","",IFERROR([1]!b_info_issuer(B8),"")) -> 0 | D8: =IF([1]!b_info_latestissurercreditrating(B8)="0","",IFERROR([1]!b_info_latestissurercreditrating(B8),"")) -> 0 | E8: =IFERROR(([1]!b_stm07_bs($B8,47,$A8,1,100000000))/[1]!b_stm07_bs($B8,109,$A8,1,100000000),"") | F8: =IFERROR(([1]!s_stmnote_bank_26($B8,$A8,1,100000000)-[1]!s_stmnote_bank_26($B8,#REF!,1,100000000)+#REF!)/[1]!s_stmnote_bank_1n($B8,#REF!,1,100000000),"") | G8: =IFERROR(H8+K8/100,"") | H8: =IFERROR([1]!s_stmnote_bank($B8,"34",$A8,100000000)/[1]!s_stmnote_bank_1n(B8,$A8,1,100000000),"") | I8: =[1]!b_stm07_bs(B8,74,$A8,1,100000000) -> 0 | J8: =[1]!b_stm07_bs(B8,109,$A8,1,100000000) -> 0 | K8: =[1]!s_stmnote_bank_5n(B8,$A8,1) -> 0 | L8: =[1]!s_stmnote_bank_23n(B8,$A8,1) -> 0 | M8: =[1]!s_stmnote_bank_capadequacyratio(B8,$A8,1) -> 0 | N8: =[1]!s_stmnote_bank_capadequacyratio_ct1(B8,$A8,1) -> 0 | O8: =IF(OR([1]!s_fa_roe(B8,20201231)="0",[1]!s_fa_roe(B8,20211231)="0",[1]!s_fa_roe(B8,20221231)="0"),"",IFERROR(([1]!s_fa_roe(B8,20221231)+[1]!s_fa_roe(B8,20201231)+[1]!s_fa_roe(B8,20211231))/3,"")) -> 0 | P8: =IFERROR(([1]!s_stmnote_bank_65(B8,$A8,1,2,4,100000000)+[1]!s_stmnote_bank_65(B8,$A8,1,2,6,100000000))/[1]!s_stmnote_bank_1n(B8,$A8,1,100000000),"") | Q8: =IFERROR([1]!s_stmnote_bank_614(B8,$A8,1,2,100000000)/[1]!s_stmnote_bank_647(B8,$A8,1,2,100000000),"") | R8: =IFERROR(([1]!b_stm07_bs(B8,104,$A8,1,100000000)+[1]!b_stm07_bs(B8,106,$A8,1,100000000)+[1]!b_stm07_bs(B8,76,$A8,1,100000000)+[1]!b_stm07_bs(B8,108,$A8,1,100000000)+[1]!b_stm07_bs(B8,95,$A8,1,100000000))/[1]!b_stm07_bs(B8,128,$A8,1,100000000),"") | S8: =IFERROR(([1]!s_stmnote_bank_614(B8,$A8,1,2,100000000)+[1]!b_stm07_bs(B8,104,$A8,1,100000000)+[1]!b_stm07_bs(B8,106,$A8,1,100000000)+[1]!b_stm07_bs(B8,76,$A8,1,100000000)+[1]!b_stm07_bs(B8,108,$A8,1,100000000)+[1]!b_stm07_bs(B8,95,$A8,1,100000000))/[1]!b_stm07_bs(B8,128,$A8,1,100000000),"") | T8: =[1]!b_issuer_shareholder(B8,"",1) -> 0 | U8: =[1]!b_issuer_propofshareholder(B8,"",1) -> 0 | V8: =LEFT(C8,2) -> 0 | W8: =[1]!s_info_city(B8) -> 0 | X8: =IF([1]!s_stmnote_bank_17n(B8,$A8,1)="0","",[1]!s_stmnote_bank_17n(B8,$A8,1)) -> 0 | Y8: =IF([1]!s_stmnote_bank_18n(B8,$A8,1)="0","",[1]!s_stmnote_bank_18n(B8,$A8,1)) -> 0 | Z8: =IF([1]!s_stmnote_bank_58(B8,$A8,1)="0","",[1]!s_stmnote_bank_58(B8,$A8,1)) -> 0 | AA8: =IF([1]!s_stmnote_bank_60(B8,$A8,1)="0","",[1]!s_stmnote_bank_60(B8,$A8,1)) -> 0 | AB8: =[1]!s_stmnote_bank_5444(B8,$A8,1) -> 0 | AC8: =[1]!s_stmnote_bank_129n($B8,$A8,1) -> 0 | AD8: =[1]!s_stmnote_bank_30(B8,$A8,1) -> 0
A9: 2024-06-30 | B9: 091506008.IB | C9: =IF([1]!b_info_issuer(B9)="0","",IFERROR([1]!b_info_issuer(B9),"")) -> 0 | D9: =IF([1]!b_info_latestissurercreditrating(B9)="0","",IFERROR([1]!b_info_latestissurercreditrating(B9),"")) -> 0 | E9: =IFERROR(([1]!b_stm07_bs($B9,47,$A9,1,100000000))/[1]!b_stm07_bs($B9,109,$A9,1,100000000),"") | F9: =IFERROR(([1]!s_stmnote_bank_26($B9,$A9,1,100000000)-[1]!s_stmnote_bank_26($B9,#REF!,1,100000000)+#REF!)/[1]!s_stmnote_bank_1n($B9,#REF!,1,100000000),"") | G9: =IFERROR(H9+K9/100,"") | H9: =IFERROR([1]!s_stmnote_bank($B9,"34",$A9,100000000)/[1]!s_stmnote_bank_1n(B9,$A9,1,100000000),"") | I9: =[1]!b_stm07_bs(B9,74,$A9,1,100000000) -> 0 | J9: =[1]!b_stm07_bs(B9,109,$A9,1,100000000) -> 0 | K9: =[1]!s_stmnote_bank_5n(B9,$A9,1) -> 0 | L9: =[1]!s_stmnote_bank_23n(B9,$A9,1) -> 0 | M9: =[1]!s_stmnote_bank_capadequacyratio(B9,$A9,1) -> 0 | N9: =[1]!s_stmnote_bank_capadequacyratio_ct1(B9,$A9,1) -> 0 | O9: =IF(OR([1]!s_fa_roe(B9,20201231)="0",[1]!s_fa_roe(B9,20211231)="0",[1]!s_fa_roe(B9,20221231)="0"),"",IFERROR(([1]!s_fa_roe(B9,20221231)+[1]!s_fa_roe(B9,20201231)+[1]!s_fa_roe(B9,20211231))/3,"")) -> 0 | P9: =IFERROR(([1]!s_stmnote_bank_65(B9,$A9,1,2,4,100000000)+[1]!s_stmnote_bank_65(B9,$A9,1,2,6,100000000))/[1]!s_stmnote_bank_1n(B9,$A9,1,100000000),"") | Q9: =IFERROR([1]!s_stmnote_bank_614(B9,$A9,1,2,100000000)/[1]!s_stmnote_bank_647(B9,$A9,1,2,100000000),"") | R9: =IFERROR(([1]!b_stm07_bs(B9,104,$A9,1,100000000)+[1]!b_stm07_bs(B9,106,$A9,1,100000000)+[1]!b_stm07_bs(B9,76,$A9,1,100000000)+[1]!b_stm07_bs(B9,108,$A9,1,100000000)+[1]!b_stm07_bs(B9,95,$A9,1,100000000))/[1]!b_stm07_bs(B9,128,$A9,1,100000000),"") | S9: =IFERROR(([1]!s_stmnote_bank_614(B9,$A9,1,2,100000000)+[1]!b_stm07_bs(B9,104,$A9,1,100000000)+[1]!b_stm07_bs(B9,106,$A9,1,100000000)+[1]!b_stm07_bs(B9,76,$A9,1,100000000)+[1]!b_stm07_bs(B9,108,$A9,1,100000000)+[1]!b_stm07_bs(B9,95,$A9,1,100000000))/[1]!b_stm07_bs(B9,128,$A9,1,100000000),"") | T9: =[1]!b_issuer_shareholder(B9,"",1) -> 0 | U9: =[1]!b_issuer_propofshareholder(B9,"",1) -> 0 | V9: =LEFT(C9,2) -> 0 | W9: =[1]!s_info_city(B9) -> 0 | X9: =IF([1]!s_stmnote_bank_17n(B9,$A9,1)="0","",[1]!s_stmnote_bank_17n(B9,$A9,1)) -> 0 | Y9: =IF([1]!s_stmnote_bank_18n(B9,$A9,1)="0","",[1]!s_stmnote_bank_18n(B9,$A9,1)) -> 0 | Z9: =IF([1]!s_stmnote_bank_58(B9,$A9,1)="0","",[1]!s_stmnote_bank_58(B9,$A9,1)) -> 0 | AA9: =IF([1]!s_stmnote_bank_60(B9,$A9,1)="0","",[1]!s_stmnote_bank_60(B9,$A9,1)) -> 0 | AB9: =[1]!s_stmnote_bank_5444(B9,$A9,1) -> 0 | AC9: =[1]!s_stmnote_bank_129n($B9,$A9,1) -> 0 | AD9: =[1]!s_stmnote_bank_30(B9,$A9,1) -> 0
A10: 2024-06-30 | B10: 091506009.IB | C10: =IF([1]!b_info_issuer(B10)="0","",IFERROR([1]!b_info_issuer(B10),"")) -> 0 | D10: =IF([1]!b_info_latestissurercreditrating(B10)="0","",IFERROR([1]!b_info_latestissurercreditrating(B10),"")) -> 0 | E10: =IFERROR(([1]!b_stm07_bs($B10,47,$A10,1,100000000))/[1]!b_stm07_bs($B10,109,$A10,1,100000000),"") | F10: =IFERROR(([1]!s_stmnote_bank_26($B10,$A10,1,100000000)-[1]!s_stmnote_bank_26($B10,#REF!,1,100000000)+#REF!)/[1]!s_stmnote_bank_1n($B10,#REF!,1,100000000),"") | G10: =IFERROR(H10+K10/100,"") | H10: =IFERROR([1]!s_stmnote_bank($B10,"34",$A10,100000000)/[1]!s_stmnote_bank_1n(B10,$A10,1,100000000),"") | I10: =[1]!b_stm07_bs(B10,74,$A10,1,100000000) -> 0 | J10: =[1]!b_stm07_bs(B10,109,$A10,1,100000000) -> 0 | K10: =[1]!s_stmnote_bank_5n(B10,$A10,1) -> 0 | L10: =[1]!s_stmnote_bank_23n(B10,$A10,1) -> 0 | M10: =[1]!s_stmnote_bank_capadequacyratio(B10,$A10,1) -> 0 | N10: =[1]!s_stmnote_bank_capadequacyratio_ct1(B10,$A10,1) -> 0 | O10: =IF(OR([1]!s_fa_roe(B10,20201231)="0",[1]!s_fa_roe(B10,20211231)="0",[1]!s_fa_roe(B10,20221231)="0"),"",IFERROR(([1]!s_fa_roe(B10,20221231)+[1]!s_fa_roe(B10,20201231)+[1]!s_fa_roe(B10,20211231))/3,"")) -> 0 | P10: =IFERROR(([1]!s_stmnote_bank_65(B10,$A10,1,2,4,100000000)+[1]!s_stmnote_bank_65(B10,$A10,1,2,6,100000000))/[1]!s_stmnote_bank_1n(B10,$A10,1,100000000),"") | Q10: =IFERROR([1]!s_stmnote_bank_614(B10,$A10,1,2,100000000)/[1]!s_stmnote_bank_647(B10,$A10,1,2,100000000),"") | R10: =IFERROR(([1]!b_stm07_bs(B10,104,$A10,1,100000000)+[1]!b_stm07_bs(B10,106,$A10,1,100000000)+[1]!b_stm07_bs(B10,76,$A10,1,100000000)+[1]!b_stm07_bs(B10,108,$A10,1,100000000)+[1]!b_stm07_bs(B10,95,$A10,1,100000000))/[1]!b_stm07_bs(B10,128,$A10,1,100000000),"") | S10: =IFERROR(([1]!s_stmnote_bank_614(B10,$A10,1,2,100000000)+[1]!b_stm07_bs(B10,104,$A10,1,100000000)+[1]!b_stm07_bs(B10,106,$A10,1,100000000)+[1]!b_stm07_bs(B10,76,$A10,1,100000000)+[1]!b_stm07_bs(B10,108,$A10,1,100000000)+[1]!b_stm07_bs(B10,95,$A10,1,100000000))/[1]!b_stm07_bs(B10,128,$A10,1,100000000),"") | T10: =[1]!b_issuer_shareholder(B10,"",1) -> 0 | U10: =[1]!b_issuer_propofshareholder(B10,"",1) -> 0 | V10: =LEFT(C10,2) -> 0 | W10: =[1]!s_info_city(B10) -> 0 | X10: =IF([1]!s_stmnote_bank_17n(B10,$A10,1)="0","",[1]!s_stmnote_bank_17n(B10,$A10,1)) -> 0 | Y10: =IF([1]!s_stmnote_bank_18n(B10,$A10,1)="0","",[1]!s_stmnote_bank_18n(B10,$A10,1)) -> 0 | Z10: =IF([1]!s_stmnote_bank_58(B10,$A10,1)="0","",[1]!s_stmnote_bank_58(B10,$A10,1)) -> 0 | AA10: =IF([1]!s_stmnote_bank_60(B10,$A10,1)="0","",[1]!s_stmnote_bank_60(B10,$A10,1)) -> 0 | AB10: =[1]!s_stmnote_bank_5444(B10,$A10,1) -> 0 | AC10: =[1]!s_stmnote_bank_129n($B10,$A10,1) -> 0 | AD10: =[1]!s_stmnote_bank_30(B10,$A10,1) -> 0
A11: 2024-06-30 | B11: 091506010.IB | C11: =IF([1]!b_info_issuer(B11)="0","",IFERROR([1]!b_info_issuer(B11),"")) -> 0 | D11: =IF([1]!b_info_latestissurercreditrating(B11)="0","",IFERROR([1]!b_info_latestissurercreditrating(B11),"")) -> 0 | E11: =IFERROR(([1]!b_stm07_bs($B11,47,$A11,1,100000000))/[1]!b_stm07_bs($B11,109,$A11,1,100000000),"") | F11: =IFERROR(([1]!s_stmnote_bank_26($B11,$A11,1,100000000)-[1]!s_stmnote_bank_26($B11,#REF!,1,100000000)+#REF!)/[1]!s_stmnote_bank_1n($B11,#REF!,1,100000000),"") | G11: =IFERROR(H11+K11/100,"") | H11: =IFERROR([1]!s_stmnote_bank($B11,"34",$A11,100000000)/[1]!s_stmnote_bank_1n(B11,$A11,1,100000000),"") | I11: =[1]!b_stm07_bs(B11,74,$A11,1,100000000) -> 0 | J11: =[1]!b_stm07_bs(B11,109,$A11,1,100000000) -> 0 | K11: =[1]!s_stmnote_bank_5n(B11,$A11,1) -> 0 | L11: =[1]!s_stmnote_bank_23n(B11,$A11,1) -> 0 | M11: =[1]!s_stmnote_bank_capadequacyratio(B11,$A11,1) -> 0 | N11: =[1]!s_stmnote_bank_capadequacyratio_ct1(B11,$A11,1) -> 0 | O11: =IF(OR([1]!s_fa_roe(B11,20201231)="0",[1]!s_fa_roe(B11,20211231)="0",[1]!s_fa_roe(B11,20221231)="0"),"",IFERROR(([1]!s_fa_roe(B11,20221231)+[1]!s_fa_roe(B11,20201231)+[1]!s_fa_roe(B11,20211231))/3,"")) -> 0 | P11: =IFERROR(([1]!s_stmnote_bank_65(B11,$A11,1,2,4,100000000)+[1]!s_stmnote_bank_65(B11,$A11,1,2,6,100000000))/[1]!s_stmnote_bank_1n(B11,$A11,1,100000000),"") | Q11: =IFERROR([1]!s_stmnote_bank_614(B11,$A11,1,2,100000000)/[1]!s_stmnote_bank_647(B11,$A11,1,2,100000000),"") | R11: =IFERROR(([1]!b_stm07_bs(B11,104,$A11,1,100000000)+[1]!b_stm07_bs(B11,106,$A11,1,100000000)+[1]!b_stm07_bs(B11,76,$A11,1,100000000)+[1]!b_stm07_bs(B11,108,$A11,1,100000000)+[1]!b_stm07_bs(B11,95,$A11,1,100000000))/[1]!b_stm07_bs(B11,128,$A11,1,100000000),"") | S11: =IFERROR(([1]!s_stmnote_bank_614(B11,$A11,1,2,100000000)+[1]!b_stm07_bs(B11,104,$A11,1,100000000)+[1]!b_stm07_bs(B11,106,$A11,1,100000000)+[1]!b_stm07_bs(B11,76,$A11,1,100000000)+[1]!b_stm07_bs(B11,108,$A11,1,100000000)+[1]!b_stm07_bs(B11,95,$A11,1,100000000))/[1]!b_stm07_bs(B11,128,$A11,1,100000000),"") | T11: =[1]!b_issuer_shareholder(B11,"",1) -> 0 | U11: =[1]!b_issuer_propofshareholder(B11,"",1) -> 0 | V11: =LEFT(C11,2) -> 0 | W11: =[1]!s_info_city(B11) -> 0 | X11: =IF([1]!s_stmnote_bank_17n(B11,$A11,1)="0","",[1]!s_stmnote_bank_17n(B11,$A11,1)) -> 0 | Y11: =IF([1]!s_stmnote_bank_18n(B11,$A11,1)="0","",[1]!s_stmnote_bank_18n(B11,$A11,1)) -> 0 | Z11: =IF([1]!s_stmnote_bank_58(B11,$A11,1)="0","",[1]!s_stmnote_bank_58(B11,$A11,1)) -> 0 | AA11: =IF([1]!s_stmnote_bank_60(B11,$A11,1)="0","",[1]!s_stmnote_bank_60(B11,$A11,1)) -> 0 | AB11: =[1]!s_stmnote_bank_5444(B11,$A11,1) -> 0 | AC11: =[1]!s_stmnote_bank_129n($B11,$A11,1) -> 0 | AD11: =[1]!s_stmnote_bank_30(B11,$A11,1) -> 0
A12: 2024-06-30 | B12: 091506011.IB | C12: =IF([1]!b_info_issuer(B12)="0","",IFERROR([1]!b_info_issuer(B12),"")) -> 0 | D12: =IF([1]!b_info_latestissurercreditrating(B12)="0","",IFERROR([1]!b_info_latestissurercreditrating(B12),"")) -> 0 | E12: =IFERROR(([1]!b_stm07_bs($B12,47,$A12,1,100000000))/[1]!b_stm07_bs($B12,109,$A12,1,100000000),"") | F12: =IFERROR(([1]!s_stmnote_bank_26($B12,$A12,1,100000000)-[1]!s_stmnote_bank_26($B12,#REF!,1,100000000)+#REF!)/[1]!s_stmnote_bank_1n($B12,#REF!,1,100000000),"") | G12: =IFERROR(H12+K12/100,"") | H12: =IFERROR([1]!s_stmnote_bank($B12,"34",$A12,100000000)/[1]!s_stmnote_bank_1n(B12,$A12,1,100000000),"") | I12: =[1]!b_stm07_bs(B12,74,$A12,1,100000000) -> 0 | J12: =[1]!b_stm07_bs(B12,109,$A12,1,100000000) -> 0 | K12: =[1]!s_stmnote_bank_5n(B12,$A12,1) -> 0 | L12: =[1]!s_stmnote_bank_23n(B12,$A12,1) -> 0 | M12: =[1]!s_stmnote_bank_capadequacyratio(B12,$A12,1) -> 0 | N12: =[1]!s_stmnote_bank_capadequacyratio_ct1(B12,$A12,1) -> 0 | O12: =IF(OR([1]!s_fa_roe(B12,20201231)="0",[1]!s_fa_roe(B12,20211231)="0",[1]!s_fa_roe(B12,20221231)="0"),"",IFERROR(([1]!s_fa_roe(B12,20221231)+[1]!s_fa_roe(B12,20201231)+[1]!s_fa_roe(B12,20211231))/3,"")) -> 0 | P12: =IFERROR(([1]!s_stmnote_bank_65(B12,$A12,1,2,4,100000000)+[1]!s_stmnote_bank_65(B12,$A12,1,2,6,100000000))/[1]!s_stmnote_bank_1n(B12,$A12,1,100000000),"") | Q12: =IFERROR([1]!s_stmnote_bank_614(B12,$A12,1,2,100000000)/[1]!s_stmnote_bank_647(B12,$A12,1,2,100000000),"") | R12: =IFERROR(([1]!b_stm07_bs(B12,104,$A12,1,100000000)+[1]!b_stm07_bs(B12,106,$A12,1,100000000)+[1]!b_stm07_bs(B12,76,$A12,1,100000000)+[1]!b_stm07_bs(B12,108,$A12,1,100000000)+[1]!b_stm07_bs(B12,95,$A12,1,100000000))/[1]!b_stm07_bs(B12,128,$A12,1,100000000),"") | S12: =IFERROR(([1]!s_stmnote_bank_614(B12,$A12,1,2,100000000)+[1]!b_stm07_bs(B12,104,$A12,1,100000000)+[1]!b_stm07_bs(B12,106,$A12,1,100000000)+[1]!b_stm07_bs(B12,76,$A12,1,100000000)+[1]!b_stm07_bs(B12,108,$A12,1,100000000)+[1]!b_stm07_bs(B12,95,$A12,1,100000000))/[1]!b_stm07_bs(B12,128,$A12,1,100000000),"") | T12: =[1]!b_issuer_shareholder(B12,"",1) -> 0 | U12: =[1]!b_issuer_propofshareholder(B12,"",1) -> 0 | V12: =LEFT(C12,2) -> 0 | W12: =[1]!s_info_city(B12) -> 0 | X12: =IF([1]!s_stmnote_bank_17n(B12,$A12,1)="0","",[1]!s_stmnote_bank_17n(B12,$A12,1)) -> 0 | Y12: =IF([1]!s_stmnote_bank_18n(B12,$A12,1)="0","",[1]!s_stmnote_bank_18n(B12,$A12,1)) -> 0 | Z12: =IF([1]!s_stmnote_bank_58(B12,$A12,1)="0","",[1]!s_stmnote_bank_58(B12,$A12,1)) -> 0 | AA12: =IF([1]!s_stmnote_bank_60(B12,$A12,1)="0","",[1]!s_stmnote_bank_60(B12,$A12,1)) -> 0 | AB12: =[1]!s_stmnote_bank_5444(B12,$A12,1) -> 0 | AC12: =[1]!s_stmnote_bank_129n($B12,$A12,1) -> 0 | AD12: =[1]!s_stmnote_bank_30(B12,$A12,1) -> 0
A13: 2024-06-30 | B13: 091506012.IB | C13: =IF([1]!b_info_issuer(B13)="0","",IFERROR([1]!b_info_issuer(B13),"")) -> 0 | D13: =IF([1]!b_info_latestissurercreditrating(B13)="0","",IFERROR([1]!b_info_latestissurercreditrating(B13),"")) -> 0 | E13: =IFERROR(([1]!b_stm07_bs($B13,47,$A13,1,100000000))/[1]!b_stm07_bs($B13,109,$A13,1,100000000),"") | F13: =IFERROR(([1]!s_stmnote_bank_26($B13,$A13,1,100000000)-[1]!s_stmnote_bank_26($B13,#REF!,1,100000000)+#REF!)/[1]!s_stmnote_bank_1n($B13,#REF!,1,100000000),"") | G13: =IFERROR(H13+K13/100,"") | H13: =IFERROR([1]!s_stmnote_bank($B13,"34",$A13,100000000)/[1]!s_stmnote_bank_1n(B13,$A13,1,100000000),"") | I13: =[1]!b_stm07_bs(B13,74,$A13,1,100000000) -> 0 | J13: =[1]!b_stm07_bs(B13,109,$A13,1,100000000) -> 0 | K13: =[1]!s_stmnote_bank_5n(B13,$A13,1) -> 0 | L13: =[1]!s_stmnote_bank_23n(B13,$A13,1) -> 0 | M13: =[1]!s_stmnote_bank_capadequacyratio(B13,$A13,1) -> 0 | N13: =[1]!s_stmnote_bank_capadequacyratio_ct1(B13,$A13,1) -> 0 | O13: =IF(OR([1]!s_fa_roe(B13,20201231)="0",[1]!s_fa_roe(B13,20211231)="0",[1]!s_fa_roe(B13,20221231)="0"),"",IFERROR(([1]!s_fa_roe(B13,20221231)+[1]!s_fa_roe(B13,20201231)+[1]!s_fa_roe(B13,20211231))/3,"")) -> 0 | P13: =IFERROR(([1]!s_stmnote_bank_65(B13,$A13,1,2,4,100000000)+[1]!s_stmnote_bank_65(B13,$A13,1,2,6,100000000))/[1]!s_stmnote_bank_1n(B13,$A13,1,100000000),"") | Q13: =IFERROR([1]!s_stmnote_bank_614(B13,$A13,1,2,100000000)/[1]!s_stmnote_bank_647(B13,$A13,1,2,100000000),"") | R13: =IFERROR(([1]!b_stm07_bs(B13,104,$A13,1,100000000)+[1]!b_stm07_bs(B13,106,$A13,1,100000000)+[1]!b_stm07_bs(B13,76,$A13,1,100000000)+[1]!b_stm07_bs(B13,108,$A13,1,100000000)+[1]!b_stm07_bs(B13,95,$A13,1,100000000))/[1]!b_stm07_bs(B13,128,$A13,1,100000000),"") | S13: =IFERROR(([1]!s_stmnote_bank_614(B13,$A13,1,2,100000000)+[1]!b_stm07_bs(B13,104,$A13,1,100000000)+[1]!b_stm07_bs(B13,106,$A13,1,100000000)+[1]!b_stm07_bs(B13,76,$A13,1,100000000)+[1]!b_stm07_bs(B13,108,$A13,1,100000000)+[1]!b_stm07_bs(B13,95,$A13,1,100000000))/[1]!b_stm07_bs(B13,128,$A13,1,100000000),"") | T13: =[1]!b_issuer_shareholder(B13,"",1) -> 0 | U13: =[1]!b_issuer_propofshareholder(B13,"",1) -> 0 | V13: =LEFT(C13,2) -> 0 | W13: =[1]!s_info_city(B13) -> 0 | X13: =IF([1]!s_stmnote_bank_17n(B13,$A13,1)="0","",[1]!s_stmnote_bank_17n(B13,$A13,1)) -> 0 | Y13: =IF([1]!s_stmnote_bank_18n(B13,$A13,1)="0","",[1]!s_stmnote_bank_18n(B13,$A13,1)) -> 0 | Z13: =IF([1]!s_stmnote_bank_58(B13,$A13,1)="0","",[1]!s_stmnote_bank_58(B13,$A13,1)) -> 0 | AA13: =IF([1]!s_stmnote_bank_60(B13,$A13,1)="0","",[1]!s_stmnote_bank_60(B13,$A13,1)) -> 0 | AB13: =[1]!s_stmnote_bank_5444(B13,$A13,1) -> 0 | AC13: =[1]!s_stmnote_bank_129n($B13,$A13,1) -> 0 | AD13: =[1]!s_stmnote_bank_30(B13,$A13,1) -> 0
... A568: 2024-06-30 | B568: 091506567.IB | C568: =IF([1]!b_info_issuer(B568)="0","",IFERROR([1]!b_info_issuer(B568),"")) -> 0 | D568: =IF([1]!b_info_latestissurercreditrating(B568)="0","",IFERROR([1]!b_info_latestissurercreditrating(B568),"")) -> 0 | E568: =IFERROR(([1]!b_stm07_bs($B568,47,$A568,1,100000000))/[1]!b_stm07_bs($B568,109,$A568,1,100000000),"") | F568: =IFERROR(([1]!s_stmnote_bank_26($B568,$A568,1,100000000)-[1]!s_stmnote_bank_26($B568,#REF!,1,100000000)+#REF!)/[1]!s_stmnote_bank_1n($B568,#REF!,1,100000000),"") | G568: =IFERROR(H568+K568/100,"") | H568: =IFERROR([1]!s_stmnote_bank($B568,"34",$A568,100000000)/[1]!s_stmnote_bank_1n(B568,$A568,1,100000000),"") | I568: =[1]!b_stm07_bs(B568,74,$A568,1,100000000) -> 0 | J568: =[1]!b_stm07_bs(B568,109,$A568,1,100000000) -> 0 | K568: =[1]!s_stmnote_bank_5n(B568,$A568,1) -> 0 | L568: =[1]!s_stmnote_bank_23n(B568,$A568,1) -> 0 | M568: =[1]!s_stmnote_bank_capadequacyratio(B568,$A568,1) -> 0 | N568: =[1]!s_stmnote_bank_capadequacyratio_ct1(B568,$A568,1) -> 0 | O568: =IF(OR([1]!s_fa_roe(B568,20201231)="0",[1]!s_fa_roe(B568,20211231)="0",[1]!s_fa_roe(B568,20221231)="0"),"",IFERROR(([1]!s_fa_roe(B568,20221231)+[1]!s_fa_roe(B568,20201231)+[1]!s_fa_roe(B568,20211231))/3,"")) -> 0 | P568: =IFERROR(([1]!s_stmnote_bank_65(B568,$A568,1,2,4,100000000)+[1]!s_stmnote_bank_65(B568,$A568,1,2,6,100000000))/[1]!s_stmnote_bank_1n(B568,$A568,1,100000000),"") | Q568: =IFERROR([1]!s_stmnote_bank_614(B568,$A568,1,2,100000000)/[1]!s_stmnote_bank_647(B568,$A568,1,2,100000000),"") | R568: =IFERROR(([1]!b_stm07_bs(B568,104,$A568,1,100000000)+[1]!b_stm07_bs(B568,106,$A568,1,100000000)+[1]!b_stm07_bs(B568,76,$A568,1,100000000)+[1]!b_stm07_bs(B568,108,$A568,1,100000000)+[1]!b_stm07_bs(B568,95,$A568,1,100000000))/[1]!b_stm07_bs(B568,128,$A568,1,100000000),"") | S568: =IFERROR(([1]!s_stmnote_bank_614(B568,$A568,1,2,100000000)+[1]!b_stm07_bs(B568,104,$A568,1,100000000)+[1]!b_stm07_bs(B568,106,$A568,1,100000000)+[1]!b_stm07_bs(B568,76,$A568,1,100000000)+[1]!b_stm07_bs(B568,108,$A568,1,100000000)+[1]!b_stm07_bs(B568,95,$A568,1,100000000))/[1]!b_stm07_bs(B568,128,$A568,1,100000000),"") | T568: =[1]!b_issuer_shareholder(B568,"",1) -> 0 | U568: =[1]!b_issuer_propofshareholder(B568,"",1) -> 0 | V568: =LEFT(C568,2) -> 0 | W568: =[1]!s_info_city(B568) -> 0 | X568: =IF([1]!s_stmnote_bank_17n(B568,$A568,1)="0","",[1]!s_stmnote_bank_17n(B568,$A568,1)) -> 0 | Y568: =IF([1]!s_stmnote_bank_18n(B568,$A568,1)="0","",[1]!s_stmnote_bank_18n(B568,$A568,1)) -> 0 | Z568: =IF([1]!s_stmnote_bank_58(B568,$A568,1)="0","",[1]!s_stmnote_bank_58(B568,$A568,1)) -> 0 | AA568: =IF([1]!s_stmnote_bank_60(B568,$A568,1)="0","",[1]!s_stmnote_bank_60(B568,$A568,1)) -> 0 | AB568: =[1]!s_stmnote_bank_5444(B568,$A568,1) -> 0 | AC568: =[1]!s_stmnote_bank_129n($B568,$A568,1) -> 0 | AD568: =[1]!s_stmnote_bank_30(B568,$A568,1) -> 0

Sheet 22年 (2)
A1: 20211231 | B1: 20201231 | C1: 20191231 | D1: 20220630 | E1: 20210930 | F1: 20210630 | G1: 20210331 | H1: 金融债或存单市场表现对应内评(优先金融债，无存续金融债则取存单表现） | I1: 新内评 | J1: 持仓(截至2023811） | K1: 简评 | L1: 现金/存款 | M1: 贷款资产质量 | U1: 非信贷资产质量 | Z1: 定量指标 | AJ1: 地产+建筑贷款/总贷款 | AK1: 对公活期存款/总存款 | AL1: 同业资金/总负债 | AM1: 对公活期存款+同业资金/总负债 | AN1: 定量打分 | AV1: 定性指标 | AY1: 定性打分 | BC1: 总计分 | BD1: 模型评级 | BE1: 外部支持 | BF1: 其他调整 | BG1: 备注 | BH1: 外部支持 | BJ1: 业务运营 | BL1: 集中度 | BN1: 盈利拆分（公布口径） | BQ1: 成本收入比 | BR1: 盈利拆分（计算口径） | CJ1: 非息收入占比 | CK1: 贷款利息收入 | CL1: 投资类收入 | CM1: 平均贷款收益率 | CN1: 存款利息支出 | CO1: 平均存款收益率 | CR1: 22年末ROE | CT1: 23年中ROE | CU1: 23年中ROE排位 | CV1: 22年贷款规模 | CW1: 个人贷款规模 | CX1: 个人贷款占比
A2: 证券代码 | B2: 发行人中文名称 | C2: 简称 | D2: 分类 | E2: 是否有额度 | F2: 最新外评 | G2: 原内评 | M2: 不良资产处置（核销+转让+现金清收+证券化+抵债等方式） | N2: 不良生成率 | O2: 不良生成率排序 | P2: 不良+关注 | Q2: 不良+关注行业排序 | R2: 关注类占比 | S2: 二阶段占比 | T2: 三阶段占比 | U2: 非标/总资产 | V2: 非标逾期占比 | W2: 二阶段/(金融投资+特殊报表科目） | X2: 三阶段/(金融投资+特殊报表科目） | Y2: 三阶段减值准备/三阶段 | Z2: 资产规模 | AA2: 吸收存款 | AB2: 不良贷款率 | AC2: 拨备覆盖率 | AD2: 拨备排位 | AE2: 资本充足率 | AF2: 核心一级资本充足率 | AG2: 核心资本排位 | AH2: ROE(3年移动平均） | AI2: ROE(3年移动平均）排位 | AN2: 资产规模 | AO2: 吸收存款 | AP2: 不良率 | AQ2: 拨备覆盖率 | AR2: 资本充足率 | AS2: 核心一级资本充足率 | AT2: ROE(3年移动平均） | AU2: 定量打分 | AV2: =#REF! -> #REF! | AW2: =#REF! -> #REF! | AX2: =#REF! -> #REF! | AY2: 区域环境及增长潜力 | AZ2: 信贷资产五级分类偏离度 | BA2: 非信贷资产质量 | BB2: 定性总分 | BH2: 第一大股东 | BI2: 第一大股东持股比例 | BJ2: 所在省 | BK2: 所在地 | BL2: 单一最大贷客户款占资本净额比例 | BM2: 最大十家客户贷款占资本净额比例 | BN2: 生息资产收益率 | BO2: 计息负债平均成本 | BP2: 净息差 | BR2: 生息资产收益率 | BY2: 计息负债平均成本 | CF2: 净息差 | CG2: 净息差排序 | CH2: 净息差/（不良+关注） | CI2: 净息差/（不良+关注）排序 | CP2: 22年末净资产 | CQ2: 22年中净资产 | CR2: 22年末ROE | CS2: 22年末ROE排位 | CT2: 23年中ROE | CU2: 23年中ROE
A3: 参数行，勿删 | AN3: 0.2 | AO3: 0.2 | AP3: 0.18 | AQ3: 0.12 | AR3: 0.09 | AS3: 0.12 | AT3: 0.09
A4: 公式行，勿删 | B4: =IF([1]!b_info_issuer(A4)="0","",IFERROR([1]!b_info_issuer(A4),"")) -> 0 | C4: =IF([1]!b_issuer_issuershortened(A4)="0","",IFERROR([1]!b_issuer_issuershortened(A4),"")) -> 0 | F4: =IF([1]!b_info_latestissurercreditrating(A4)="0","",IFERROR([1]!b_info_latestissurercreditrating(A4),"")) -> 0 | G4: =_xlfn.IFNA(VLOOKUP(B4,'[2]主表-22'!$C:$H,5,0),"") | L4: =IFERROR(([1]!b_stm07_bs($A4,47,$A$1,1,100000000))/[1]!b_stm07_bs($A4,109,$A$1,1,100000000),"") | N4: =IFERROR(([1]!s_stmnote_bank_26($A4,$A$1,1,100000000)-[1]!s_stmnote_bank_26($A4,$B$1,1,100000000)+M4)/[1]!s_stmnote_bank_1n($A4,$B$1,1,100000000),"") | O4: =RANK(N4,N$5:N$192,1)&" "&COUNTIF(N$5:N$192,">0") -> #VALUE! | P4: =IF(IFERROR(R4+AB4/100,"")=0,"",IFERROR(R4+AB4/100,"")) | Q4: =RANK(P4,P$5:P$192,1)&" "&COUNTIF(P$5:P$192,">0") -> #VALUE! | R4: =IFERROR([1]!s_stmnote_bank($A4,"34",$A$1,100000000)/[1]!s_stmnote_bank_1n(A4,$A$1,1,100000000),"") | S4: =IFERROR((1113.54+22.69)/[1]!s_stmnote_bank_1n(A4,$A$1,1,100000000),"") | T4: =IFERROR((508.62)/[1]!s_stmnote_bank_1n(A4,$A$1,1,100000000),"") | U4: =IFERROR((1298.51)/[1]!b_stm07_bs($A4,74,$A$1,1,100000000),"") | W4: =IFERROR((22.36)/([1]!s_stm07_bs_fininv($A4,$A$1,1,100000000)+[1]!s_stm07_bs_71($A4,$A$1,1,100000000)),"") | X4: =IFERROR((240.77+1.12)/([1]!s_stm07_bs_fininv($A4,$A$1,1,100000000)+[1]!s_stm07_bs_71($A4,$A$1,1,100000000)),"") | Y4: =(10.47+240.21)/(240.77+1.12) -> 1.0363388 | Z4: =IF([1]!b_stm07_bs(A4,74,$A$1,1,100000000)="0","",IFERROR([1]!b_stm07_bs(A4,74,$A$1,1,100000000),"")) -> 0 | AA4: =IF([1]!b_stm07_bs(A4,109,$A$1,1,100000000)="0","",IFERROR([1]!b_stm07_bs(A4,109,$A$1,1,100000000),"")) -> 0 | AB4: =IF([1]!s_stmnote_bank_5n(A4,$A$1,1)="0","",IFERROR([1]!s_stmnote_bank_5n(A4,$A$1,1),"")) -> 0 | AC4: =IF([1]!s_stmnote_bank_23n(A4,$A$1,1)=0,"",IFERROR([1]!s_stmnote_bank_23n(A4,$A$1,1),"")) | AD4: =RANK(AC4,AC$5:AC$192,1)&" "&COUNTIF(AC$5:AC$192,">0") -> #VALUE! | AE4: =IF([1]!s_stmnote_bank_capadequacyratio(A4,$A$1,1)="0","",IFERROR([1]!s_stmnote_bank_capadequacyratio(A4,$A$1,1),"")) -> 0 | AF4: =IF([1]!s_stmnote_bank_capadequacyratio_ct1(A4,$A$1,1)=0,"",IFERROR([1]!s_stmnote_bank_capadequacyratio_ct1(A4,$A$1,1),"")) | AG4: =RANK(AF4,AF$5:AF$192,0)&" "&COUNTIF(AF$5:AF$192,">0") -> #VALUE! | AH4: =IF(OR([1]!s_fa_roe(A4,20201231)=0,[1]!s_fa_roe(A4,20211231)="0",[1]!s_fa_roe(A4,20221231)="0"),"",IFERROR(([1]!s_fa_roe(A4,20221231)+[1]!s_fa_roe(A4,20201231)+[1]!s_fa_roe(A4,20211231))/3,"")) | AI4: =RANK(AH4,AH$5:AH$192,1)&" "&COUNTIF(AH$5:AH$192,">0") -> #VALUE! | AJ4: =IFERROR(([1]!s_stmnote_bank_65(A4,$A$1,1,2,4,100000000)+[1]!s_stmnote_bank_65(A4,$A$1,1,2,6,100000000))/[1]!s_stmnote_bank_1n(A4,$A$1,1,100000000),"") | AK4: =IFERROR([1]!s_stmnote_bank_614(A4,$A$1,1,2,100000000)/[1]!s_stmnote_bank_647(A4,$A$1,1,2,100000000),"") | AL4: =IFERROR(([1]!b_stm07_bs(A4,104,$A$1,1,100000000)+[1]!b_stm07_bs(A4,106,$A$1,1,100000000)+[1]!b_stm07_bs(A4,76,$A$1,1,100000000)+[1]!b_stm07_bs(A4,108,$A$1,1,100000000)+[1]!b_stm07_bs(A4,95,$A$1,1,100000000))/[1]!b_stm07_bs(A4,128,$A$1,1,100000000),"") | AM4: =IFERROR(([1]!s_stmnote_bank_614(A4,$A$1,1,2,100000000)+[1]!b_stm07_bs(A4,104,$A$1,1,100000000)+[1]!b_stm07_bs(A4,106,$A$1,1,100000000)+[1]!b_stm07_bs(A4,76,$A$1,1,100000000)+[1]!b_stm07_bs(A4,108,$A$1,1,100000000)+[1]!b_stm07_bs(A4,95,$A$1,1,100000000))/[1]!b_stm07_bs(A4,128,$A$1,1,100000000),"") | AN4: =IF(Z4>#REF!,#REF!,IF(Z4>#REF!,#REF!,IF(Z4>#REF!,#REF!,IF(Z4>#REF!,#REF!,IF(Z4>#REF!,#REF!,IF(Z4>#REF!,#REF!,IF(Z4>#REF!,#REF!,#REF!))))))) -> #REF! | AO4: =IF(AA4>#REF!,#REF!,IF(AA4>#REF!,#REF!,IF(AA4>#REF!,#REF!,IF(AA4>#REF!,#REF!,IF(AA4>#REF!,#REF!,IF(AA4>#REF!,#REF!,IF(AA4>#REF!,#REF!,#REF!))))))) -> #REF! | AP4: =IF(AB4<#REF!,#REF!,IF(AB4<#REF!,#REF!,IF(AB4<#REF!,#REF!,IF(AB4<#REF!,#REF!,IF(AB4<#REF!,#REF!,IF(AB4<#REF!,#REF!,#REF!)))))) -> #REF! | AQ4: =IF(AC4>#REF!,#REF!,IF(AC4>#REF!,#REF!,IF(AC4>#REF!,#REF!,IF(AC4>#REF!,#REF!,#REF!)))) -> #REF! | AR4: =IF(AE4>#REF!,#REF!,IF(AE4>#REF!,#REF!,IF(AE4>#REF!,#REF!,IF(AE4>#REF!,#REF!,#REF!)))) -> #REF! | AS4: =IF(AF4>#REF!,#REF!,IF(AF4>#REF!,#REF!,IF(AF4>#REF!,#REF!,IF(AF4>#REF!,#REF!,#REF!)))) -> #REF! | AT4: =IF(AH4>#REF!,#REF!,IF(AH4>#REF!,#REF!,IF(AH4>#REF!,#REF!,IF(AH4>#REF!,#REF!,IF(AH4>#REF!,#REF!,#REF!))))) -> #REF! | AU4: =AN4*$AN$3+AP4*$AP$3+AQ4*$AQ$3+AR4*$AR$3+AS4*$AS$3+AT4*$AT$3+$AO$3*AO4 -> #REF! | AV4: 强 | AW4: 较低 | AX4: 好 | AY4: =IFERROR(VLOOKUP(AV4,#REF!,3,0),"") | AZ4: =IFERROR(VLOOKUP(AW4,#REF!,3,0),"") | BA4: =IFERROR(VLOOKUP(AX4,#REF!,3,0),"") | BB4: =IFERROR(AY4*#REF!+AZ4*#REF!+BA4*#REF!,"") | BC4: =IFERROR(AU4*0.6+BB4*0.4,"") | BD4: =IFERROR(VLOOKUP(BC4*10,#REF!,2,1),"") | BH4: =[1]!b_issuer_shareholder(A4,"",1) -> 0 | BI4: =[1]!b_issuer_propofshareholder(A4,"",1) -> 0 | BJ4: =LEFT(B4,2) -> 0 | BK4: =[1]!s_info_city(A4) -> 0 | BL4: =IF([1]!s_stmnote_bank_17n(A4,$A$1,1)="0","",[1]!s_stmnote_bank_17n(A4,$A$1,1)) -> 0 | BM4: =IF([1]!s_stmnote_bank_18n(A4,$A$1,1)="0","",[1]!s_stmnote_bank_18n(A4,$A$1,1)) -> 0 | BN4: =IF([1]!s_stmnote_bank_58(A4,$A$1,1)="0","",[1]!s_stmnote_bank_58(A4,$A$1,1)) -> 0 | BO4: =IF([1]!s_stmnote_bank_60(A4,$A$1,1)="0","",[1]!s_stmnote_bank_60(A4,$A$1,1)) -> 0 | BP4: =[1]!s_stmnote_bank_5444(A4,$A$1,1) -> 0 | BQ4: =[1]!s_stmnote_bank_129n($A4,$A$1,1) -> 0 | BR4: =([1]!b_stm07_is(A4,19,$A$1,1,100000000))/AVERAGE([1]!s_stmnote_bank_35(A4,$A$1,1,100000000),[1]!s_stmnote_bank_35(A4,$E$1,1,100000000),[1]!s_stmnote_bank_35(A4,$F$1,1,100000000),[1]!s_stmnote_bank_35(A4,$G$1,1,100000000))*100 -> #DIV/0! | BT4: 10 | BU4: 70 | BV4: 5 | BW4: 10 | BX4: =100-SUM(BT4:BW4) -> 5 | BY4: =IFERROR([1]!b_stm07_is(A4,20,$A$1,1,100000000)/AVERAGEIF(CA4:CE4,">0")*100,0) -> 0 | CF4: =IF(BP4<>0,BP4,IFERROR(IF(([1]!b_stm07_is(A4,19,$A$1,1,100000000)-[1]!b_stm07_is(A4,20,$A$1,1,100000000))/AVERAGE([1]!s_stmnote_bank_35(A4,$A$1,1,100000000),[1]!s_stmnote_bank_35(A4,$B$1,1,100000000))*100=0,"",([1]!b_stm07_is(A4,19,$A$1,1,100000000)-[1]!b_stm07_is(A4,20,$A$1,1,100000000))/AVERAGE([1]!s_stmnote_bank_35(A4,$A$1,1,100000000),[1]!s_stmnote_bank_35(A4,$B$1,1,100000000))*100),"")) | CG4: =RANK(CF4,CF$5:CF$192,0)&" "&COUNTIF(CF$5:CF$192,">0") -> #VALUE! | CH4: =IFERROR(CF4/100/P4,"") | CI4: =RANK(CH4,CH$5:CH$192,0)&" "&COUNTIF(CH$5:CH$192,">0") -> #VALUE! | CJ4: =[1]!s_stmnote_bank_30(A4,$A$1,1) -> 0 | CM4: =CK4/(5/8*[1]!s_stmnote_bank_1n($A4,$A$1,1,100000000)+[1]!s_stmnote_bank_1n($A4,$B$1,1,100000000)*3/8) -> #DIV/0! | CO4: =CN4/(5/8*[1]!b_stm07_bs($A4,109,$A$1,1,100000000)+[1]!b_stm07_bs($A4,109,$B$1,1,100000000)*3/8) -> #DIV/0! | CP4: =[1]!b_stm07_bs($A4,141,$A$1,1,100000000) -> 0 | CQ4: =[1]!b_stm07_bs($A4,141,$D$1,1,100000000) -> 0 | CR4: =IF([1]!s_fa_roic_yearly($A4,$A$1)=0,"",[1]!s_fa_roic_yearly($A4,$A$1)) | CS4: =RANK(CR4,CR$5:CR$192,1)&" "&COUNTIF(CR$5:CR$192,">0") -> #VALUE! | CT4: =IF([1]!s_fa_roic_yearly($A4,$D$1)=0,"",[1]!s_fa_roic_yearly($A4,$D$1)) | CU4: =RANK(CT4,CT$5:CT$192,1)&" "&COUNTIF(CT$5:CT$192,">0") -> #VALUE! | CV4: =[1]!s_stm07_bs(A4,"W14578191",$A$1,1,100000000) -> 0 | CW4: =[1]!s_stmnote_bank_682($A4,$A$1,1,2,100000000) -> 0 | CX4: =IF(CW4*CV4=0,"",CW4/CV4)
A5: 111885082.IB | B5: 大连农村商业银行股份有限公司 | C5: 大连农商行 | D5: 农商行 | F5: AA- | J5: =VLOOKUP(B5,[3]额度信息!$B:$T,19,0) -> #N/A | L5: =IFERROR(([1]!b_stm07_bs($A5,47,$A$1,1,100000000))/[1]!b_stm07_bs($A5,109,$A$1,1,100000000),"") -> 0.093121223 | O5: =RANK(N5,N$5:N$192,1)&" "&COUNTIF(N$5:N$192,">0") -> #N/A | P5: =IF(IFERROR(R5+AB5/100,"")=0,"",IFERROR(R5+AB5/100,"")) -> 0.0424 | Q5: =RANK(P5,P$5:P$192,1)&" "&COUNTIF(P$5:P$192,">0") -> 121 169 | R5: =IFERROR([1]!s_stmnote_bank($A5,"34",$A$1,100000000)/[1]!s_stmnote_bank_1n(A5,$A$1,1,100000000),"") -> 0 | Z5: =[1]!b_stm07_bs(A5,74,$A$1,1,100000000) -> 1280.9931 | AA5: =[1]!b_stm07_bs(A5,109,$A$1,1,100000000) -> 1131.2467 | AB5: =[1]!s_stmnote_bank_5n(A5,$A$1,1) -> 4.24 | AC5: =IF([1]!s_stmnote_bank_23n(A5,$A$1,1)=0,"",IFERROR([1]!s_stmnote_bank_23n(A5,$A$1,1),"")) | AD5: =RANK(AC5,AC$5:AC$192,1)&" "&COUNTIF(AC$5:AC$192,">0") -> #VALUE! | AE5: =[1]!s_stmnote_bank_capadequacyratio(A5,$A$1,1) -> 0 | AF5: =IF([1]!s_stmnote_bank_capadequacyratio_ct1(A5,$A$1,1)=0,"",IFERROR([1]!s_stmnote_bank_capadequacyratio_ct1(A5,$A$1,1),"")) | AG5: =RANK(AF5,AF$5:AF$192,1)&" "&COUNTIF(AF$5:AF$192,">0") -> #VALUE! | AH5: =IF(OR([1]!s_fa_roe(A5,20201231)=0,[1]!s_fa_roe(A5,20211231)="0",[1]!s_fa_roe(A5,20221231)="0"),"",IFERROR(([1]!s_fa_roe(A5,20221231)+[1]!s_fa_roe(A5,20201231)+[1]!s_fa_roe(A5,20211231))/3,"")) -> 0.6798 | AI5: =RANK(AH5,AH$5:AH$192,1)&" "&COUNTIF(AH$5:AH$192,">0") -> 4 173 | AJ5: =IFERROR(([1]!s_stmnote_bank_65(A5,$A$1,1,2,4,100000000)+[1]!s_stmnote_bank_65(A5,$A$1,1,2,6,100000000))/[1]!s_stmnote_bank_1n(A5,$A$1,1,100000000),"") -> 0.23258203 | AK5: =IFERROR([1]!s_stmnote_bank_614(A5,$A$1,1,2,100000000)/[1]!s_stmnote_bank_647(A5,$A$1,1,2,100000000),"") -> 0 | AL5: =IFERROR(([1]!b_stm07_bs(A5,104,$A$1,1,100000000)+[1]!b_stm07_bs(A5,106,$A$1,1,100000000)+[1]!b_stm07_bs(A5,76,$A$1,1,100000000)+[1]!b_stm07_bs(A5,108,$A$1,1,100000000)+[1]!b_stm07_bs(A5,95,$A$1,1,100000000))/[1]!b_stm07_bs(A5,128,$A$1,1,100000000),"") -> 0.037966512 | AM5: =IFERROR(([1]!s_stmnote_bank_614(A5,$A$1,1,2,100000000)+[1]!b_stm07_bs(A5,104,$A$1,1,100000000)+[1]!b_stm07_bs(A5,106,$A$1,1,100000000)+[1]!b_stm07_bs(A5,76,$A$1,1,100000000)+[1]!b_stm07_bs(A5,108,$A$1,1,100000000)+[1]!b_stm07_bs(A5,95,$A$1,1,100000000))/[1]!b_stm07_bs(A5,128,$A$1,1,100000000),"") -> 0.037966512 | AN5: =IF(Z5>#REF!,#REF!,IF(Z5>#REF!,#REF!,IF(Z5>#REF!,#REF!,IF(Z5>#REF!,#REF!,IF(Z5>#REF!,#REF!,IF(Z5>#REF!,#REF!,IF(Z5>#REF!,#REF!,#REF!))))))) -> #REF! | AO5: =IF(AA5>#REF!,#REF!,IF(AA5>#REF!,#REF!,IF(AA5>#REF!,#REF!,IF(AA5>#REF!,#REF!,IF(AA5>#REF!,#REF!,IF(AA5>#REF!,#REF!,IF(AA5>#REF!,#REF!,#REF!))))))) -> #REF! | AP5: =IF(AB5<#REF!,#REF!,IF(AB5<#REF!,#REF!,IF(AB5<#REF!,#REF!,IF(AB5<#REF!,#REF!,IF(AB5<#REF!,#REF!,IF(AB5<#REF!,#REF!,#REF!)))))) -> #REF! | AQ5: =IF(AC5>#REF!,#REF!,IF(AC5>#REF!,#REF!,IF(AC5>#REF!,#REF!,IF(AC5>#REF!,#REF!,#REF!)))) -> #REF! | AR5: =IF(AE5>#REF!,#REF!,IF(AE5>#REF!,#REF!,IF(AE5>#REF!,#REF!,IF(AE5>#REF!,#REF!,#REF!)))) -> #REF! | AS5: =IF(AF5>#REF!,#REF!,IF(AF5>#REF!,#REF!,IF(AF5>#REF!,#REF!,IF(AF5>#REF!,#REF!,#REF!)))) -> #REF! | AT5: =IF(AH5>#REF!,#REF!,IF(AH5>#REF!,#REF!,IF(AH5>#REF!,#REF!,IF(AH5>#REF!,#REF!,IF(AH5>#REF!,#REF!,#REF!))))) -> #REF! | AU5: =AN5*$AN$3+AP5*$AP$3+AQ5*$AQ$3+AR5*$AR$3+AS5*$AS$3+AT5*$AT$3+$AO$3*AO5 -> #REF! | AY5: =IFERROR(VLOOKUP(AV5,#REF!,3,0),"") | AZ5: =IFERROR(VLOOKUP(AW5,#REF!,3,0),"") | BA5: =IFERROR(VLOOKUP(AX5,#REF!,3,0),"") | BB5: =IFERROR(AY5*#REF!+AZ5*#REF!+BA5*#REF!,"") | BC5: =IFERROR(AU5*0.6+BB5*0.4,"") | BD5: =IFERROR(VLOOKUP(BC5*10,#REF!,2,1),"") | BH5: 大连德泰控股有限公司 | BI5: 10 | BJ5: 辽宁 | BK5: 大连市 | BL5: =IF([1]!s_stmnote_bank_17n(A5,$A$1,1)="0","",[1]!s_stmnote_bank_17n(A5,$A$1,1)) -> 0 | BM5: =IF([1]!s_stmnote_bank_18n(A5,$A$1,1)="0","",[1]!s_stmnote_bank_18n(A5,$A$1,1)) -> 0 | BP5: =[1]!s_stmnote_bank_5444(A5,$A$1,1) -> 0 | BQ5: =[1]!s_stmnote_bank_129n($A5,$A$1,1) -> 60.6565 | BR5: =IFERROR(BS5/SUMPRODUCT(BT5:BX5,$BT$4:$BX$4)*SUMIFS($BT$4:$BX$4,BT5:BX5,">0")*100,0) -> 4.3579095 | BS5: =[1]!b_stm07_is(A5,19,$A$1,1,100000000) -> 49.784056 | BT5: =[1]!s_stm07_bs(A5,"W15273164",$A$1,1,100000000)-[1]!s_stm07_bs(A5,"W17642530",$A$1,1,100000000)-[1]!s_stm07_bs(A5,"W15910877",$A$1,1,100000000)-[1]!s_stm07_bs_39(A5,$A$1,1,100000000)-[1]!s_stm07_bs(A5,"W17700468",$A$1,1,100000000)-[1]!s_stm07_bs(A5,"W16504296",$A$1,1,100000000)-[1]!s_stm07_bs(A5,"W13769069",$A$1,1,100000000) -> 1207.8577 | BU5: =[1]!s_stm07_bs(A5,"W15273164",$B$1,1,100000000)-[1]!s_stm07_bs(A5,"W17642530",$B$1,1,100000000)-[1]!s_stm07_bs(A5,"W15910877",$B$1,1,100000000)-[1]!s_stm07_bs_39(A5,$B$1,1,100000000)-[1]!s_stm07_bs(A5,"W17700468",$B$1,1,100000000)-[1]!s_stm07_bs(A5,"W16504296",$B$1,1,100000000)-[1]!s_stm07_bs(A5,"W13769069",$B$1,1,100000000) -> 1114.455 | BV5: =[1]!s_stm07_bs(A5,"W15273164",$E$1,1,100000000)-[1]!s_stm07_bs(A5,"W17642530",$E$1,1,100000000)-[1]!s_stm07_bs(A5,"W15910877",$E$1,1,100000000)-[1]!s_stm07_bs_39(A5,$E$1,1,100000000)-[1]!s_stm07_bs(A5,"W17700468",$E$1,1,100000000)-[1]!s_stm07_bs(A5,"W16504296",$E$1,1,100000000)-[1]!s_stm07_bs(A5,"W13769069",$E$1,1,100000000) -> 1216.4244 | BW5: =[1]!s_stm07_bs(A5,"W15273164",$F$1,1,100000000)-[1]!s_stm07_bs(A5,"W17642530",$F$1,1,100000000)-[1]!s_stm07_bs(A5,"W15910877",$F$1,1,100000000)-[1]!s_stm07_bs_39(A5,$F$1,1,100000000)-[1]!s_stm07_bs(A5,"W17700468",$F$1,1,100000000)-[1]!s_stm07_bs(A5,"W16504296",$F$1,1,100000000)-[1]!s_stm07_bs(A5,"W13769069",$F$1,1,100000000) -> 1202.1681 | BX5: =[1]!s_stm07_bs(A5,"W15273164",$G$1,1,100000000)-[1]!s_stm07_bs(A5,"W17642530",$G$1,1,100000000)-[1]!s_stm07_bs(A5,"W15910877",$G$1,1,100000000)-[1]!s_stm07_bs_39(A5,$G$1,1,100000000)-[1]!s_stm07_bs(A5,"W17700468",$G$1,1,100000000)-[1]!s_stm07_bs(A5,"W16504296",$G$1,1,100000000)-[1]!s_stm07_bs(A5,"W13769069",$G$1,1,100000000) -> 1208.8324 | BY5: =IFERROR([1]!b_stm07_is(A5,20,$A$1,1,100000000)/AVERAGEIF(CA5:CE5,">0")*100,0) -> 3.0994077 | BZ5: =[1]!b_stm07_is(A5,20,$A$1,1,100000000) -> 35.461784 | CA5: =[1]!s_stmnote_bank_38(A5,$A$1,1,100000000) -> 1191.5108 | CB5: =[1]!s_stmnote_bank_38(A5,$B$1,1,100000000) -> 1049.9961 | CC5: =[1]!s_stmnote_bank_38(A5,$E$1,1,100000000) -> 1189.5793 | CD5: =[1]!s_stmnote_bank_38(A5,$F$1,1,100000000) -> 1176.328 | CE5: =[1]!s_stmnote_bank_38(A5,$G$1,1,100000000) -> 1113.3216 | CF5: =IF(BP5<>0,BP5,IFERROR(IF(([1]!b_stm07_is(A5,19,$A$1,1,100000000)-[1]!b_stm07_is(A5,20,$A$1,1,100000000))/AVERAGE([1]!s_stmnote_bank_35(A5,$A$1,1,100000000),[1]!s_stmnote_bank_35(A5,$B$1,1,100000000))*100=0,"",([1]!b_stm07_is(A5,19,$A$1,1,100000000)-[1]!b_stm07_is(A5,20,$A$1,1,100000000))/AVERAGE([1]!s_stmnote_bank_35(A5,$A$1,1,100000000),[1]!s_stmnote_bank_35(A5,$B$1,1,100000000))*100),"")) -> 1.284989 | CG5: =RANK(CF5,CF$5:CF$192,0)&" "&COUNTIF(CF$5:CF$192,">0") -> 162 171 | CH5: =IFERROR(CF5/100/P5,"") -> 0.30306343 | CI5: =RANK(CH5,CH$5:CH$192,0)&" "&COUNTIF(CH$5:CH$192,">0") -> 143 169 | CJ5: =[1]!s_stmnote_bank_30(A5,$A$1,1) -> 31.1487 | CP5: =[1]!b_stm07_bs($A5,141,$A$1,1,100000000) -> 82.638154 | CQ5: =[1]!b_stm07_bs($A5,141,$D$1,1,100000000) -> 85.94281 | CR5: =IF([1]!s_fa_roic_yearly($A5,$A$1)=0,"",[1]!s_fa_roic_yearly($A5,$A$1)) -> 0.7435 | CS5: =RANK(CR5,CR$5:CR$192,0)/COUNTIF(CR$5:CR$192,">0") -> 0.9704142 | CT5: =IF([1]!s_fa_roic_yearly($A5,$D$1)=0,"",[1]!s_fa_roic_yearly($A5,$D$1)) -> 1.4688 | CU5: =RANK(CT5,CT$5:CT$192,0)/COUNTIF(CT$5:CT$192,">0") -> 0.98591549 | CV5: =[1]!s_stm07_bs(A5,"W14578191",$A$1,1,100000000) -> 679.82747 | CW5: =[1]!s_stmnote_bank_682($A5,$A$1,1,2,100000000) -> 0 | CX5: =IF(CW5*CV5=0,"",CW5/CV5)
A6: 112392890.IB | B6: 法国巴黎银行(中国)有限公司 | C6: 法国巴黎银行(中国) | D6: 外资行 | E6: 有 | F6: AAA | H6: B+ | J6: =VLOOKUP(B6,[3]额度信息!$B:$T,19,0) -> #N/A | K6: 业务以中间业务为主，获得母行法巴较多资源支持，客户也以集团为主，协同性很强；信贷业务占比小、服务集团关联客户为主，风险暴露少；盈利虽然偏低，但资本、流动性安全垫很高;高度依赖同业资金，降2级；集团支持提1级 | L6: =IFERROR(([1]!b_stm07_bs($A6,47,$A$1,1,100000000))/[1]!b_stm07_bs($A6,109,$A$1,1,100000000),"") -> 0.19592606 | O6: =RANK(N6,N$5:N$192,1)&" "&COUNTIF(N$5:N$192,">0") -> #N/A | P6: =IF(IFERROR(R6+AB6/100,"")=0,"",IFERROR(R6+AB6/100,"")) -> 0.0052975703 | Q6: =RANK(P6,P$5:P$192,1)&" "&COUNTIF(P$5:P$192,">0") -> 1 169 | R6: =IFERROR([1]!s_stmnote_bank($A6,"34",$A$1,100000000)/[1]!s_stmnote_bank_1n(A6,$A$1,1,100000000),"") -> 0.0023975703 | Z6: =[1]!b_stm07_bs(A6,74,$A$1,1,100000000) -> 645.1722 | AA6: =[1]!b_stm07_bs(A6,109,$A$1,1,100000000) -> 266.42332 | AB6: =[1]!s_stmnote_bank_5n(A6,$A$1,1) -> 0.29 | AC6: =IF([1]!s_stmnote_bank_23n(A6,$A$1,1)=0,"",IFERROR([1]!s_stmnote_bank_23n(A6,$A$1,1),"")) -> 1076.23 | AD6: =RANK(AC6,AC$5:AC$192,1)&" "&COUNTIF(AC$5:AC$192,">0") -> 166 167 | AE6: =[1]!s_stmnote_bank_capadequacyratio(A6,$A$1,1) -> 16.6 | AF6: =IF([1]!s_stmnote_bank_capadequacyratio_ct1(A6,$A$1,1)=0,"",IFERROR([1]!s_stmnote_bank_capadequacyratio_ct1(A6,$A$1,1),"")) -> 16 | AG6: =RANK(AF6,AF$5:AF$192,1)&" "&COUNTIF(AF$5:AF$192,">0") -> 159 167 | AH6: =IF(OR([1]!s_fa_roe(A6,20201231)=0,[1]!s_fa_roe(A6,20211231)="0",[1]!s_fa_roe(A6,20221231)="0"),"",IFERROR(([1]!s_fa_roe(A6,20221231)+[1]!s_fa_roe(A6,20201231)+[1]!s_fa_roe(A6,20211231))/3,"")) -> 2.9750667 | AI6: =RANK(AH6,AH$5:AH$192,1)&" "&COUNTIF(AH$5:AH$192,">0") -> 17 173 | AJ6: =IFERROR(([1]!s_stmnote_bank_65(A6,$A$1,1,2,4,100000000)+[1]!s_stmnote_bank_65(A6,$A$1,1,2,6,100000000))/[1]!s_stmnote_bank_1n(A6,$A$1,1,100000000),"") -> 0.039835042 | AK6: =IFERROR([1]!s_stmnote_bank_614(A6,$A$1,1,2,100000000)/[1]!s_stmnote_bank_647(A6,$A$1,1,2,100000000),"") -> 0.3717991 | AL6: =IFERROR(([1]!b_stm07_bs(A6,104,$A$1,1,100000000)+[1]!b_stm07_bs(A6,106,$A$1,1,100000000)+[1]!b_stm07_bs(A6,76,$A$1,1,100000000)+[1]!b_stm07_bs(A6,108,$A$1,1,100000000)+[1]!b_stm07_bs(A6,95,$A$1,1,100000000))/[1]!b_stm07_bs(A6,128,$A$1,1,100000000),"") -> 0.3048583 | AM6: =IFERROR(([1]!s_stmnote_bank_614(A6,$A$1,1,2,100000000)+[1]!b_stm07_bs(A6,104,$A$1,1,100000000)+[1]!b_stm07_bs(A6,106,$A$1,1,100000000)+[1]!b_stm07_bs(A6,76,$A$1,1,100000000)+[1]!b_stm07_bs(A6,108,$A$1,1,100000000)+[1]!b_stm07_bs(A6,95,$A$1,1,100000000))/[1]!b_stm07_bs(A6,128,$A$1,1,100000000),"") -> 0.48807651 | AN6: =IF(Z6>#REF!,#REF!,IF(Z6>#REF!,#REF!,IF(Z6>#REF!,#REF!,IF(Z6>#REF!,#REF!,IF(Z6>#REF!,#REF!,IF(Z6>#REF!,#REF!,IF(Z6>#REF!,#REF!,#REF!))))))) -> #REF! | AO6: =IF(AA6>#REF!,#REF!,IF(AA6>#REF!,#REF!,IF(AA6>#REF!,#REF!,IF(AA6>#REF!,#REF!,IF(AA6>#REF!,#REF!,IF(AA6>#REF!,#REF!,IF(AA6>#REF!,#REF!,#REF!))))))) -> #REF! | AP6: =IF(AB6<#REF!,#REF!,IF(AB6<#REF!,#REF!,IF(AB6<#REF!,#REF!,IF(AB6<#REF!,#REF!,IF(AB6<#REF!,#REF!,IF(AB6<#REF!,#REF!,#REF!)))))) -> #REF! | AQ6: =IF(AC6>#REF!,#REF!,IF(AC6>#REF!,#REF!,IF(AC6>#REF!,#REF!,IF(AC6>#REF!,#REF!,#REF!)))) -> #REF! | AR6: =IF(AE6>#REF!,#REF!,IF(AE6>#REF!,#REF!,IF(AE6>#REF!,#REF!,IF(AE6>#REF!,#REF!,#REF!)))) -> #REF! | AS6: =IF(AF6>#REF!,#REF!,IF(AF6>#REF!,#REF!,IF(AF6>#REF!,#REF!,IF(AF6>#REF!,#REF!,#REF!)))) -> #REF! | AT6: =IF(AH6>#REF!,#REF!,IF(AH6>#REF!,#REF!,IF(AH6>#REF!,#REF!,IF(AH6>#REF!,#REF!,IF(AH6>#REF!,#REF!,#REF!))))) -> #REF! | AU6: =AN6*$AN$3+AP6*$AP$3+AQ6*$AQ$3+AR6*$AR$3+AS6*$AS$3+AT6*$AT$3+$AO$3*AO6 -> #REF! | AV6: 强 | AW6: 低 | AX6: 好 | AY6: =IFERROR(VLOOKUP(AV6,#REF!,3,0),"") | AZ6: =IFERROR(VLOOKUP(AW6,#REF!,3,0),"") | BA6: =IFERROR(VLOOKUP(AX6,#REF!,3,0),"") | BB6: =IFERROR(AY6*#REF!+AZ6*#REF!+BA6*#REF!,"") | BC6: =IFERROR(AU6*0.6+BB6*0.4,"") | BD6: =IFERROR(VLOOKUP(BC6*10,#REF!,2,1),"") | BE6: 2 | BF6: -1 | BG6: 负债不稳-1 | BL6: =IF([1]!s_stmnote_bank_17n(A6,$A$1,1)="0","",[1]!s_stmnote_bank_17n(A6,$A$1,1)) -> 0 | BM6: =IF([1]!s_stmnote_bank_18n(A6,$A$1,1)="0","",[1]!s_stmnote_bank_18n(A6,$A$1,1)) -> 0 | BP6: =[1]!s_stmnote_bank_5444(A6,$A$1,1) -> 0 | BQ6: =[1]!s_stmnote_bank_129n($A6,$A$1,1) -> 78.8717 | BR6: =IFERROR(BS6/SUMPRODUCT(BT6:BX6,$BT$4:$BX$4)*SUMIFS($BT$4:$BX$4,BT6:BX6,">0")*100,0) -> 1.9205411 | BS6: =[1]!b_stm07_is(A6,19,$A$1,1,100000000) -> 13.085051 | BT6: =[1]!s_stm07_bs(A6,"W15273164",$A$1,1,100000000)-[1]!s_stm07_bs(A6,"W17642530",$A$1,1,100000000)-[1]!s_stm07_bs(A6,"W15910877",$A$1,1,100000000)-[1]!s_stm07_bs_39(A6,$A$1,1,100000000)-[1]!s_stm07_bs(A6,"W17700468",$A$1,1,100000000)-[1]!s_stm07_bs(A6,"W16504296",$A$1,1,100000000)-[1]!s_stm07_bs(A6,"W13769069",$A$1,1,100000000) -> 620.62995 | BU6: =[1]!s_stm07_bs(A6,"W15273164",$B$1,1,100000000)-[1]!s_stm07_bs(A6,"W17642530",$B$1,1,100000000)-[1]!s_stm07_bs(A6,"W15910877",$B$1,1,100000000)-[1]!s_stm07_bs_39(A6,$B$1,1,100000000)-[1]!s_stm07_bs(A6,"W17700468",$B$1,1,100000000)-[1]!s_stm07_bs(A6,"W16504296",$B$1,1,100000000)-[1]!s_stm07_bs(A6,"W13769069",$B$1,1,100000000) -> 691.46867 | BV6: =[1]!s_stm07_bs(A6,"W15273164",$E$1,1,100000000)-[1]!s_stm07_bs(A6,"W17642530",$E$1,1,100000000)-[1]!s_stm07_bs(A6,"W15910877",$E$1,1,100000000)-[1]!s_stm07_bs_39(A6,$E$1,1,100000000)-[1]!s_stm07_bs(A6,"W17700468",$E$1,1,100000000)-[1]!s_stm07_bs(A6,"W16504296",$E$1,1,100000000)-[1]!s_stm07_bs(A6,"W13769069",$E$1,1,100000000) -> 660.6366 | BW6: =[1]!s_stm07_bs(A6,"W15273164",$F$1,1,100000000)-[1]!s_stm07_bs(A6,"W17642530",$F$1,1,100000000)-[1]!s_stm07_bs(A6,"W15910877",$F$1,1,100000000)-[1]!s_stm07_bs_39(A6,$F$1,1,100000000)-[1]!s_stm07_bs(A6,"W17700468",$F$1,1,100000000)-[1]!s_stm07_bs(A6,"W16504296",$F$1,1,100000000)-[1]!s_stm07_bs(A6,"W13769069",$F$1,1,100000000) -> 0 | BX6: =[1]!s_stm07_bs(A6,"W15273164",$G$1,1,100000000)-[1]!s_stm07_bs(A6,"W17642530",$G$1,1,100000000)-[1]!s_stm07_bs(A6,"W15910877",$G$1,1,100000000)-[1]!s_stm07_bs_39(A6,$G$1,1,100000000)-[1]!s_stm07_bs(A6,"W17700468",$G$1,1,100000000)-[1]!s_stm07_bs(A6,"W16504296",$G$1,1,100000000)-[1]!s_stm07_bs(A6,"W13769069",$G$1,1,100000000) -> 0 | BY6: =IFERROR([1]!b_stm07_is(A6,20,$A$1,1,100000000)/AVERAGEIF(CA6:CE6,">0")*100,0) -> 1.8172822 | BZ6: =[1]!b_stm07_is(A6,20,$A$1,1,100000000) -> 7.8186414 | CA6: =[1]!s_stmnote_bank_38(A6,$A$1,1,100000000) -> 431.24335 | CB6: =[1]!s_stmnote_bank_38(A6,$B$1,1,100000000) -> 429.23295 | CC6: =[1]!s_stmnote_bank_38(A6,$E$1,1,100000000) -> 0 | CD6: =[1]!s_stmnote_bank_38(A6,$F$1,1,100000000) -> 0 | CE6: =[1]!s_stmnote_bank_38(A6,$G$1,1,100000000) -> 0 | CF6: =IF(BP6<>0,BP6,IFERROR(IF(([1]!b_stm07_is(A6,19,$A$1,1,100000000)-[1]!b_stm07_is(A6,20,$A$1,1,100000000))/AVERAGE([1]!s_stmnote_bank_35(A6,$A$1,1,100000000),[1]!s_stmnote_bank_35(A6,$B$1,1,100000000))*100=0,"",([1]!b_stm07_is(A6,19,$A$1,1,100000000)-[1]!b_stm07_is(A6,20,$A$1,1,100000000))/AVERAGE([1]!s_stmnote_bank_35(A6,$A$1,1,100000000),[1]!s_stmnote_bank_35(A6,$B$1,1,100000000))*100),"")) -> 1.0146216 | CG6: =RANK(CF6,CF$5:CF$192,0)&" "&COUNTIF(CF$5:CF$192,">0") -> 169 171 | CH6: =IFERROR(CF6/100/P6,"") -> 1.9152584 | CI6: =RANK(CH6,CH$5:CH$192,0)&" "&COUNTIF(CH$5:CH$192,">0") -> 12 169 | CJ6: =[1]!s_stmnote_bank_30(A6,$A$1,1) -> 52.3122 | CP6: =[1]!b_stm07_bs($A6,141,$A$1,1,100000000) -> 104.52749 | CQ6: =[1]!b_stm07_bs($A6,141,$D$1,1,100000000) -> 108.7685 | CR6: =IF([1]!s_fa_roic_yearly($A6,$A$1)=0,"",[1]!s_fa_roic_yearly($A6,$A$1)) -> 2.159 | CS6: =RANK(CR6,CR$5:CR$192,0)/COUNTIF(CR$5:CR$192,">0") -> 0.9408284 | CT6: =IF([1]!s_fa_roic_yearly($A6,$D$1)=0,"",[1]!s_fa_roic_yearly($A6,$D$1)) -> 8.1698 | CU6: =RANK(CT6,CT$5:CT$192,0)/COUNTIF(CT$5:CT$192,">0") -> 0.6971831 | CV6: =[1]!s_stm07_bs(A6,"W14578191",$A$1,1,100000000) -> 139.17603 | CW6: =[1]!s_stmnote_bank_682($A6,$A$1,1,2,100000000) -> 0 | CX6: =IF(CW6*CV6=0,"",CW6/CV6)
A7: 112188604.IB | B7: 德意志银行(中国)有限公司 | C7: 德意志银行(中国) | D7: 外资行 | F7: AAA | H7: BB | J7: =VLOOKUP(B7,[3]额度信息!$B:$T,19,0) -> #N/A | L7: =IFERROR(([1]!b_stm07_bs($A7,47,$A$1,1,100000000))/[1]!b_stm07_bs($A7,109,$A$1,1,100000000),"") -> 0.16382361 | O7: =RANK(N7,N$5:N$192,1)&" "&COUNTIF(N$5:N$192,">0") -> #N/A | P7: =IF(IFERROR(R7+AB7/100,"")=0,"",IFERROR(R7+AB7/100,"")) -> 0.037279924 | Q7: =RANK(P7,P$5:P$192,1)&" "&COUNTIF(P$5:P$192,">0") -> 102 169 | R7: =IFERROR([1]!s_stmnote_bank($A7,"34",$A$1,100000000)/[1]!s_stmnote_bank_1n(A7,$A$1,1,100000000),"") -> 0.036579924 | Z7: =[1]!b_stm07_bs(A7,74,$A$1,1,100000000) -> 740.05471 | AA7: =[1]!b_stm07_bs(A7,109,$A$1,1,100000000) -> 422.25867 | AB7: =[1]!s_stmnote_bank_5n(A7,$A$1,1) -> 0.07 | AC7: =IF([1]!s_stmnote_bank_23n(A7,$A$1,1)=0,"",IFERROR([1]!s_stmnote_bank_23n(A7,$A$1,1),"")) -> 3356 | AD7: =RANK(AC7,AC$5:AC$192,1)&" "&COUNTIF(AC$5:AC$192,">0") -> 167 167 | AE7: =[1]!s_stmnote_bank_capadequacyratio(A7,$A$1,1) -> 17.27 | AF7: =IF([1]!s_stmnote_bank_capadequacyratio_ct1(A7,$A$1,1)=0,"",IFERROR([1]!s_stmnote_bank_capadequacyratio_ct1(A7,$A$1,1),"")) -> 16.53 | AG7: =RANK(AF7,AF$5:AF$192,1)&" "&COUNTIF(AF$5:AF$192,">0") -> 161 167 | AH7: =IF(OR([1]!s_fa_roe(A7,20201231)=0,[1]!s_fa_roe(A7,20211231)="0",[1]!s_fa_roe(A7,20221231)="0"),"",IFERROR(([1]!s_fa_roe(A7,20221231)+[1]!s_fa_roe(A7,20201231)+[1]!s_fa_roe(A7,20211231))/3,"")) -> 4.5847667 | AI7: =RANK(AH7,AH$5:AH$192,1)&" "&COUNTIF(AH$5:AH$192,">0") -> 32 173 | AJ7: =IFERROR(([1]!s_stmnote_bank_65(A7,$A$1,1,2,4,100000000)+[1]!s_stmnote_bank_65(A7,$A$1,1,2,6,100000000))/[1]!s_stmnote_bank_1n(A7,$A$1,1,100000000),"") -> 0.036066908 | AK7: =IFERROR([1]!s_stmnote_bank_614(A7,$A$1,1,2,100000000)/[1]!s_stmnote_bank_647(A7,$A$1,1,2,100000000),"") -> 0.46185558 | AL7: =IFERROR(([1]!b_stm07_bs(A7,104,$A$1,1,100000000)+[1]!b_stm07_bs(A7,106,$A$1,1,100000000)+[1]!b_stm07_bs(A7,76,$A$1,1,100000000)+[1]!b_stm07_bs(A7,108,$A$1,1,100000000)+[1]!b_stm07_bs(A7,95,$A$1,1,100000000))/[1]!b_stm07_bs(A7,128,$A$1,1,100000000),"") -> 0.23599443 | AM7: =IFERROR(([1]!s_stmnote_bank_614(A7,$A$1,1,2,100000000)+[1]!b_stm07_bs(A7,104,$A$1,1,100000000)+[1]!b_stm07_bs(A7,106,$A$1,1,100000000)+[1]!b_stm07_bs(A7,76,$A$1,1,100000000)+[1]!b_stm07_bs(A7,108,$A$1,1,100000000)+[1]!b_stm07_bs(A7,95,$A$1,1,100000000))/[1]!b_stm07_bs(A7,128,$A$1,1,100000000),"") -> 0.53851935 | AN7: =IF(Z7>#REF!,#REF!,IF(Z7>#REF!,#REF!,IF(Z7>#REF!,#REF!,IF(Z7>#REF!,#REF!,IF(Z7>#REF!,#REF!,IF(Z7>#REF!,#REF!,IF(Z7>#REF!,#REF!,#REF!))))))) -> #REF! | AO7: =IF(AA7>#REF!,#REF!,IF(AA7>#REF!,#REF!,IF(AA7>#REF!,#REF!,IF(AA7>#REF!,#REF!,IF(AA7>#REF!,#REF!,IF(AA7>#REF!,#REF!,IF(AA7>#REF!,#REF!,#REF!))))))) -> #REF! | AP7: =IF(AB7<#REF!,#REF!,IF(AB7<#REF!,#REF!,IF(AB7<#REF!,#REF!,IF(AB7<#REF!,#REF!,IF(AB7<#REF!,#REF!,IF(AB7<#REF!,#REF!,#REF!)))))) -> #REF! | AQ7: =IF(AC7>#REF!,#REF!,IF(AC7>#REF!,#REF!,IF(AC7>#REF!,#REF!,IF(AC7>#REF!,#REF!,#REF!)))) -> #REF! | AR7: =IF(AE7>#REF!,#REF!,IF(AE7>#REF!,#REF!,IF(AE7>#REF!,#REF!,IF(AE7>#REF!,#REF!,#REF!)))) -> #REF! | AS7: =IF(AF7>#REF!,#REF!,IF(AF7>#REF!,#REF!,IF(AF7>#REF!,#REF!,IF(AF7>#REF!,#REF!,#REF!)))) -> #REF! | AT7: =IF(AH7>#REF!,#REF!,IF(AH7>#REF!,#REF!,IF(AH7>#REF!,#REF!,IF(AH7>#REF!,#REF!,IF(AH7>#REF!,#REF!,#REF!))))) -> #REF! | AU7: =AN7*$AN$3+AP7*$AP$3+AQ7*$AQ$3+AR7*$AR$3+AS7*$AS$3+AT7*$AT$3+$AO$3*AO7 -> #REF! | AV7: 中 | AW7: 较低 | AX7: 较差 | AY7: =IFERROR(VLOOKUP(AV7,#REF!,3,0),"") | AZ7: =IFERROR(VLOOKUP(AW7,#REF!,3,0),"") | BA7: =IFERROR(VLOOKUP(AX7,#REF!,3,0),"") | BB7: =IFERROR(AY7*#REF!+AZ7*#REF!+BA7*#REF!,"") | BC7: =IFERROR(AU7*0.6+BB7*0.4,"") | BD7: =IFERROR(VLOOKUP(BC7*10,#REF!,2,1),"") | BH7: 德意志银行股份有限公司 | BI7: 100 | BJ7: 全国 | BK7: - | BL7: =IF([1]!s_stmnote_bank_17n(A7,$A$1,1)="0","",[1]!s_stmnote_bank_17n(A7,$A$1,1)) -> 7.44 | BM7: =IF([1]!s_stmnote_bank_18n(A7,$A$1,1)="0","",[1]!s_stmnote_bank_18n(A7,$A$1,1)) -> 0 | BP7: =[1]!s_stmnote_bank_5444(A7,$A$1,1) -> 1.59 | BQ7: =[1]!s_stmnote_bank_129n($A7,$A$1,1) -> 55.83 | BR7: =IFERROR(BS7/SUMPRODUCT(BT7:BX7,$BT$4:$BX$4)*SUMIFS($BT$4:$BX$4,BT7:BX7,">0")*100,0) -> 2.0683127 | BS7: =[1]!b_stm07_is(A7,19,$A$1,1,100000000) -> 14.932406 | BT7: =[1]!s_stm07_bs(A7,"W15273164",$A$1,1,100000000)-[1]!s_stm07_bs(A7,"W17642530",$A$1,1,100000000)-[1]!s_stm07_bs(A7,"W15910877",$A$1,1,100000000)-[1]!s_stm07_bs_39(A7,$A$1,1,100000000)-[1]!s_stm07_bs(A7,"W17700468",$A$1,1,100000000)-[1]!s_stm07_bs(A7,"W16504296",$A$1,1,100000000)-[1]!s_stm07_bs(A7,"W13769069",$A$1,1,100000000) -> 729.67293 | BU7: =[1]!s_stm07_bs(A7,"W15273164",$B$1,1,100000000)-[1]!s_stm07_bs(A7,"W17642530",$B$1,1,100000000)-[1]!s_stm07_bs(A7,"W15910877",$B$1,1,100000000)-[1]!s_stm07_bs_39(A7,$B$1,1,100000000)-[1]!s_stm07_bs(A7,"W17700468",$B$1,1,100000000)-[1]!s_stm07_bs(A7,"W16504296",$B$1,1,100000000)-[1]!s_stm07_bs(A7,"W13769069",$B$1,1,100000000) -> 720.859 | BV7: =[1]!s_stm07_bs(A7,"W15273164",$E$1,1,100000000)-[1]!s_stm07_bs(A7,"W17642530",$E$1,1,100000000)-[1]!s_stm07_bs(A7,"W15910877",$E$1,1,100000000)-[1]!s_stm07_bs_39(A7,$E$1,1,100000000)-[1]!s_stm07_bs(A7,"W17700468",$E$1,1,100000000)-[1]!s_stm07_bs(A7,"W16504296",$E$1,1,100000000)-[1]!s_stm07_bs(A7,"W13769069",$E$1,1,100000000) -> 0 | BW7: =[1]!s_stm07_bs(A7,"W15273164",$F$1,1,100000000)-[1]!s_stm07_bs(A7,"W17642530",$F$1,1,100000000)-[1]!s_stm07_bs(A7,"W15910877",$F$1,1,100000000)-[1]!s_stm07_bs_39(A7,$F$1,1,100000000)-[1]!s_stm07_bs(A7,"W17700468",$F$1,1,100000000)-[1]!s_stm07_bs(A7,"W16504296",$F$1,1,100000000)-[1]!s_stm07_bs(A7,"W13769069",$F$1,1,100000000) -> 0 | BX7: =[1]!s_stm07_bs(A7,"W15273164",$G$1,1,100000000)-[1]!s_stm07_bs(A7,"W17642530",$G$1,1,100000000)-[1]!s_stm07_bs(A7,"W15910877",$G$1,1,100000000)-[1]!s_stm07_bs_39(A7,$G$1,1,100000000)-[1]!s_stm07_bs(A7,"W17700468",$G$1,1,100000000)-[1]!s_stm07_bs(A7,"W16504296",$G$1,1,100000000)-[1]!s_stm07_bs(A7,"W13769069",$G$1,1,100000000) -> 0 | BY7: =IFERROR([1]!b_stm07_is(A7,20,$A$1,1,100000000)/AVERAGEIF(CA7:CE7,">0")*100,0) -> 1.2158453 | BZ7: =[1]!b_stm07_is(A7,20,$A$1,1,100000000) -> 7.0313947 | CA7: =[1]!s_stmnote_bank_38(A7,$A$1,1,100000000) -> 574.39235 | CB7: =[1]!s_stmnote_bank_38(A7,$B$1,1,100000000) -> 582.23419 | CC7: =[1]!s_stmnote_bank_38(A7,$E$1,1,100000000) -> 0 | CD7: =[1]!s_stmnote_bank_38(A7,$F$1,1,100000000) -> 0 | CE7: =[1]!s_stmnote_bank_38(A7,$G$1,1,100000000) -> 0 | CF7: =IF(BP7<>0,BP7,IFERROR(IF(([1]!b_stm07_is(A7,19,$A$1,1,100000000)-[1]!b_stm07_is(A7,20,$A$1,1,100000000))/AVERAGE([1]!s_stmnote_bank_35(A7,$A$1,1,100000000),[1]!s_stmnote_bank_35(A7,$B$1,1,100000000))*100=0,"",([1]!b_stm07_is(A7,19,$A$1,1,100000000)-[1]!b_stm07_is(A7,20,$A$1,1,100000000))/AVERAGE([1]!s_stmnote_bank_35(A7,$A$1,1,100000000),[1]!s_stmnote_bank_35(A7,$B$1,1,100000000))*100),"")) -> 1.59 | CG7: =RANK(CF7,CF$5:CF$192,0)&" "&COUNTIF(CF$5:CF$192,">0") -> 148 171 | CH7: =IFERROR(CF7/100/P7,"") -> 0.42650301 | CI7: =RANK(CH7,CH$5:CH$192,0)&" "&COUNTIF(CH$5:CH$192,">0") -> 129 169 | CJ7: =[1]!s_stmnote_bank_30(A7,$A$1,1) -> 51.001 | CP7: =[1]!b_stm07_bs($A7,141,$A$1,1,100000000) -> 95.405262 | CQ7: =[1]!b_stm07_bs($A7,141,$D$1,1,100000000) -> 0 | CR7: =IF([1]!s_fa_roic_yearly($A7,$A$1)=0,"",[1]!s_fa_roic_yearly($A7,$A$1)) -> 5.6454 | CS7: =RANK(CR7,CR$5:CR$192,0)/COUNTIF(CR$5:CR$192,">0") -> 0.77514793 | CT7: =IF([1]!s_fa_roic_yearly($A7,$D$1)=0,"",[1]!s_fa_roic_yearly($A7,$D$1)) | CU7: =RANK(CT7,CT$5:CT$192,0)/COUNTIF(CT$5:CT$192,">0") -> #VALUE! | CV7: =[1]!s_stm07_bs(A7,"W14578191",$A$1,1,100000000) -> 173.03889 | CW7: =[1]!s_stmnote_bank_682($A7,$A$1,1,2,100000000) -> 0.23277252 | CX7: =IF(CW7*CV7=0,"",CW7/CV7) -> 0.0013452035
A8: 111980324.IB | B8: 浙江南浔农村商业银行股份有限公司 | C8: 浙江南浔农商行 | D8: 农商行 | F8: AA | H8: B+ | J8: =VLOOKUP(B8,[3]额度信息!$B:$T,19,0) -> #N/A | L8: =IFERROR(([1]!b_stm07_bs($A8,47,$A$1,1,100000000))/[1]!b_stm07_bs($A8,109,$A$1,1,100000000),"") -> 0.11263656 | O8: =RANK(N8,N$5:N$192,1)&" "&COUNTIF(N$5:N$192,">0") -> #N/A | P8: =IF(IFERROR(R8+AB8/100,"")=0,"",IFERROR(R8+AB8/100,"")) -> 0.020583451 | Q8: =RANK(P8,P$5:P$192,1)&" "&COUNTIF(P$5:P$192,">0") -> 41 169 | R8: =IFERROR([1]!s_stmnote_bank($A8,"34",$A$1,100000000)/[1]!s_stmnote_bank_1n(A8,$A$1,1,100000000),"") -> 0.015683451 | Z8: =[1]!b_stm07_bs(A8,74,$A$1,1,100000000) -> 666.67088 | AA8: =[1]!b_stm07_bs(A8,109,$A$1,1,100000000) -> 549.83248 | AB8: =[1]!s_stmnote_bank_5n(A8,$A$1,1) -> 0.49 | AC8: =IF([1]!s_stmnote_bank_23n(A8,$A$1,1)=0,"",IFERROR([1]!s_stmnote_bank_23n(A8,$A$1,1),"")) -> 611.6 | AD8: =RANK(AC8,AC$5:AC$192,1)&" "&COUNTIF(AC$5:AC$192,">0") -> 156 167 | AE8: =[1]!s_stmnote_bank_capadequacyratio(A8,$A$1,1) -> 14.47 | AF8: =IF([1]!s_stmnote_bank_capadequacyratio_ct1(A8,$A$1,1)=0,"",IFERROR([1]!s_stmnote_bank_capadequacyratio_ct1(A8,$A$1,1),"")) -> 11.72 | AG8: =RANK(AF8,AF$5:AF$192,1)&" "&COUNTIF(AF$5:AF$192,">0") -> 119 167 | AH8: =IF(OR([1]!s_fa_roe(A8,20201231)=0,[1]!s_fa_roe(A8,20211231)="0",[1]!s_fa_roe(A8,20221231)="0"),"",IFERROR(([1]!s_fa_roe(A8,20221231)+[1]!s_fa_roe(A8,20201231)+[1]!s_fa_roe(A8,20211231))/3,"")) -> 11.370233 | AI8: =RANK(AH8,AH$5:AH$192,1)&" "&COUNTIF(AH$5:AH$192,">0") -> 145 173 | AJ8: =IFERROR(([1]!s_stmnote_bank_65(A8,$A$1,1,2,4,100000000)+[1]!s_stmnote_bank_65(A8,$A$1,1,2,6,100000000))/[1]!s_stmnote_bank_1n(A8,$A$1,1,100000000),"") -> 0.070443653 | AK8: =IFERROR([1]!s_stmnote_bank_614(A8,$A$1,1,2,100000000)/[1]!s_stmnote_bank_647(A8,$A$1,1,2,100000000),"") -> 0.13907507 | AL8: =IFERROR(([1]!b_stm07_bs(A8,104,$A$1,1,100000000)+[1]!b_stm07_bs(A8,106,$A$1,1,100000000)+[1]!b_stm07_bs(A8,76,$A$1,1,100000000)+[1]!b_stm07_bs(A8,108,$A$1,1,100000000)+[1]!b_stm07_bs(A8,95,$A$1,1,100000000))/[1]!b_stm07_bs(A8,128,$A$1,1,100000000),"") -> 0.030782821 | AM8: =IFERROR(([1]!s_stmnote_bank_614(A8,$A$1,1,2,100000000)+[1]!b_stm07_bs(A8,104,$A$1,1,100000000)+[1]!b_stm07_bs(A8,106,$A$1,1,100000000)+[1]!b_stm07_bs(A8,76,$A$1,1,100000000)+[1]!b_stm07_bs(A8,108,$A$1,1,100000000)+[1]!b_stm07_bs(A8,95,$A$1,1,100000000))/[1]!b_stm07_bs(A8,128,$A$1,1,100000000),"") -> 0.1574488 | AN8: =IF(Z8>#REF!,#REF!,IF(Z8>#REF!,#REF!,IF(Z8>#REF!,#REF!,IF(Z8>#REF!,#REF!,IF(Z8>#REF!,#REF!,IF(Z8>#REF!,#REF!,IF(Z8>#REF!,#REF!,#REF!))))))) -> #REF! | AO8: =IF(AA8>#REF!,#REF!,IF(AA8>#REF!,#REF!,IF(AA8>#REF!,#REF!,IF(AA8>#REF!,#REF!,IF(AA8>#REF!,#REF!,IF(AA8>#REF!,#REF!,IF(AA8>#REF!,#REF!,#REF!))))))) -> #REF! | AP8: =IF(AB8<#REF!,#REF!,IF(AB8<#REF!,#REF!,IF(AB8<#REF!,#REF!,IF(AB8<#REF!,#REF!,IF(AB8<#REF!,#REF!,IF(AB8<#REF!,#REF!,#REF!)))))) -> #REF! | AQ8: =IF(AC8>#REF!,#REF!,IF(AC8>#REF!,#REF!,IF(AC8>#REF!,#REF!,IF(AC8>#REF!,#REF!,#REF!)))) -> #REF! | AR8: =IF(AE8>#REF!,#REF!,IF(AE8>#REF!,#REF!,IF(AE8>#REF!,#REF!,IF(AE8>#REF!,#REF!,#REF!)))) -> #REF! | AS8: =IF(AF8>#REF!,#REF!,IF(AF8>#REF!,#REF!,IF(AF8>#REF!,#REF!,IF(AF8>#REF!,#REF!,#REF!)))) -> #REF! | AT8: =IF(AH8>#REF!,#REF!,IF(AH8>#REF!,#REF!,IF(AH8>#REF!,#REF!,IF(AH8>#REF!,#REF!,IF(AH8>#REF!,#REF!,#REF!))))) -> #REF! | AU8: =AN8*$AN$3+AP8*$AP$3+AQ8*$AQ$3+AR8*$AR$3+AS8*$AS$3+AT8*$AT$3+$AO$3*AO8 -> #REF! | AY8: =IFERROR(VLOOKUP(AV8,#REF!,3,0),"") | AZ8: =IFERROR(VLOOKUP(AW8,#REF!,3,0),"") | BA8: =IFERROR(VLOOKUP(AX8,#REF!,3,0),"") | BB8: =IFERROR(AY8*#REF!+AZ8*#REF!+BA8*#REF!,"") | BC8: =IFERROR(AU8*0.6+BB8*0.4,"") | BD8: =IFERROR(VLOOKUP(BC8*10,#REF!,2,1),"") | BH8: 湖州适溪畜产品加工有限公司 | BI8: 5.04 | BJ8: 浙江 | BK8: 湖州市 | BL8: =IF([1]!s_stmnote_bank_17n(A8,$A$1,1)="0","",[1]!s_stmnote_bank_17n(A8,$A$1,1)) -> 0 | BM8: =IF([1]!s_stmnote_bank_18n(A8,$A$1,1)="0","",[1]!s_stmnote_bank_18n(A8,$A$1,1)) -> 0 | BP8: =[1]!s_stmnote_bank_5444(A8,$A$1,1) -> 0 | BQ8: =[1]!s_stmnote_bank_129n($A8,$A$1,1) -> 50.4776 | BR8: =IFERROR(BS8/SUMPRODUCT(BT8:BX8,$BT$4:$BX$4)*SUMIFS($BT$4:$BX$4,BT8:BX8,">0")*100,0) -> 5.5657097 | BS8: =[1]!b_stm07_is(A8,19,$A$1,1,100000000) -> 32.147015 | BT8: =[1]!s_stm07_bs(A8,"W15273164",$A$1,1,100000000)-[1]!s_stm07_bs(A8,"W17642530",$A$1,1,100000000)-[1]!s_stm07_bs(A8,"W15910877",$A$1,1,100000000)-[1]!s_stm07_bs_39(A8,$A$1,1,100000000)-[1]!s_stm07_bs(A8,"W17700468",$A$1,1,100000000)-[1]!s_stm07_bs(A8,"W16504296",$A$1,1,100000000)-[1]!s_stm07_bs(A8,"W13769069",$A$1,1,100000000) -> 657.09723 | BU8: =[1]!s_stm07_bs(A8,"W15273164",$B$1,1,100000000)-[1]!s_stm07_bs(A8,"W17642530",$B$1,1,100000000)-[1]!s_stm07_bs(A8,"W15910877",$B$1,1,100000000)-[1]!s_stm07_bs_39(A8,$B$1,1,100000000)-[1]!s_stm07_bs(A8,"W17700468",$B$1,1,100000000)-[1]!s_stm07_bs(A8,"W16504296",$B$1,1,100000000)-[1]!s_stm07_bs(A8,"W13769069",$B$1,1,100000000) -> 566.23247 | BV8: =[1]!s_stm07_bs(A8,"W15273164",$E$1,1,100000000)-[1]!s_stm07_bs(A8,"W17642530",$E$1,1,100000000)-[1]!s_stm07_bs(A8,"W15910877",$E$1,1,100000000)-[1]!s_stm07_bs_39(A8,$E$1,1,100000000)-[1]!s_stm07_bs(A8,"W17700468",$E$1,1,100000000)-[1]!s_stm07_bs(A8,"W16504296",$E$1,1,100000000)-[1]!s_stm07_bs(A8,"W13769069",$E$1,1,100000000) -> 0 | BW8: =[1]!s_stm07_bs(A8,"W15273164",$F$1,1,100000000)-[1]!s_stm07_bs(A8,"W17642530",$F$1,1,100000000)-[1]!s_stm07_bs(A8,"W15910877",$F$1,1,100000000)-[1]!s_stm07_bs_39(A8,$F$1,1,100000000)-[1]!s_stm07_bs(A8,"W17700468",$F$1,1,100000000)-[1]!s_stm07_bs(A8,"W16504296",$F$1,1,100000000)-[1]!s_stm07_bs(A8,"W13769069",$F$1,1,100000000) -> 0 | BX8: =[1]!s_stm07_bs(A8,"W15273164",$G$1,1,100000000)-[1]!s_stm07_bs(A8,"W17642530",$G$1,1,100000000)-[1]!s_stm07_bs(A8,"W15910877",$G$1,1,100000000)-[1]!s_stm07_bs_39(A8,$G$1,1,100000000)-[1]!s_stm07_bs(A8,"W17700468",$G$1,1,100000000)-[1]!s_stm07_bs(A8,"W16504296",$G$1,1,100000000)-[1]!s_stm07_bs(A8,"W13769069",$G$1,1,100000000) -> 0 | BY8: =IFERROR([1]!b_stm07_is(A8,20,$A$1,1,100000000)/AVERAGEIF(CA8:CE8,">0")*100,0) -> 2.3326533 | BZ8: =[1]!b_stm07_is(A8,20,$A$1,1,100000000) -> 12.878987 | CA8: =[1]!s_stmnote_bank_38(A8,$A$1,1,100000000) -> 599.61037 | CB8: =[1]!s_stmnote_bank_38(A8,$B$1,1,100000000) -> 504.6246 | CC8: =[1]!s_stmnote_bank_38(A8,$E$1,1,100000000) -> 0 | CD8: =[1]!s_stmnote_bank_38(A8,$F$1,1,100000000) -> 0 | CE8: =[1]!s_stmnote_bank_38(A8,$G$1,1,100000000) -> 0 | CF8: =IF(BP8<>0,BP8,IFERROR(IF(([1]!b_stm07_is(A8,19,$A$1,1,100000000)-[1]!b_stm07_is(A8,20,$A$1,1,100000000))/AVERAGE([1]!s_stmnote_bank_35(A8,$A$1,1,100000000),[1]!s_stmnote_bank_35(A8,$B$1,1,100000000))*100=0,"",([1]!b_stm07_is(A8,19,$A$1,1,100000000)-[1]!b_stm07_is(A8,20,$A$1,1,100000000))/AVERAGE([1]!s_stmnote_bank_35(A8,$A$1,1,100000000),[1]!s_stmnote_bank_35(A8,$B$1,1,100000000))*100),"")) -> 3.1967281 | CG8: =RANK(CF8,CF$5:CF$192,0)&" "&COUNTIF(CF$5:CF$192,">0") -> 7 171 | CH8: =IFERROR(CF8/100/P8,"") -> 1.5530574 | CI8: =RANK(CH8,CH$5:CH$192,0)&" "&COUNTIF(CH$5:CH$192,">0") -> 23 169 | CJ8: =[1]!s_stmnote_bank_30(A8,$A$1,1) -> 5.0215 | CP8: =[1]!b_stm07_bs($A8,141,$A$1,1,100000000) -> 62.972965 | CQ8: =[1]!b_stm07_bs($A8,141,$D$1,1,100000000) -> 0 | CR8: =IF([1]!s_fa_roic_yearly($A8,$A$1)=0,"",[1]!s_fa_roic_yearly($A8,$A$1)) -> 11.9556 | CS8: =RANK(CR8,CR$5:CR$192,0)/COUNTIF(CR$5:CR$192,">0") -> 0.17159763 | CT8: =IF([1]!s_fa_roic_yearly($A8,$D$1)=0,"",[1]!s_fa_roic_yearly($A8,$D$1)) -> 11.3666 | CU8: =RANK(CT8,CT$5:CT$192,0)/COUNTIF(CT$5:CT$192,">0") -> 0.32394366 | CV8: =[1]!s_stm07_bs(A8,"W14578191",$A$1,1,100000000) -> 451.34696 | CW8: =[1]!s_stmnote_bank_682($A8,$A$1,1,2,100000000) -> 305.03073 | CX8: =IF(CW8*CV8=0,"",CW8/CV8) -> 0.67582315
A9: 111890100 | B9: 星展银行(中国)有限公司 | C9: 星展银行(中国) | D9: 外资行 | E9: 有普通 | F9: AAA | H9: BB- | J9: =VLOOKUP(B9,[3]额度信息!$B:$T,19,0) -> #N/A | K9: 以服务集团客户及出口东南亚中小企业为主，与母行星展有较大协同，传统信贷为主，贷款投放谨慎，地产占比偏高，但多为母行客户且多为商业地产项目，有一定安全垫；流动性很强；考虑地产风险敞口，以及严重依赖同业资金，下调3级；集团支持提1级 | L9: =IFERROR(([1]!b_stm07_bs($A9,47,$A$1,1,100000000))/[1]!b_stm07_bs($A9,109,$A$1,1,100000000),"") -> 0.16584508 | O9: =RANK(N9,N$5:N$192,1)&" "&COUNTIF(N$5:N$192,">0") -> #N/A | P9: =IF(IFERROR(R9+AB9/100,"")=0,"",IFERROR(R9+AB9/100,"")) -> 0.010622583 | Q9: =RANK(P9,P$5:P$192,1)&" "&COUNTIF(P$5:P$192,">0") -> 6 169 | R9: =IFERROR([1]!s_stmnote_bank($A9,"34",$A$1,100000000)/[1]!s_stmnote_bank_1n(A9,$A$1,1,100000000),"") -> 0.0036225835 | Z9: =[1]!b_stm07_bs(A9,74,$A$1,1,100000000) -> 1399.3067 | AA9: =[1]!b_stm07_bs(A9,109,$A$1,1,100000000) -> 720.69074 | AB9: =[1]!s_stmnote_bank_5n(A9,$A$1,1) -> 0.7 | AC9: =IF([1]!s_stmnote_bank_23n(A9,$A$1,1)=0,"",IFERROR([1]!s_stmnote_bank_23n(A9,$A$1,1),"")) -> 282.7 | AD9: =RANK(AC9,AC$5:AC$192,1)&" "&COUNTIF(AC$5:AC$192,">0") -> 101 167 | AE9: =[1]!s_stmnote_bank_capadequacyratio(A9,$A$1,1) -> 15.3 | AF9: =IF([1]!s_stmnote_bank_capadequacyratio_ct1(A9,$A$1,1)=0,"",IFERROR([1]!s_stmnote_bank_capadequacyratio_ct1(A9,$A$1,1),"")) -> 12.7 | AG9: =RANK(AF9,AF$5:AF$192,1)&" "&COUNTIF(AF$5:AF$192,">0") -> 134 167 | AH9: =IF(OR([1]!s_fa_roe(A9,20201231)=0,[1]!s_fa_roe(A9,20211231)="0",[1]!s_fa_roe(A9,20221231)="0"),"",IFERROR(([1]!s_fa_roe(A9,20221231)+[1]!s_fa_roe(A9,20201231)+[1]!s_fa_roe(A9,20211231))/3,"")) -> 4.2466667 | AI9: =RANK(AH9,AH$5:AH$192,1)&" "&COUNTIF(AH$5:AH$192,">0") -> 25 173 | AJ9: =IFERROR(([1]!s_stmnote_bank_65(A9,$A$1,1,2,4,100000000)+[1]!s_stmnote_bank_65(A9,$A$1,1,2,6,100000000))/[1]!s_stmnote_bank_1n(A9,$A$1,1,100000000),"") -> 0.16474998 | AK9: =IFERROR([1]!s_stmnote_bank_614(A9,$A$1,1,2,100000000)/[1]!s_stmnote_bank_647(A9,$A$1,1,2,100000000),"") -> 0.21516199 | AL9: =IFERROR(([1]!b_stm07_bs(A9,104,$A$1,1,100000000)+[1]!b_stm07_bs(A9,106,$A$1,1,100000000)+[1]!b_stm07_bs(A9,76,$A$1,1,100000000)+[1]!b_stm07_bs(A9,108,$A$1,1,100000000)+[1]!b_stm07_bs(A9,95,$A$1,1,100000000))/[1]!b_stm07_bs(A9,128,$A$1,1,100000000),"") -> 0.35691044 | AM9: =IFERROR(([1]!s_stmnote_bank_614(A9,$A$1,1,2,100000000)+[1]!b_stm07_bs(A9,104,$A$1,1,100000000)+[1]!b_stm07_bs(A9,106,$A$1,1,100000000)+[1]!b_stm07_bs(A9,76,$A$1,1,100000000)+[1]!b_stm07_bs(A9,108,$A$1,1,100000000)+[1]!b_stm07_bs(A9,95,$A$1,1,100000000))/[1]!b_stm07_bs(A9,128,$A$1,1,100000000),"") -> 0.47884747 | AN9: =IF(Z9>#REF!,#REF!,IF(Z9>#REF!,#REF!,IF(Z9>#REF!,#REF!,IF(Z9>#REF!,#REF!,IF(Z9>#REF!,#REF!,IF(Z9>#REF!,#REF!,IF(Z9>#REF!,#REF!,#REF!))))))) -> #REF! | AO9: =IF(AA9>#REF!,#REF!,IF(AA9>#REF!,#REF!,IF(AA9>#REF!,#REF!,IF(AA9>#REF!,#REF!,IF(AA9>#REF!,#REF!,IF(AA9>#REF!,#REF!,IF(AA9>#REF!,#REF!,#REF!))))))) -> #REF! | AP9: =IF(AB9<#REF!,#REF!,IF(AB9<#REF!,#REF!,IF(AB9<#REF!,#REF!,IF(AB9<#REF!,#REF!,IF(AB9<#REF!,#REF!,IF(AB9<#REF!,#REF!,#REF!)))))) -> #REF! | AQ9: =IF(AC9>#REF!,#REF!,IF(AC9>#REF!,#REF!,IF(AC9>#REF!,#REF!,IF(AC9>#REF!,#REF!,#REF!)))) -> #REF! | AR9: =IF(AE9>#REF!,#REF!,IF(AE9>#REF!,#REF!,IF(AE9>#REF!,#REF!,IF(AE9>#REF!,#REF!,#REF!)))) -> #REF! | AS9: =IF(AF9>#REF!,#REF!,IF(AF9>#REF!,#REF!,IF(AF9>#REF!,#REF!,IF(AF9>#REF!,#REF!,#REF!)))) -> #REF! | AT9: =IF(AH9>#REF!,#REF!,IF(AH9>#REF!,#REF!,IF(AH9>#REF!,#REF!,IF(AH9>#REF!,#REF!,IF(AH9>#REF!,#REF!,#REF!))))) -> #REF! | AU9: =AN9*$AN$3+AP9*$AP$3+AQ9*$AQ$3+AR9*$AR$3+AS9*$AS$3+AT9*$AT$3+$AO$3*AO9 -> #REF! | AV9: 强 | AW9: 较低 | AX9: 好 | AY9: =IFERROR(VLOOKUP(AV9,#REF!,3,0),"") | AZ9: =IFERROR(VLOOKUP(AW9,#REF!,3,0),"") | BA9: =IFERROR(VLOOKUP(AX9,#REF!,3,0),"") | BB9: =IFERROR(AY9*#REF!+AZ9*#REF!+BA9*#REF!,"") | BC9: =IFERROR(AU9*0.6+BB9*0.4,"") | BD9: =IFERROR(VLOOKUP(BC9*10,#REF!,2,1),"") | BE9: 1 | BF9: -2 | BG9: 地产敞口-1，负债不稳-1 | BH9: 星展银行有限公司 | BI9: 100 | BJ9: 上海 | BK9: 上海市 | BL9: =IF([1]!s_stmnote_bank_17n(A9,$A$1,1)="0","",[1]!s_stmnote_bank_17n(A9,$A$1,1)) -> 0 | BM9: =IF([1]!s_stmnote_bank_18n(A9,$A$1,1)="0","",[1]!s_stmnote_bank_18n(A9,$A$1,1)) -> 0 | BP9: =[1]!s_stmnote_bank_5444(A9,$A$1,1) -> 0 | BQ9: =[1]!s_stmnote_bank_129n($A9,$A$1,1) -> 61.6757 | BR9: =IFERROR(BS9/SUMPRODUCT(BT9:BX9,$BT$4:$BX$4)*SUMIFS($BT$4:$BX$4,BT9:BX9,">0")*100,0) -> 2.6674988 | BS9: =[1]!b_stm07_is(A9,19,$A$1,1,100000000) -> 35.257539 | BT9: =[1]!s_stm07_bs(A9,"W15273164",$A$1,1,100000000)-[1]!s_stm07_bs(A9,"W17642530",$A$1,1,100000000)-[1]!s_stm07_bs(A9,"W15910877",$A$1,1,100000000)-[1]!s_stm07_bs_39(A9,$A$1,1,100000000)-[1]!s_stm07_bs(A9,"W17700468",$A$1,1,100000000)-[1]!s_stm07_bs(A9,"W16504296",$A$1,1,100000000)-[1]!s_stm07_bs(A9,"W13769069",$A$1,1,100000000) -> 1373.2323 | BU9: =[1]!s_stm07_bs(A9,"W15273164",$B$1,1,100000000)-[1]!s_stm07_bs(A9,"W17642530",$B$1,1,100000000)-[1]!s_stm07_bs(A9,"W15910877",$B$1,1,100000000)-[1]!s_stm07_bs_39(A9,$B$1,1,100000000)-[1]!s_stm07_bs(A9,"W17700468",$B$1,1,100000000)-[1]!s_stm07_bs(A9,"W16504296",$B$1,1,100000000)-[1]!s_stm07_bs(A9,"W13769069",$B$1,1,100000000) -> 1306.9705 | BV9: =[1]!s_stm07_bs(A9,"W15273164",$E$1,1,100000000)-[1]!s_stm07_bs(A9,"W17642530",$E$1,1,100000000)-[1]!s_stm07_bs(A9,"W15910877",$E$1,1,100000000)-[1]!s_stm07_bs_39(A9,$E$1,1,100000000)-[1]!s_stm07_bs(A9,"W17700468",$E$1,1,100000000)-[1]!s_stm07_bs(A9,"W16504296",$E$1,1,100000000)-[1]!s_stm07_bs(A9,"W13769069",$E$1,1,100000000) -> 1348.2118 | BW9: =[1]!s_stm07_bs(A9,"W15273164",$F$1,1,100000000)-[1]!s_stm07_bs(A9,"W17642530",$F$1,1,100000000)-[1]!s_stm07_bs(A9,"W15910877",$F$1,1,100000000)-[1]!s_stm07_bs_39(A9,$F$1,1,100000000)-[1]!s_stm07_bs(A9,"W17700468",$F$1,1,100000000)-[1]!s_stm07_bs(A9,"W16504296",$F$1,1,100000000)-[1]!s_stm07_bs(A9,"W13769069",$F$1,1,100000000) -> 1338.828 | BX9: =[1]!s_stm07_bs(A9,"W15273164",$G$1,1,100000000)-[1]!s_stm07_bs(A9,"W17642530",$G$1,1,100000000)-[1]!s_stm07_bs(A9,"W15910877",$G$1,1,100000000)-[1]!s_stm07_bs_39(A9,$G$1,1,100000000)-[1]!s_stm07_bs(A9,"W17700468",$G$1,1,100000000)-[1]!s_stm07_bs(A9,"W16504296",$G$1,1,100000000)-[1]!s_stm07_bs(A9,"W13769069",$G$1,1,100000000) -> 1364.9853 | BY9: =IFERROR([1]!b_stm07_is(A9,20,$A$1,1,100000000)/AVERAGEIF(CA9:CE9,">0")*100,0) -> 1.5948673 | BZ9: =[1]!b_stm07_is(A9,20,$A$1,1,100000000) -> 17.75272 | CA9: =[1]!s_stmnote_bank_38(A9,$A$1,1,100000000) -> 1174.5677 | CB9: =[1]!s_stmnote_bank_38(A9,$B$1,1,100000000) -> 1051.6638 | CC9: =[1]!s_stmnote_bank_38(A9,$E$1,1,100000000) -> 0 | CD9: =[1]!s_stmnote_bank_38(A9,$F$1,1,100000000) -> 0 | CE9: =[1]!s_stmnote_bank_38(A9,$G$1,1,100000000) -> 0 | CF9: =IF(BP9<>0,BP9,IFERROR(IF(([1]!b_stm07_is(A9,19,$A$1,1,100000000)-[1]!b_stm07_is(A9,20,$A$1,1,100000000))/AVERAGE([1]!s_stmnote_bank_35(A9,$A$1,1,100000000),[1]!s_stmnote_bank_35(A9,$B$1,1,100000000))*100=0,"",([1]!b_stm07_is(A9,19,$A$1,1,100000000)-[1]!b_stm07_is(A9,20,$A$1,1,100000000))/AVERAGE([1]!s_stmnote_bank_35(A9,$A$1,1,100000000),[1]!s_stmnote_bank_35(A9,$B$1,1,100000000))*100),"")) -> 1.4285628 | CG9: =RANK(CF9,CF$5:CF$192,0)&" "&COUNTIF(CF$5:CF$192,">0") -> 157 171 | CH9: =IFERROR(CF9/100/P9,"") -> 1.3448355 | CI9: =RANK(CH9,CH$5:CH$192,0)&" "&COUNTIF(CH$5:CH$192,">0") -> 30 169 | CJ9: =[1]!s_stmnote_bank_30(A9,$A$1,1) -> 40.5001 | CP9: =[1]!b_stm07_bs($A9,141,$A$1,1,100000000) -> 127.62366 | CQ9: =[1]!b_stm07_bs($A9,141,$D$1,1,100000000) -> 131.43321 | CR9: =IF([1]!s_fa_roic_yearly($A9,$A$1)=0,"",[1]!s_fa_roic_yearly($A9,$A$1)) -> 5.9431 | CS9: =RANK(CR9,CR$5:CR$192,0)/COUNTIF(CR$5:CR$192,">0") -> 0.73372781 | CT9: =IF([1]!s_fa_roic_yearly($A9,$D$1)=0,"",[1]!s_fa_roic_yearly($A9,$D$1)) -> 6.9058 | CU9: =RANK(CT9,CT$5:CT$192,0)/COUNTIF(CT$5:CT$192,">0") -> 0.78873239 | CV9: =[1]!s_stm07_bs(A9,"W14578191",$A$1,1,100000000) -> 485.60281 | CW9: =[1]!s_stmnote_bank_682($A9,$A$1,1,2,100000000) -> 55.300886 | CX9: =IF(CW9*CV9=0,"",CW9/CV9) -> 0.1138809
A10: 112174755.IB | B10: 恒生银行(中国)有限公司 | C10: 恒生银行(中国) | D10: 外资行 | E10: 有普通 | F10: AAA | H10: BB | J10: =VLOOKUP(B10,[3]额度信息!$B:$T,19,0) -> #N/A | K10: 恒生银行全资子公司 | L10: =IFERROR(([1]!b_stm07_bs($A10,47,$A$1,1,100000000))/[1]!b_stm07_bs($A10,109,$A$1,1,100000000),"") -> 0.16907988 | M10: 3.1 | N10: =IFERROR(([1]!s_stmnote_bank_26($A10,$A$1,1,100000000)-[1]!s_stmnote_bank_26($A10,$B$1,1,100000000)+M10)/[1]!s_stmnote_bank_1n($A10,$B$1,1,100000000),"") -> 0.0048221113 | O10: =RANK(N10,N$5:N$192,1)&" "&COUNTIF(N$5:N$192,">0") -> 11 50 | P10: =IF(IFERROR(R10+AB10/100,"")=0,"",IFERROR(R10+AB10/100,"")) -> 0.0072 | Q10: =RANK(P10,P$5:P$192,1)&" "&COUNTIF(P$5:P$192,">0") -> 4 169 | R10: =IFERROR([1]!s_stmnote_bank($A10,"34",$A$1,100000000)/[1]!s_stmnote_bank_1n(A10,$A$1,1,100000000),"") -> 0 | S10: 0.142 | T10: 0.018 | Z10: =[1]!b_stm07_bs(A10,74,$A$1,1,100000000) -> 1370.6721 | AA10: =[1]!b_stm07_bs(A10,109,$A$1,1,100000000) -> 539.37734 | AB10: 0.72 | AC10: =IF([1]!s_stmnote_bank_23n(A10,$A$1,1)=0,"",IFERROR([1]!s_stmnote_bank_23n(A10,$A$1,1),"")) -> 410.89 | AD10: =RANK(AC10,AC$5:AC$192,1)&" "&COUNTIF(AC$5:AC$192,">0") -> 133 167 | AE10: =[1]!s_stmnote_bank_capadequacyratio(A10,$A$1,1) -> 13.6 | AF10: =IF([1]!s_stmnote_bank_capadequacyratio_ct1(A10,$A$1,1)=0,"",IFERROR([1]!s_stmnote_bank_capadequacyratio_ct1(A10,$A$1,1),"")) -> 12.4 | AG10: =RANK(AF10,AF$5:AF$192,1)&" "&COUNTIF(AF$5:AF$192,">0") -> 128 167 | AH10: =IF(OR([1]!s_fa_roe(A10,20201231)=0,[1]!s_fa_roe(A10,20211231)="0",[1]!s_fa_roe(A10,20221231)="0"),"",IFERROR(([1]!s_fa_roe(A10,20221231)+[1]!s_fa_roe(A10,20201231)+[1]!s_fa_roe(A10,20211231))/3,"")) -> 5.5486 | AI10: =RANK(AH10,AH$5:AH$192,1)&" "&COUNTIF(AH$5:AH$192,">0") -> 49 173 | AJ10: =IFERROR(([1]!s_stmnote_bank_65(A10,$A$1,1,2,4,100000000)+[1]!s_stmnote_bank_65(A10,$A$1,1,2,6,100000000))/[1]!s_stmnote_bank_1n(A10,$A$1,1,100000000),"") -> 0.24504659 | AK10: =IFERROR([1]!s_stmnote_bank_614(A10,$A$1,1,2,100000000)/[1]!s_stmnote_bank_647(A10,$A$1,1,2,100000000),"") -> 0.49691971 | AL10: =IFERROR(([1]!b_stm07_bs(A10,104,$A$1,1,100000000)+[1]!b_stm07_bs(A10,106,$A$1,1,100000000)+[1]!b_stm07_bs(A10,76,$A$1,1,100000000)+[1]!b_stm07_bs(A10,108,$A$1,1,100000000)+[1]!b_stm07_bs(A10,95,$A$1,1,100000000))/[1]!b_stm07_bs(A10,128,$A$1,1,100000000),"") -> 0.5464096 | AM10: =IFERROR(([1]!s_stmnote_bank_614(A10,$A$1,1,2,100000000)+[1]!b_stm07_bs(A10,104,$A$1,1,100000000)+[1]!b_stm07_bs(A10,106,$A$1,1,100000000)+[1]!b_stm07_bs(A10,76,$A$1,1,100000000)+[1]!b_stm07_bs(A10,108,$A$1,1,100000000)+[1]!b_stm07_bs(A10,95,$A$1,1,100000000))/[1]!b_stm07_bs(A10,128,$A$1,1,100000000),"") -> 0.76132646 | AN10: =IF(Z10>#REF!,#REF!,IF(Z10>#REF!,#REF!,IF(Z10>#REF!,#REF!,IF(Z10>#REF!,#REF!,IF(Z10>#REF!,#REF!,IF(Z10>#REF!,#REF!,IF(Z10>#REF!,#REF!,#REF!))))))) -> #REF! | AO10: =IF(AA10>#REF!,#REF!,IF(AA10>#REF!,#REF!,IF(AA10>#REF!,#REF!,IF(AA10>#REF!,#REF!,IF(AA10>#REF!,#REF!,IF(AA10>#REF!,#REF!,IF(AA10>#REF!,#REF!,#REF!))))))) -> #REF! | AP10: =IF(AB10<#REF!,#REF!,IF(AB10<#REF!,#REF!,IF(AB10<#REF!,#REF!,IF(AB10<#REF!,#REF!,IF(AB10<#REF!,#REF!,IF(AB10<#REF!,#REF!,#REF!)))))) -> #REF! | AQ10: =IF(AC10>#REF!,#REF!,IF(AC10>#REF!,#REF!,IF(AC10>#REF!,#REF!,IF(AC10>#REF!,#REF!,#REF!)))) -> #REF! | AR10: =IF(AE10>#REF!,#REF!,IF(AE10>#REF!,#REF!,IF(AE10>#REF!,#REF!,IF(AE10>#REF!,#REF!,#REF!)))) -> #REF! | AS10: =IF(AF10>#REF!,#REF!,IF(AF10>#REF!,#REF!,IF(AF10>#REF!,#REF!,IF(AF10>#REF!,#REF!,#REF!)))) -> #REF! | AT10: =IF(AH10>#REF!,#REF!,IF(AH10>#REF!,#REF!,IF(AH10>#REF!,#REF!,IF(AH10>#REF!,#REF!,IF(AH10>#REF!,#REF!,#REF!))))) -> #REF! | AU10: =AN10*$AN$3+AP10*$AP$3+AQ10*$AQ$3+AR10*$AR$3+AS10*$AS$3+AT10*$AT$3+$AO$3*AO10 -> #REF! | AV10: 强 | AW10: 高 | AX10: 好 | AY10: =IFERROR(VLOOKUP(AV10,#REF!,3,0),"") | AZ10: =IFERROR(VLOOKUP(AW10,#REF!,3,0),"") | BA10: =IFERROR(VLOOKUP(AX10,#REF!,3,0),"") | BB10: =IFERROR(AY10*#REF!+AZ10*#REF!+BA10*#REF!,"") | BC10: =IFERROR(AU10*0.6+BB10*0.4,"") | BD10: =IFERROR(VLOOKUP(BC10*10,#REF!,2,1),"") | BE10: 1 | BF10: -2 | BG10: 地产敞口-2，负债不稳-2 | BH10: 恒生银行有限公司 | BI10: 100 | BJ10: 全国 | BK10: - | BL10: =IF([1]!s_stmnote_bank_17n(A10,$A$1,1)="0","",[1]!s_stmnote_bank_17n(A10,$A$1,1)) -> 0 | BM10: =IF([1]!s_stmnote_bank_18n(A10,$A$1,1)="0","",[1]!s_stmnote_bank_18n(A10,$A$1,1)) -> 0 | BP10: =[1]!s_stmnote_bank_5444(A10,$A$1,1) -> 0 | BQ10: =[1]!s_stmnote_bank_129n($A10,$A$1,1) -> 52.89 | BR10: =IFERROR(BS10/SUMPRODUCT(BT10:BX10,$BT$4:$BX$4)*SUMIFS($BT$4:$BX$4,BT10:BX10,">0")*100,0) -> 3.5025212 | BS10: =[1]!b_stm07_is(A10,19,$A$1,1,100000000) -> 42.096059 | BT10: =[1]!s_stm07_bs(A10,"W15273164",$A$1,1,100000000)-[1]!s_stm07_bs(A10,"W17642530",$A$1,1,100000000)-[1]!s_stm07_bs(A10,"W15910877",$A$1,1,100000000)-[1]!s_stm07_bs_39(A10,$A$1,1,100000000)-[1]!s_stm07_bs(A10,"W17700468",$A$1,1,100000000)-[1]!s_stm07_bs(A10,"W16504296",$A$1,1,100000000)-[1]!s_stm07_bs(A10,"W13769069",$A$1,1,100000000) -> 1356.141 | BU10: =[1]!s_stm07_bs(A10,"W15273164",$B$1,1,100000000)-[1]!s_stm07_bs(A10,"W17642530",$B$1,1,100000000)-[1]!s_stm07_bs(A10,"W15910877",$B$1,1,100000000)-[1]!s_stm07_bs_39(A10,$B$1,1,100000000)-[1]!s_stm07_bs(A10,"W17700468",$B$1,1,100000000)-[1]!s_stm07_bs(A10,"W16504296",$B$1,1,100000000)-[1]!s_stm07_bs(A10,"W13769069",$B$1,1,100000000) -> 1179.8413 | BV10: =[1]!s_stm07_bs(A10,"W15273164",$E$1,1,100000000)-[1]!s_stm07_bs(A10,"W17642530",$E$1,1,100000000)-[1]!s_stm07_bs(A10,"W15910877",$E$1,1,100000000)-[1]!s_stm07_bs_39(A10,$E$1,1,100000000)-[1]!s_stm07_bs(A10,"W17700468",$E$1,1,100000000)-[1]!s_stm07_bs(A10,"W16504296",$E$1,1,100000000)-[1]!s_stm07_bs(A10,"W13769069",$E$1,1,100000000) -> 0 | BW10: =[1]!s_stm07_bs(A10,"W15273164",$F$1,1,100000000)-[1]!s_stm07_bs(A10,"W17642530",$F$1,1,100000000)-[1]!s_stm07_bs(A10,"W15910877",$F$1,1,100000000)-[1]!s_stm07_bs_39(A10,$F$1,1,100000000)-[1]!s_stm07_bs(A10,"W17700468",$F$1,1,100000000)-[1]!s_stm07_bs(A10,"W16504296",$F$1,1,100000000)-[1]!s_stm07_bs(A10,"W13769069",$F$1,1,100000000) -> 0 | BX10: =[1]!s_stm07_bs(A10,"W15273164",$G$1,1,100000000)-[1]!s_stm07_bs(A10,"W17642530",$G$1,1,100000000)-[1]!s_stm07_bs(A10,"W15910877",$G$1,1,100000000)-[1]!s_stm07_bs_39(A10,$G$1,1,100000000)-[1]!s_stm07_bs(A10,"W17700468",$G$1,1,100000000)-[1]!s_stm07_bs(A10,"W16504296",$G$1,1,100000000)-[1]!s_stm07_bs(A10,"W13769069",$G$1,1,100000000) -> 0 | BY10: =IFERROR([1]!b_stm07_is(A10,20,$A$1,1,100000000)/AVERAGEIF(CA10:CE10,">0")*100,0) -> 2.0876577 | BZ10: =[1]!b_stm07_is(A10,20,$A$1,1,100000000) -> 23.665042 | CA10: =[1]!s_stmnote_bank_38(A10,$A$1,1,100000000) -> 1220.816 | CB10: =[1]!s_stmnote_bank_38(A10,$B$1,1,100000000) -> 1046.3221 | CC10: =[1]!s_stmnote_bank_38(A10,$E$1,1,100000000) -> 0 | CD10: =[1]!s_stmnote_bank_38(A10,$F$1,1,100000000) -> 0 | CE10: =[1]!s_stmnote_bank_38(A10,$G$1,1,100000000) -> 0 | CF10: =IF(BP10<>0,BP10,IFERROR(IF(([1]!b_stm07_is(A10,19,$A$1,1,100000000)-[1]!b_stm07_is(A10,20,$A$1,1,100000000))/AVERAGE([1]!s_stmnote_bank_35(A10,$A$1,1,100000000),[1]!s_stmnote_bank_35(A10,$B$1,1,100000000))*100=0,"",([1]!b_stm07_is(A10,19,$A$1,1,100000000)-[1]!b_stm07_is(A10,20,$A$1,1,100000000))/AVERAGE([1]!s_stmnote_bank_35(A10,$A$1,1,100000000),[1]!s_stmnote_bank_35(A10,$B$1,1,100000000))*100),"")) -> 1.4965826 | CG10: =RANK(CF10,CF$5:CF$192,0)&" "&COUNTIF(CF$5:CF$192,">0") -> 154 171 | CH10: =IFERROR(CF10/100/P10,"") -> 2.078587 | CI10: =RANK(CH10,CH$5:CH$192,0)&" "&COUNTIF(CH$5:CH$192,">0") -> 8 169 | CJ10: =[1]!s_stmnote_bank_30(A10,$A$1,1) -> 25.0878 | CP10: =[1]!b_stm07_bs($A10,141,$A$1,1,100000000) -> 123.55156 | CQ10: =[1]!b_stm07_bs($A10,141,$D$1,1,100000000) -> 0 | CR10: =IF([1]!s_fa_roic_yearly($A10,$A$1)=0,"",[1]!s_fa_roic_yearly($A10,$A$1)) -> 5.9792 | CS10: =RANK(CR10,CR$5:CR$192,0)/COUNTIF(CR$5:CR$192,">0") -> 0.72189349 | CT10: =IF([1]!s_fa_roic_yearly($A10,$D$1)=0,"",[1]!s_fa_roic_yearly($A10,$D$1)) | CU10: =RANK(CT10,CT$5:CT$192,0)/COUNTIF(CT$5:CT$192,">0") -> #VALUE! | CV10: =[1]!s_stm07_bs(A10,"W14578191",$A$1,1,100000000) -> 683.33083 | CW10: =[1]!s_stmnote_bank_682($A10,$A$1,1,2,100000000) -> 157.78729 | CX10: =IF(CW10*CV10=0,"",CW10/CV10) -> 0.23090907
A11: 112173062.IB | B11: 嘉兴银行股份有限公司 | C11: 嘉兴银行 | D11: 城商行 | E11: 嘉兴银行 | F11: AA+ | G11: BBB | H11: BB | J11: =VLOOKUP(B11,[3]额度信息!$B:$T,19,0) -> 0 | K11: 主要观点： 1、 该行业务集中在浙江嘉兴地区，在嘉兴总资产占比87%。存、贷款市场份额占据嘉兴的5.7%、4.0%，排名第5，在嘉兴当地有一定区域影响力。该行是嘉兴唯一的城商行，对于区域融资较为重要且国资持股比例较高，能够获得一定的外部支持。 2、 该行业务包括公司银行、个人银行和资金业务三大板块。贷款类业务主要投放小微企业，净息差较高，不良率保持较低水平。资金业务以利率债和江浙地区城投债投资为主，投资风险可控。总体来看，该行盈利能力较强。 3、 2018-20年，客户存款/总负债分别为75.1%、72.8%和75.4%，该行吸收存款能力强，负债稳定性良好，流动性风险低。 主要关注： 1、 该行股权较为分散，由国资和民企共同持股，无实际控制人。不过主要股东在董事会中均有席位，内部治理尚可。 2、 贷款主要投向嘉兴当地的小微企业和个人经营性贷款，风险高于同业，不过资产质量历史表现尚可，后续需关注区域经济情况和资产质量变化。 3、 2018-2020年核心一级资本充足率分别为9.7%、10.1%和8.6%，面临一定的核心资本补充压力。 4、 2018-20年，该行净息差2.96%、2.81%、2.01%，20年受疫情影响，该行下调贷款利率、减免利息，导致净息差降幅较大，但仍属于同业较高水平。 | L11: =IFERROR(([1]!b_stm07_bs($A11,47,$A$1,1,100000000))/[1]!b_stm07_bs($A11,109,$A$1,1,100000000),"") -> 0.13140154 | O11: =RANK(N11,N$5:N$192,1)&" "&COUNTIF(N$5:N$192,">0") -> #N/A | P11: =IF(IFERROR(R11+AB11/100,"")=0,"",IFERROR(R11+AB11/100,"")) -> 0.028279872 | Q11: =RANK(P11,P$5:P$192,1)&" "&COUNTIF(P$5:P$192,">0") -> 74 169 | R11: =IFERROR([1]!s_stmnote_bank($A11,"34",$A$1,100000000)/[1]!s_stmnote_bank_1n(A11,$A$1,1,100000000),"") -> 0.020579872 | Z11: =[1]!b_stm07_bs(A11,74,$A$1,1,100000000) -> 1223.8837 | AA11: =[1]!b_stm07_bs(A11,109,$A$1,1,100000000) -> 887.51317 | AB11: =[1]!s_stmnote_bank_5n(A11,$A$1,1) -> 0.77 | AC11: =IF([1]!s_stmnote_bank_23n(A11,$A$1,1)=0,"",IFERROR([1]!s_stmnote_bank_23n(A11,$A$1,1),"")) -> 602.59 | AD11: =RANK(AC11,AC$5:AC$192,1)&" "&COUNTIF(AC$5:AC$192,">0") -> 155 167 | AE11: =[1]!s_stmnote_bank_capadequacyratio(A11,$A$1,1) -> 13.14 | AF11: =IF([1]!s_stmnote_bank_capadequacyratio_ct1(A11,$A$1,1)=0,"",IFERROR([1]!s_stmnote_bank_capadequacyratio_ct1(A11,$A$1,1),"")) -> 8.18 | AG11: =RANK(AF11,AF$5:AF$192,1)&" "&COUNTIF(AF$5:AF$192,">0") -> 15 167 | AH11: =IF(OR([1]!s_fa_roe(A11,20201231)=0,[1]!s_fa_roe(A11,20211231)="0",[1]!s_fa_roe(A11,20221231)="0"),"",IFERROR(([1]!s_fa_roe(A11,20221231)+[1]!s_fa_roe(A11,20201231)+[1]!s_fa_roe(A11,20211231))/3,"")) -> 12.0831 | AI11: =RANK(AH11,AH$5:AH$192,1)&" "&COUNTIF(AH$5:AH$192,">0") -> 149 173 | AJ11: =IFERROR(([1]!s_stmnote_bank_65(A11,$A$1,1,2,4,100000000)+[1]!s_stmnote_bank_65(A11,$A$1,1,2,6,100000000))/[1]!s_stmnote_bank_1n(A11,$A$1,1,100000000),"") -> 0.16741509 | AK11: =IFERROR([1]!s_stmnote_bank_614(A11,$A$1,1,2,100000000)/[1]!s_stmnote_bank_647(A11,$A$1,1,2,100000000),"") -> 0.33683594 | AL11: =IFERROR(([1]!b_stm07_bs(A11,104,$A$1,1,100000000)+[1]!b_stm07_bs(A11,106,$A$1,1,100000000)+[1]!b_stm07_bs(A11,76,$A$1,1,100000000)+[1]!b_stm07_bs(A11,108,$A$1,1,100000000)+[1]!b_stm07_bs(A11,95,$A$1,1,100000000))/[1]!b_stm07_bs(A11,128,$A$1,1,100000000),"") -> 0.16424619 | AM11: =IFERROR(([1]!s_stmnote_bank_614(A11,$A$1,1,2,100000000)+[1]!b_stm07_bs(A11,104,$A$1,1,100000000)+[1]!b_stm07_bs(A11,106,$A$1,1,100000000)+[1]!b_stm07_bs(A11,76,$A$1,1,100000000)+[1]!b_stm07_bs(A11,108,$A$1,1,100000000)+[1]!b_stm07_bs(A11,95,$A$1,1,100000000))/[1]!b_stm07_bs(A11,128,$A$1,1,100000000),"") -> 0.42605777 | AN11: =IF(Z11>#REF!,#REF!,IF(Z11>#REF!,#REF!,IF(Z11>#REF!,#REF!,IF(Z11>#REF!,#REF!,IF(Z11>#REF!,#REF!,IF(Z11>#REF!,#REF!,IF(Z11>#REF!,#REF!,#REF!))))))) -> #REF! | AO11: =IF(AA11>#REF!,#REF!,IF(AA11>#REF!,#REF!,IF(AA11>#REF!,#REF!,IF(AA11>#REF!,#REF!,IF(AA11>#REF!,#REF!,IF(AA11>#REF!,#REF!,IF(AA11>#REF!,#REF!,#REF!))))))) -> #REF! | AP11: =IF(AB11<#REF!,#REF!,IF(AB11<#REF!,#REF!,IF(AB11<#REF!,#REF!,IF(AB11<#REF!,#REF!,IF(AB11<#REF!,#REF!,IF(AB11<#REF!,#REF!,#REF!)))))) -> #REF! | AQ11: =IF(AC11>#REF!,#REF!,IF(AC11>#REF!,#REF!,IF(AC11>#REF!,#REF!,IF(AC11>#REF!,#REF!,#REF!)))) -> #REF! | AR11: =IF(AE11>#REF!,#REF!,IF(AE11>#REF!,#REF!,IF(AE11>#REF!,#REF!,IF(AE11>#REF!,#REF!,#REF!)))) -> #REF! | AS11: =IF(AF11>#REF!,#REF!,IF(AF11>#REF!,#REF!,IF(AF11>#REF!,#REF!,IF(AF11>#REF!,#REF!,#REF!)))) -> #REF! | AT11: =IF(AH11>#REF!,#REF!,IF(AH11>#REF!,#REF!,IF(AH11>#REF!,#REF!,IF(AH11>#REF!,#REF!,IF(AH11>#REF!,#REF!,#REF!))))) -> #REF! | AU11: =AN11*$AN$3+AP11*$AP$3+AQ11*$AQ$3+AR11*$AR$3+AS11*$AS$3+AT11*$AT$3+$AO$3*AO11 -> #REF! | AV11: 中 | AW11: 较低 | AX11: 较好 | AY11: =IFERROR(VLOOKUP(AV11,#REF!,3,0),"") | AZ11: =IFERROR(VLOOKUP(AW11,#REF!,3,0),"") | BA11: =IFERROR(VLOOKUP(AX11,#REF!,3,0),"") | BB11: =IFERROR(AY11*#REF!+AZ11*#REF!+BA11*#REF!,"") | BC11: =IFERROR(AU11*0.6+BB11*0.4,"") | BD11: =IFERROR(VLOOKUP(BC11*10,#REF!,2,1),"") | BE11: 0 | BF11: -1 | BG11: 内控问题频发、高管更换频繁-1 | BH11: 嘉兴市城市投资发展集团有限公司 | BI11: 9.9099998 | BJ11: 江苏 | BK11: 嘉兴市 | BL11: =IF([1]!s_stmnote_bank_17n(A11,$A$1,1)="0","",[1]!s_stmnote_bank_17n(A11,$A$1,1)) -> 4.92 | BM11: =IF([1]!s_stmnote_bank_18n(A11,$A$1,1)="0","",[1]!s_stmnote_bank_18n(A11,$A$1,1)) -> 38.1 | BP11: =[1]!s_stmnote_bank_5444(A11,$A$1,1) -> 2.05 | BQ11: =[1]!s_stmnote_bank_129n($A11,$A$1,1) -> 37.25 | BR11: =IFERROR(BS11/SUMPRODUCT(BT11:BX11,$BT$4:$BX$4)*SUMIFS($BT$4:$BX$4,BT11:BX11,">0")*100,0) -> 4.6159999 | BS11: =[1]!b_stm07_is(A11,19,$A$1,1,100000000) -> 49.007713 | BT11: =[1]!s_stm07_bs(A11,"W15273164",$A$1,1,100000000)-[1]!s_stm07_bs(A11,"W17642530",$A$1,1,100000000)-[1]!s_stm07_bs(A11,"W15910877",$A$1,1,100000000)-[1]!s_stm07_bs_39(A11,$A$1,1,100000000)-[1]!s_stm07_bs(A11,"W17700468",$A$1,1,100000000)-[1]!s_stm07_bs(A11,"W16504296",$A$1,1,100000000)-[1]!s_stm07_bs(A11,"W13769069",$A$1,1,100000000) -> 1208.0495 | BU11: =[1]!s_stm07_bs(A11,"W15273164",$B$1,1,100000000)-[1]!s_stm07_bs(A11,"W17642530",$B$1,1,100000000)-[1]!s_stm07_bs(A11,"W15910877",$B$1,1,100000000)-[1]!s_stm07_bs_39(A11,$B$1,1,100000000)-[1]!s_stm07_bs(A11,"W17700468",$B$1,1,100000000)-[1]!s_stm07_bs(A11,"W16504296",$B$1,1,100000000)-[1]!s_stm07_bs(A11,"W13769069",$B$1,1,100000000) -> 1030.481 | BV11: =[1]!s_stm07_bs(A11,"W15273164",$E$1,1,100000000)-[1]!s_stm07_bs(A11,"W17642530",$E$1,1,100000000)-[1]!s_stm07_bs(A11,"W15910877",$E$1,1,100000000)-[1]!s_stm07_bs_39(A11,$E$1,1,100000000)-[1]!s_stm07_bs(A11,"W17700468",$E$1,1,100000000)-[1]!s_stm07_bs(A11,"W16504296",$E$1,1,100000000)-[1]!s_stm07_bs(A11,"W13769069",$E$1,1,100000000) -> 1122.9138 | BW11: =[1]!s_stm07_bs(A11,"W15273164",$F$1,1,100000000)-[1]!s_stm07_bs(A11,"W17642530",$F$1,1,100000000)-[1]!s_stm07_bs(A11,"W15910877",$F$1,1,100000000)-[1]!s_stm07_bs_39(A11,$F$1,1,100000000)-[1]!s_stm07_bs(A11,"W17700468",$F$1,1,100000000)-[1]!s_stm07_bs(A11,"W16504296",$F$1,1,100000000)-[1]!s_stm07_bs(A11,"W13769069",$F$1,1,100000000) -> 1091.1515 | BX11: =[1]!s_stm07_bs(A11,"W15273164",$G$1,1,100000000)-[1]!s_stm07_bs(A11,"W17642530",$G$1,1,100000000)-[1]!s_stm07_bs(A11,"W15910877",$G$1,1,100000000)-[1]!s_stm07_bs_39(A11,$G$1,1,100000000)-[1]!s_stm07_bs(A11,"W17700468",$G$1,1,100000000)-[1]!s_stm07_bs(A11,"W16504296",$G$1,1,100000000)-[1]!s_stm07_bs(A11,"W13769069",$G$1,1,100000000) -> 1085.7943 | BY11: =IFERROR([1]!b_stm07_is(A11,20,$A$1,1,100000000)/AVERAGEIF(CA11:CE11,">0")*100,0) -> 2.7890151 | BZ11: =[1]!b_stm07_is(A11,20,$A$1,1,100000000) -> 28.892147 | CA11: =[1]!s_stmnote_bank_38(A11,$A$1,1,100000000) -> 1127.1833 | CB11: =[1]!s_stmnote_bank_38(A11,$B$1,1,100000000) -> 963.78287 | CC11: =[1]!s_stmnote_bank_38(A11,$E$1,1,100000000) -> 1047.0457 | CD11: =[1]!s_stmnote_bank_38(A11,$F$1,1,100000000) -> 1026.0514 | CE11: =[1]!s_stmnote_bank_38(A11,$G$1,1,100000000) -> 1015.5693 | CF11: =IF(BP11<>0,BP11,IFERROR(IF(([1]!b_stm07_is(A11,19,$A$1,1,100000000)-[1]!b_stm07_is(A11,20,$A$1,1,100000000))/AVERAGE([1]!s_stmnote_bank_35(A11,$A$1,1,100000000),[1]!s_stmnote_bank_35(A11,$B$1,1,100000000))*100=0,"",([1]!b_stm07_is(A11,19,$A$1,1,100000000)-[1]!b_stm07_is(A11,20,$A$1,1,100000000))/AVERAGE([1]!s_stmnote_bank_35(A11,$A$1,1,100000000),[1]!s_stmnote_bank_35(A11,$B$1,1,100000000))*100),"")) -> 2.05 | CG11: =RANK(CF11,CF$5:CF$192,0)&" "&COUNTIF(CF$5:CF$192,">0") -> 85 171 | CH11: =IFERROR(CF11/100/P11,"") -> 0.72489719 | CI11: =RANK(CH11,CH$5:CH$192,0)&" "&COUNTIF(CH$5:CH$192,">0") -> 76 169 | CJ11: =[1]!s_stmnote_bank_30(A11,$A$1,1) -> 31.7113 | CP11: =[1]!b_stm07_bs($A11,141,$A$1,1,100000000) -> 82.046059 | CQ11: =[1]!b_stm07_bs($A11,141,$D$1,1,100000000) -> 90.260597 | CR11: =IF([1]!s_fa_roic_yearly($A11,$A$1)=0,"",[1]!s_fa_roic_yearly($A11,$A$1)) -> 12.2196 | CS11: =RANK(CR11,CR$5:CR$192,0)/COUNTIF(CR$5:CR$192,">0") -> 0.15384615 | CT11: =IF([1]!s_fa_roic_yearly($A11,$D$1)=0,"",[1]!s_fa_roic_yearly($A11,$D$1)) -> 20.4492 | CU11: =RANK(CT11,CT$5:CT$192,0)/COUNTIF(CT$5:CT$192,">0") -> 0.0070422535 | CV11: =[1]!s_stm07_bs(A11,"W14578191",$A$1,1,100000000) -> 672.59706 | CW11: =[1]!s_stmnote_bank_682($A11,$A$1,1,2,100000000) -> 202.37475 | CX11: =IF(CW11*CV11=0,"",CW11/CV11) -> 0.30088558
A12: 1826008.IB | B12: 华侨永亨银行(中国)有限公司 | C12: 华侨永亨银行(中国) | D12: 外资行 | E12: 有普通 | F12: AAA | G12: BB+ | H12: BB- | J12: =VLOOKUP(B12,[3]额度信息!$B:$T,19,0) -> 0 | K12: 华侨银行香港的永亨银行之后，将其大陆网络与永亨大陆网络合并后成立的全资子公司， | L12: =IFERROR(([1]!b_stm07_bs($A12,47,$A$1,1,100000000))/[1]!b_stm07_bs($A12,109,$A$1,1,100000000),"") -> 0.12159485 | O12: =RANK(N12,N$5:N$192,1)&" "&COUNTIF(N$5:N$192,">0") -> #N/A | P12: =IF(IFERROR(R12+AB12/100,"")=0,"",IFERROR(R12+AB12/100,"")) -> 0.015322725 | Q12: =RANK(P12,P$5:P$192,1)&" "&COUNTIF(P$5:P$192,">0") -> 24 169 | R12: =IFERROR([1]!s_stmnote_bank($A12,"34",$A$1,100000000)/[1]!s_stmnote_bank_1n(A12,$A$1,1,100000000),"") -> 0.012622725 | Z12: =[1]!b_stm07_bs(A12,74,$A$1,1,100000000) -> 609.16402 | AA12: =[1]!b_stm07_bs(A12,109,$A$1,1,100000000) -> 317.93979 | AB12: =[1]!s_stmnote_bank_5n(A12,$A$1,1) -> 0.27 | AC12: =IF([1]!s_stmnote_bank_23n(A12,$A$1,1)=0,"",IFERROR([1]!s_stmnote_bank_23n(A12,$A$1,1),"")) -> 893.99 | AD12: =RANK(AC12,AC$5:AC$192,1)&" "&COUNTIF(AC$5:AC$192,">0") -> 164 167 | AE12: =[1]!s_stmnote_bank_capadequacyratio(A12,$A$1,1) -> 19.44 | AF12: =IF([1]!s_stmnote_bank_capadequacyratio_ct1(A12,$A$1,1)=0,"",IFERROR([1]!s_stmnote_bank_capadequacyratio_ct1(A12,$A$1,1),"")) -> 18.38 | AG12: =RANK(AF12,AF$5:AF$192,0)&" "&COUNTIF(AF$5:AF$192,">0") -> 2 167 | AH12: =IF(OR([1]!s_fa_roe(A12,20201231)=0,[1]!s_fa_roe(A12,20211231)="0",[1]!s_fa_roe(A12,20221231)="0"),"",IFERROR(([1]!s_fa_roe(A12,20221231)+[1]!s_fa_roe(A12,20201231)+[1]!s_fa_roe(A12,20211231))/3,"")) -> 4.1145 | AI12: =RANK(AH12,AH$5:AH$192,1)&" "&COUNTIF(AH$5:AH$192,">0") -> 23 173 | AJ12: =IFERROR(([1]!s_stmnote_bank_65(A12,$A$1,1,2,4,100000000)+[1]!s_stmnote_bank_65(A12,$A$1,1,2,6,100000000))/[1]!s_stmnote_bank_1n(A12,$A$1,1,100000000),"") -> 0.22532516 | AK12: =IFERROR([1]!s_stmnote_bank_614(A12,$A$1,1,2,100000000)/[1]!s_stmnote_bank_647(A12,$A$1,1,2,100000000),"") -> 0.48757411 | AL12: =IFERROR(([1]!b_stm07_bs(A12,104,$A$1,1,100000000)+[1]!b_stm07_bs(A12,106,$A$1,1,100000000)+[1]!b_stm07_bs(A12,76,$A$1,1,100000000)+[1]!b_stm07_bs(A12,108,$A$1,1,100000000)+[1]!b_stm07_bs(A12,95,$A$1,1,100000000))/[1]!b_stm07_bs(A12,128,$A$1,1,100000000),"") -> 0.30481289 | AM12: =IFERROR(([1]!s_stmnote_bank_614(A12,$A$1,1,2,100000000)+[1]!b_stm07_bs(A12,104,$A$1,1,100000000)+[1]!b_stm07_bs(A12,106,$A$1,1,100000000)+[1]!b_stm07_bs(A12,76,$A$1,1,100000000)+[1]!b_stm07_bs(A12,108,$A$1,1,100000000)+[1]!b_stm07_bs(A12,95,$A$1,1,100000000))/[1]!b_stm07_bs(A12,128,$A$1,1,100000000),"") -> 0.60043276 | AN12: =IF(Z12>#REF!,#REF!,IF(Z12>#REF!,#REF!,IF(Z12>#REF!,#REF!,IF(Z12>#REF!,#REF!,IF(Z12>#REF!,#REF!,IF(Z12>#REF!,#REF!,IF(Z12>#REF!,#REF!,#REF!))))))) -> #REF! | AO12: =IF(AA12>#REF!,#REF!,IF(AA12>#REF!,#REF!,IF(AA12>#REF!,#REF!,IF(AA12>#REF!,#REF!,IF(AA12>#REF!,#REF!,IF(AA12>#REF!,#REF!,IF(AA12>#REF!,#REF!,#REF!))))))) -> #REF! | AP12: =IF(AB12<#REF!,#REF!,IF(AB12<#REF!,#REF!,IF(AB12<#REF!,#REF!,IF(AB12<#REF!,#REF!,IF(AB12<#REF!,#REF!,IF(AB12<#REF!,#REF!,#REF!)))))) -> #REF! | AQ12: =IF(AC12>#REF!,#REF!,IF(AC12>#REF!,#REF!,IF(AC12>#REF!,#REF!,IF(AC12>#REF!,#REF!,#REF!)))) -> #REF! | AR12: =IF(AE12>#REF!,#REF!,IF(AE12>#REF!,#REF!,IF(AE12>#REF!,#REF!,IF(AE12>#REF!,#REF!,#REF!)))) -> #REF! | AS12: =IF(AF12>#REF!,#REF!,IF(AF12>#REF!,#REF!,IF(AF12>#REF!,#REF!,IF(AF12>#REF!,#REF!,#REF!)))) -> #REF! | AT12: =IF(AH12>#REF!,#REF!,IF(AH12>#REF!,#REF!,IF(AH12>#REF!,#REF!,IF(AH12>#REF!,#REF!,IF(AH12>#REF!,#REF!,#REF!))))) -> #REF! | AU12: =AN12*$AN$3+AP12*$AP$3+AQ12*$AQ$3+AR12*$AR$3+AS12*$AS$3+AT12*$AT$3+$AO$3*AO12 -> #REF! | AV12: 中 | AW12: 中 | AX12: 好 | AY12: =IFERROR(VLOOKUP(AV12,#REF!,3,0),"") | AZ12: =IFERROR(VLOOKUP(AW12,#REF!,3,0),"") | BA12: =IFERROR(VLOOKUP(AX12,#REF!,3,0),"") | BB12: =IFERROR(AY12*#REF!+AZ12*#REF!+BA12*#REF!,"") | BC12: =IFERROR(AU12*0.6+BB12*0.4,"") | BD12: =IFERROR(VLOOKUP(BC12*10,#REF!,2,1),"") | BE12: 1 | BF12: -2 | BG12: 信息不透明及负债不稳流动性风险 | BH12: 华侨永亨银行有限公司 | BI12: 100 | BJ12: 上海 | BK12: 上海市 | BL12: =IF([1]!s_stmnote_bank_17n(A12,$A$1,1)="0","",[1]!s_stmnote_bank_17n(A12,$A$1,1)) -> 6.27 | BM12: =IF([1]!s_stmnote_bank_18n(A12,$A$1,1)="0","",[1]!s_stmnote_bank_18n(A12,$A$1,1)) -> 0 | BP12: =[1]!s_stmnote_bank_5444(A12,$A$1,1) -> 1.54 | BQ12: =[1]!s_stmnote_bank_129n($A12,$A$1,1) -> 69.49 | BR12: =IFERROR(BS12/SUMPRODUCT(BT12:BX12,$BT$4:$BX$4)*SUMIFS($BT$4:$BX$4,BT12:BX12,">0")*100,0) -> 2.7341575 | BS12: =[1]!b_stm07_is(A12,19,$A$1,1,100000000) -> 16.285892 | BT12: =[1]!s_stm07_bs(A12,"W15273164",$A$1,1,100000000)-[1]!s_stm07_bs(A12,"W17642530",$A$1,1,100000000)-[1]!s_stm07_bs(A12,"W15910877",$A$1,1,100000000)-[1]!s_stm07_bs_39(A12,$A$1,1,100000000)-[1]!s_stm07_bs(A12,"W17700468",$A$1,1,100000000)-[1]!s_stm07_bs(A12,"W16504296",$A$1,1,100000000)-[1]!s_stm07_bs(A12,"W13769069",$A$1,1,100000000) -> 604.1004 | BU12: =[1]!s_stm07_bs(A12,"W15273164",$B$1,1,100000000)-[1]!s_stm07_bs(A12,"W17642530",$B$1,1,100000000)-[1]!s_stm07_bs(A12,"W15910877",$B$1,1,100000000)-[1]!s_stm07_bs_39(A12,$B$1,1,100000000)-[1]!s_stm07_bs(A12,"W17700468",$B$1,1,100000000)-[1]!s_stm07_bs(A12,"W16504296",$B$1,1,100000000)-[1]!s_stm07_bs(A12,"W13769069",$B$1,1,100000000) -> 597.42467 | BV12: =[1]!s_stm07_bs(A12,"W15273164",$E$1,1,100000000)-[1]!s_stm07_bs(A12,"W17642530",$E$1,1,100000000)-[1]!s_stm07_bs(A12,"W15910877",$E$1,1,100000000)-[1]!s_stm07_bs_39(A12,$E$1,1,100000000)-[1]!s_stm07_bs(A12,"W17700468",$E$1,1,100000000)-[1]!s_stm07_bs(A12,"W16504296",$E$1,1,100000000)-[1]!s_stm07_bs(A12,"W13769069",$E$1,1,100000000) -> 0 | BW12: =[1]!s_stm07_bs(A12,"W15273164",$F$1,1,100000000)-[1]!s_stm07_bs(A12,"W17642530",$F$1,1,100000000)-[1]!s_stm07_bs(A12,"W15910877",$F$1,1,100000000)-[1]!s_stm07_bs_39(A12,$F$1,1,100000000)-[1]!s_stm07_bs(A12,"W17700468",$F$1,1,100000000)-[1]!s_stm07_bs(A12,"W16504296",$F$1,1,100000000)-[1]!s_stm07_bs(A12,"W13769069",$F$1,1,100000000) -> 574.73826 | BX12: =[1]!s_stm07_bs(A12,"W15273164",$G$1,1,100000000)-[1]!s_stm07_bs(A12,"W17642530",$G$1,1,100000000)-[1]!s_stm07_bs(A12,"W15910877",$G$1,1,100000000)-[1]!s_stm07_bs_39(A12,$G$1,1,100000000)-[1]!s_stm07_bs(A12,"W17700468",$G$1,1,100000000)-[1]!s_stm07_bs(A12,"W16504296",$G$1,1,100000000)-[1]!s_stm07_bs(A12,"W13769069",$G$1,1,100000000) -> 0 | BY12: =IFERROR([1]!b_stm07_is(A12,20,$A$1,1,100000000)/AVERAGEIF(CA12:CE12,">0")*100,0) -> 1.6891289 | BZ12: =[1]!b_stm07_is(A12,20,$A$1,1,100000000) -> 7.9453539 | CA12: =[1]!s_stmnote_bank_38(A12,$A$1,1,100000000) -> 477.7797 | CB12: =[1]!s_stmnote_bank_38(A12,$B$1,1,100000000) -> 471.28425 | CC12: =[1]!s_stmnote_bank_38(A12,$E$1,1,100000000) -> 0 | CD12: =[1]!s_stmnote_bank_38(A12,$F$1,1,100000000) -> 462.08123 | CE12: =[1]!s_stmnote_bank_38(A12,$G$1,1,100000000) -> 0 | CF12: =IF(BP12<>0,BP12,IFERROR(IF(([1]!b_stm07_is(A12,19,$A$1,1,100000000)-[1]!b_stm07_is(A12,20,$A$1,1,100000000))/AVERAGE([1]!s_stmnote_bank_35(A12,$A$1,1,100000000),[1]!s_stmnote_bank_35(A12,$B$1,1,100000000))*100=0,"",([1]!b_stm07_is(A12,19,$A$1,1,100000000)-[1]!b_stm07_is(A12,20,$A$1,1,100000000))/AVERAGE([1]!s_stmnote_bank_35(A12,$A$1,1,100000000),[1]!s_stmnote_bank_35(A12,$B$1,1,100000000))*100),"")) -> 1.54 | CG12: =RANK(CF12,CF$5:CF$192,0)&" "&COUNTIF(CF$5:CF$192,">0") -> 151 171 | CH12: =IFERROR(CF12/100/P12,"") -> 1.0050432 | CI12: =RANK(CH12,CH$5:CH$192,0)&" "&COUNTIF(CH$5:CH$192,">0") -> 41 169 | CJ12: =[1]!s_stmnote_bank_30(A12,$A$1,1) -> 38.8021 | CP12: =[1]!b_stm07_bs($A12,141,$A$1,1,100000000) -> 84.77704 | CQ12: =[1]!b_stm07_bs($A12,141,$D$1,1,100000000) -> 87.010876 | CR12: =IF([1]!s_fa_roic_yearly($A12,$A$1)=0,"",[1]!s_fa_roic_yearly($A12,$A$1)) -> 3.6937 | CS12: =RANK(CR12,CR$5:CR$192,1)&" "&COUNTIF(CR$5:CR$192,">0") -> 15 169 | CT12: =IF([1]!s_fa_roic_yearly($A12,$D$1)=0,"",[1]!s_fa_roic_yearly($A12,$D$1)) -> 5.6982 | CU12: =RANK(CT12,CT$5:CT$192,1)&" "&COUNTIF(CT$5:CT$192,">0") -> 19 142 | CV12: =[1]!s_stm07_bs(A12,"W14578191",$A$1,1,100000000) -> 276.01478 | CW12: =[1]!s_stmnote_bank_682($A12,$A$1,1,2,100000000) -> 52.297476 | CX12: =IF(CW12*CV12=0,"",CW12/CV12) -> 0.18947346
A13: 111994503.IB | B13: 浙江乐清农村商业银行股份有限公司 | C13: 浙江乐清农商行 | D13: 农商行 | F13: AA+ | H13: B+ | J13: =VLOOKUP(B13,[3]额度信息!$B:$T,19,0) -> #N/A | L13: =IFERROR(([1]!b_stm07_bs($A13,47,$A$1,1,100000000))/[1]!b_stm07_bs($A13,109,$A$1,1,100000000),"") -> 0.072509519 | O13: =RANK(N13,N$5:N$192,1)&" "&COUNTIF(N$5:N$192,">0") -> #N/A | P13: =IF(IFERROR(R13+AB13/100,"")=0,"",IFERROR(R13+AB13/100,"")) -> 0.014843829 | Q13: =RANK(P13,P$5:P$192,1)&" "&COUNTIF(P$5:P$192,">0") -> 22 169 | R13: =IFERROR([1]!s_stmnote_bank($A13,"34",$A$1,100000000)/[1]!s_stmnote_bank_1n(A13,$A$1,1,100000000),"") -> 0.0059438291 | Z13: =[1]!b_stm07_bs(A13,74,$A$1,1,100000000) -> 791.44588 | AA13: =[1]!b_stm07_bs(A13,109,$A$1,1,100000000) -> 619.80745 | AB13: =[1]!s_stmnote_bank_5n(A13,$A$1,1) -> 0.89 | AC13: =IF([1]!s_stmnote_bank_23n(A13,$A$1,1)=0,"",IFERROR([1]!s_stmnote_bank_23n(A13,$A$1,1),"")) -> 612.89 | AD13: =RANK(AC13,AC$5:AC$192,1)&" "&COUNTIF(AC$5:AC$192,">0") -> 157 167 | AE13: =[1]!s_stmnote_bank_capadequacyratio(A13,$A$1,1) -> 17.7027 | AF13: =IF([1]!s_stmnote_bank_capadequacyratio_ct1(A13,$A$1,1)=0,"",IFERROR([1]!s_stmnote_bank_capadequacyratio_ct1(A13,$A$1,1),"")) -> 16.6497 | AG13: =RANK(AF13,AF$5:AF$192,1)&" "&COUNTIF(AF$5:AF$192,">0") -> 162 167 | AH13: =IF(OR([1]!s_fa_roe(A13,20201231)=0,[1]!s_fa_roe(A13,20211231)="0",[1]!s_fa_roe(A13,20221231)="0"),"",IFERROR(([1]!s_fa_roe(A13,20221231)+[1]!s_fa_roe(A13,20201231)+[1]!s_fa_roe(A13,20211231))/3,"")) -> 14.826833 | AI13: =RANK(AH13,AH$5:AH$192,1)&" "&COUNTIF(AH$5:AH$192,">0") -> 168 173 | AJ13: =IFERROR(([1]!s_stmnote_bank_65(A13,$A$1,1,2,4,100000000)+[1]!s_stmnote_bank_65(A13,$A$1,1,2,6,100000000))/[1]!s_stmnote_bank_1n(A13,$A$1,1,100000000),"") -> 0.035761121 | AK13: =IFERROR([1]!s_stmnote_bank_614(A13,$A$1,1,2,100000000)/[1]!s_stmnote_bank_647(A13,$A$1,1,2,100000000),"") -> 0.13137547 | AL13: =IFERROR(([1]!b_stm07_bs(A13,104,$A$1,1,100000000)+[1]!b_stm07_bs(A13,106,$A$1,1,100000000)+[1]!b_stm07_bs(A13,76,$A$1,1,100000000)+[1]!b_stm07_bs(A13,108,$A$1,1,100000000)+[1]!b_stm07_bs(A13,95,$A$1,1,100000000))/[1]!b_stm07_bs(A13,128,$A$1,1,100000000),"") -> 0.050138549 | AM13: =IFERROR(([1]!s_stmnote_bank_614(A13,$A$1,1,2,100000000)+[1]!b_stm07_bs(A13,104,$A$1,1,100000000)+[1]!b_stm07_bs(A13,106,$A$1,1,100000000)+[1]!b_stm07_bs(A13,76,$A$1,1,100000000)+[1]!b_stm07_bs(A13,108,$A$1,1,100000000)+[1]!b_stm07_bs(A13,95,$A$1,1,100000000))/[1]!b_stm07_bs(A13,128,$A$1,1,100000000),"") -> 0.16543685 | AN13: =IF(Z13>#REF!,#REF!,IF(Z13>#REF!,#REF!,IF(Z13>#REF!,#REF!,IF(Z13>#REF!,#REF!,IF(Z13>#REF!,#REF!,IF(Z13>#REF!,#REF!,IF(Z13>#REF!,#REF!,#REF!))))))) -> #REF! | AO13: =IF(AA13>#REF!,#REF!,IF(AA13>#REF!,#REF!,IF(AA13>#REF!,#REF!,IF(AA13>#REF!,#REF!,IF(AA13>#REF!,#REF!,IF(AA13>#REF!,#REF!,IF(AA13>#REF!,#REF!,#REF!))))))) -> #REF! | AP13: =IF(AB13<#REF!,#REF!,IF(AB13<#REF!,#REF!,IF(AB13<#REF!,#REF!,IF(AB13<#REF!,#REF!,IF(AB13<#REF!,#REF!,IF(AB13<#REF!,#REF!,#REF!)))))) -> #REF! | AQ13: =IF(AC13>#REF!,#REF!,IF(AC13>#REF!,#REF!,IF(AC13>#REF!,#REF!,IF(AC13>#REF!,#REF!,#REF!)))) -> #REF! | AR13: =IF(AE13>#REF!,#REF!,IF(AE13>#REF!,#REF!,IF(AE13>#REF!,#REF!,IF(AE13>#REF!,#REF!,#REF!)))) -> #REF! | AS13: =IF(AF13>#REF!,#REF!,IF(AF13>#REF!,#REF!,IF(AF13>#REF!,#REF!,IF(AF13>#REF!,#REF!,#REF!)))) -> #REF! | AT13: =IF(AH13>#REF!,#REF!,IF(AH13>#REF!,#REF!,IF(AH13>#REF!,#REF!,IF(AH13>#REF!,#REF!,IF(AH13>#REF!,#REF!,#REF!))))) -> #REF! | AU13: =AN13*$AN$3+AP13*$AP$3+AQ13*$AQ$3+AR13*$AR$3+AS13*$AS$3+AT13*$AT$3+$AO$3*AO13 -> #REF! | AY13: =IFERROR(VLOOKUP(AV13,#REF!,3,0),"") | AZ13: =IFERROR(VLOOKUP(AW13,#REF!,3,0),"") | BA13: =IFERROR(VLOOKUP(AX13,#REF!,3,0),"") | BB13: =IFERROR(AY13*#REF!+AZ13*#REF!+BA13*#REF!,"") | BC13: =IFERROR(AU13*0.6+BB13*0.4,"") | BD13: =IFERROR(VLOOKUP(BC13*10,#REF!,2,1),"") | BH13: 上海上丰集团有限公司 | BI13: 5.0323 | BK13: 乐清市 | BL13: =IF([1]!s_stmnote_bank_17n(A13,$A$1,1)="0","",[1]!s_stmnote_bank_17n(A13,$A$1,1)) -> 0.69 | BM13: =IF([1]!s_stmnote_bank_18n(A13,$A$1,1)="0","",[1]!s_stmnote_bank_18n(A13,$A$1,1)) -> 4.36 | BP13: =[1]!s_stmnote_bank_5444(A13,$A$1,1) -> 3.12 | BQ13: =[1]!s_stmnote_bank_129n($A13,$A$1,1) -> 22.4 | BR13: =IFERROR(BS13/SUMPRODUCT(BT13:BX13,$BT$4:$BX$4)*SUMIFS($BT$4:$BX$4,BT13:BX13,">0")*100,0) -> 5.5560919 | BS13: =[1]!b_stm07_is(A13,19,$A$1,1,100000000) -> 39.74253 | BT13: =[1]!s_stm07_bs(A13,"W15273164",$A$1,1,100000000)-[1]!s_stm07_bs(A13,"W17642530",$A$1,1,100000000)-[1]!s_stm07_bs(A13,"W15910877",$A$1,1,100000000)-[1]!s_stm07_bs_39(A13,$A$1,1,100000000)-[1]!s_stm07_bs(A13,"W17700468",$A$1,1,100000000)-[1]!s_stm07_bs(A13,"W16504296",$A$1,1,100000000)-[1]!s_stm07_bs(A13,"W13769069",$A$1,1,100000000) -> 781.46527 | BU13: =[1]!s_stm07_bs(A13,"W15273164",$B$1,1,100000000)-[1]!s_stm07_bs(A13,"W17642530",$B$1,1,100000000)-[1]!s_stm07_bs(A13,"W15910877",$B$1,1,100000000)-[1]!s_stm07_bs_39(A13,$B$1,1,100000000)-[1]!s_stm07_bs(A13,"W17700468",$B$1,1,100000000)-[1]!s_stm07_bs(A13,"W16504296",$B$1,1,100000000)-[1]!s_stm07_bs(A13,"W13769069",$B$1,1,100000000) -> 703.56784 | BV13: =[1]!s_stm07_bs(A13,"W15273164",$E$1,1,100000000)-[1]!s_stm07_bs(A13,"W17642530",$E$1,1,100000000)-[1]!s_stm07_bs(A13,"W15910877",$E$1,1,100000000)-[1]!s_stm07_bs_39(A13,$E$1,1,100000000)-[1]!s_stm07_bs(A13,"W17700468",$E$1,1,100000000)-[1]!s_stm07_bs(A13,"W16504296",$E$1,1,100000000)-[1]!s_stm07_bs(A13,"W13769069",$E$1,1,100000000) -> 747.16 | BW13: =[1]!s_stm07_bs(A13,"W15273164",$F$1,1,100000000)-[1]!s_stm07_bs(A13,"W17642530",$F$1,1,100000000)-[1]!s_stm07_bs(A13,"W15910877",$F$1,1,100000000)-[1]!s_stm07_bs_39(A13,$F$1,1,100000000)-[1]!s_stm07_bs(A13,"W17700468",$F$1,1,100000000)-[1]!s_stm07_bs(A13,"W16504296",$F$1,1,100000000)-[1]!s_stm07_bs(A13,"W13769069",$F$1,1,100000000) -> 0 | BX13: =[1]!s_stm07_bs(A13,"W15273164",$G$1,1,100000000)-[1]!s_stm07_bs(A13,"W17642530",$G$1,1,100000000)-[1]!s_stm07_bs(A13,"W15910877",$G$1,1,100000000)-[1]!s_stm07_bs_39(A13,$G$1,1,100000000)-[1]!s_stm07_bs(A13,"W17700468",$G$1,1,100000000)-[1]!s_stm07_bs(A13,"W16504296",$G$1,1,100000000)-[1]!s_stm07_bs(A13,"W13769069",$G$1,1,100000000) -> 0 | BY13: =IFERROR([1]!b_stm07_is(A13,20,$A$1,1,100000000)/AVERAGEIF(CA13:CE13,">0")*100,0) -> 2.4929726 | BZ13: =[1]!b_stm07_is(A13,20,$A$1,1,100000000) -> 16.543205 | CA13: =[1]!s_stmnote_bank_38(A13,$A$1,1,100000000) -> 701.74122 | CB13: =[1]!s_stmnote_bank_38(A13,$B$1,1,100000000) -> 625.4459 | CC13: =[1]!s_stmnote_bank_38(A13,$E$1,1,100000000) -> 0 | CD13: =[1]!s_stmnote_bank_38(A13,$F$1,1,100000000) -> 0 | CE13: =[1]!s_stmnote_bank_38(A13,$G$1,1,100000000) -> 0 | CF13: =IF(BP13<>0,BP13,IFERROR(IF(([1]!b_stm07_is(A13,19,$A$1,1,100000000)-[1]!b_stm07_is(A13,20,$A$1,1,100000000))/AVERAGE([1]!s_stmnote_bank_35(A13,$A$1,1,100000000),[1]!s_stmnote_bank_35(A13,$B$1,1,100000000))*100=0,"",([1]!b_stm07_is(A13,19,$A$1,1,100000000)-[1]!b_stm07_is(A13,20,$A$1,1,100000000))/AVERAGE([1]!s_stmnote_bank_35(A13,$A$1,1,100000000),[1]!s_stmnote_bank_35(A13,$B$1,1,100000000))*100),"")) -> 3.12 | CG13: =RANK(CF13,CF$5:CF$192,0)&" "&COUNTIF(CF$5:CF$192,">0") -> 8 171 | CH13: =IFERROR(CF13/100/P13,"") -> 2.1018835 | CI13: =RANK(CH13,CH$5:CH$192,0)&" "&COUNTIF(CH$5:CH$192,">0") -> 7 169 | CJ13: =[1]!s_stmnote_bank_30(A13,$A$1,1) -> 10.0196 | CP13: =[1]!b_stm07_bs($A13,141,$A$1,1,100000000) -> 85.212631 | CQ13: =[1]!b_stm07_bs($A13,141,$D$1,1,100000000) -> 0 | CR13: =IF([1]!s_fa_roic_yearly($A13,$A$1)=0,"",[1]!s_fa_roic_yearly($A13,$A$1)) -> 14.9724 | CS13: =RANK(CR13,CR$5:CR$192,0)/COUNTIF(CR$5:CR$192,">0") -> 0.047337278 | CT13: =IF([1]!s_fa_roic_yearly($A13,$D$1)=0,"",[1]!s_fa_roic_yearly($A13,$D$1)) -> 13.658 | CU13: =RANK(CT13,CT$5:CT$192,0)/COUNTIF(CT$5:CT$192,">0") -> 0.15492958 | CV13: =[1]!s_stm07_bs(A13,"W14578191",$A$1,1,100000000) -> 466.39016 | CW13: =[1]!s_stmnote_bank_682($A13,$A$1,1,2,100000000) -> 424.27742 | CX13: =IF(CW13*CV13=0,"",CW13/CV13) -> 0.90970491
A14: 111770247 | B14: 绍兴银行股份有限公司 | C14: 绍兴银行 | D14: 城商行 | F14: AA+ | H14: BB | J14: =VLOOKUP(B14,[3]额度信息!$B:$T,19,0) -> #N/A | L14: =IFERROR(([1]!b_stm07_bs($A14,47,$A$1,1,100000000))/[1]!b_stm07_bs($A14,109,$A$1,1,100000000),"") -> 0.16143522 | O14: =RANK(N14,N$5:N$192,1)&" "&COUNTIF(N$5:N$192,">0") -> #N/A | P14: =IF(IFERROR(R14+AB14/100,"")=0,"",IFERROR(R14+AB14/100,"")) -> 0.0236376 | Q14: =RANK(P14,P$5:P$192,1)&" "&COUNTIF(P$5:P$192,">0") -> 54 169 | R14: =IFERROR([1]!s_stmnote_bank($A14,"34",$A$1,100000000)/[1]!s_stmnote_bank_1n(A14,$A$1,1,100000000),"") -> 0.0139376 | Z14: =[1]!b_stm07_bs(A14,74,$A$1,1,100000000) -> 1848.016 | AA14: =[1]!b_stm07_bs(A14,109,$A$1,1,100000000) -> 1177.6396 | AB14: =[1]!s_stmnote_bank_5n(A14,$A$1,1) -> 0.97 | AC14: =IF([1]!s_stmnote_bank_23n(A14,$A$1,1)=0,"",IFERROR([1]!s_stmnote_bank_23n(A14,$A$1,1),"")) -> 309.97 | AD14: =RANK(AC14,AC$5:AC$192,1)&" "&COUNTIF(AC$5:AC$192,">0") -> 112 167 | AE14: =[1]!s_stmnote_bank_capadequacyratio(A14,$A$1,1) -> 13.26 | AF14: =IF([1]!s_stmnote_bank_capadequacyratio_ct1(A14,$A$1,1)=0,"",IFERROR([1]!s_stmnote_bank_capadequacyratio_ct1(A14,$A$1,1),"")) -> 8.42 | AG14: =RANK(AF14,AF$5:AF$192,1)&" "&COUNTIF(AF$5:AF$192,">0") -> 21 167 | AH14: =IF(OR([1]!s_fa_roe(A14,20201231)=0,[1]!s_fa_roe(A14,20211231)="0",[1]!s_fa_roe(A14,20221231)="0"),"",IFERROR(([1]!s_fa_roe(A14,20221231)+[1]!s_fa_roe(A14,20201231)+[1]!s_fa_roe(A14,20211231))/3,"")) -> 9.3835667 | AI14: =RANK(AH14,AH$5:AH$192,1)&" "&COUNTIF(AH$5:AH$192,">0") -> 104 173 | AJ14: =IFERROR(([1]!s_stmnote_bank_65(A14,$A$1,1,2,4,100000000)+[1]!s_stmnote_bank_65(A14,$A$1,1,2,6,100000000))/[1]!s_stmnote_bank_1n(A14,$A$1,1,100000000),"") -> 0.11130497 | AK14: =IFERROR([1]!s_stmnote_bank_614(A14,$A$1,1,2,100000000)/[1]!s_stmnote_bank_647(A14,$A$1,1,2,100000000),"") -> 0.33974789 | AL14: =IFERROR(([1]!b_stm07_bs(A14,104,$A$1,1,100000000)+[1]!b_stm07_bs(A14,106,$A$1,1,100000000)+[1]!b_stm07_bs(A14,76,$A$1,1,100000000)+[1]!b_stm07_bs(A14,108,$A$1,1,100000000)+[1]!b_stm07_bs(A14,95,$A$1,1,100000000))/[1]!b_stm07_bs(A14,128,$A$1,1,100000000),"") -> 0.22711957 | AM14: =IFERROR(([1]!s_stmnote_bank_614(A14,$A$1,1,2,100000000)+[1]!b_stm07_bs(A14,104,$A$1,1,100000000)+[1]!b_stm07_bs(A14,106,$A$1,1,100000000)+[1]!b_stm07_bs(A14,76,$A$1,1,100000000)+[1]!b_stm07_bs(A14,108,$A$1,1,100000000)+[1]!b_stm07_bs(A14,95,$A$1,1,100000000))/[1]!b_stm07_bs(A14,128,$A$1,1,100000000),"") -> 0.45836054 | AN14: =IF(Z14>#REF!,#REF!,IF(Z14>#REF!,#REF!,IF(Z14>#REF!,#REF!,IF(Z14>#REF!,#REF!,IF(Z14>#REF!,#REF!,IF(Z14>#REF!,#REF!,IF(Z14>#REF!,#REF!,#REF!))))))) -> #REF! | AO14: =IF(AA14>#REF!,#REF!,IF(AA14>#REF!,#REF!,IF(AA14>#REF!,#REF!,IF(AA14>#REF!,#REF!,IF(AA14>#REF!,#REF!,IF(AA14>#REF!,#REF!,IF(AA14>#REF!,#REF!,#REF!))))))) -> #REF! | AP14: =IF(AB14<#REF!,#REF!,IF(AB14<#REF!,#REF!,IF(AB14<#REF!,#REF!,IF(AB14<#REF!,#REF!,IF(AB14<#REF!,#REF!,IF(AB14<#REF!,#REF!,#REF!)))))) -> #REF! | AQ14: =IF(AC14>#REF!,#REF!,IF(AC14>#REF!,#REF!,IF(AC14>#REF!,#REF!,IF(AC14>#REF!,#REF!,#REF!)))) -> #REF! | AR14: =IF(AE14>#REF!,#REF!,IF(AE14>#REF!,#REF!,IF(AE14>#REF!,#REF!,IF(AE14>#REF!,#REF!,#REF!)))) -> #REF! | AS14: =IF(AF14>#REF!,#REF!,IF(AF14>#REF!,#REF!,IF(AF14>#REF!,#REF!,IF(AF14>#REF!,#REF!,#REF!)))) -> #REF! | AT14: =IF(AH14>#REF!,#REF!,IF(AH14>#REF!,#REF!,IF(AH14>#REF!,#REF!,IF(AH14>#REF!,#REF!,IF(AH14>#REF!,#REF!,#REF!))))) -> #REF! | AU14: =AN14*$AN$3+AP14*$AP$3+AQ14*$AQ$3+AR14*$AR$3+AS14*$AS$3+AT14*$AT$3+$AO$3*AO14 -> #REF! | AY14: =IFERROR(VLOOKUP(AV14,#REF!,3,0),"") | AZ14: =IFERROR(VLOOKUP(AW14,#REF!,3,0),"") | BA14: =IFERROR(VLOOKUP(AX14,#REF!,3,0),"") | BB14: =IFERROR(AY14*#REF!+AZ14*#REF!+BA14*#REF!,"") | BC14: =IFERROR(AU14*0.6+BB14*0.4,"") | BD14: =IFERROR(VLOOKUP(BC14*10,#REF!,2,1),"") | BH14: 绍兴市金融控股有限公司 | BI14: 19.940001 | BJ14: 浙江 | BK14: 绍兴市 | BL14: =IF([1]!s_stmnote_bank_17n(A14,$A$1,1)="0","",[1]!s_stmnote_bank_17n(A14,$A$1,1)) -> 4.79 | BM14: =IF([1]!s_stmnote_bank_18n(A14,$A$1,1)="0","",[1]!s_stmnote_bank_18n(A14,$A$1,1)) -> 0 | BP14: =[1]!s_stmnote_bank_5444(A14,$A$1,1) -> 1.99 | BQ14: =[1]!s_stmnote_bank_129n($A14,$A$1,1) -> 34.12 | BR14: =IFERROR(BS14/SUMPRODUCT(BT14:BX14,$BT$4:$BX$4)*SUMIFS($BT$4:$BX$4,BT14:BX14,">0")*100,0) -> 4.4954686 | BS14: =[1]!b_stm07_is(A14,19,$A$1,1,100000000) -> 70.03739 | BT14: =[1]!s_stm07_bs(A14,"W15273164",$A$1,1,100000000)-[1]!s_stm07_bs(A14,"W17642530",$A$1,1,100000000)-[1]!s_stm07_bs(A14,"W15910877",$A$1,1,100000000)-[1]!s_stm07_bs_39(A14,$A$1,1,100000000)-[1]!s_stm07_bs(A14,"W17700468",$A$1,1,100000000)-[1]!s_stm07_bs(A14,"W16504296",$A$1,1,100000000)-[1]!s_stm07_bs(A14,"W13769069",$A$1,1,100000000) -> 1826.0768 | BU14: =[1]!s_stm07_bs(A14,"W15273164",$B$1,1,100000000)-[1]!s_stm07_bs(A14,"W17642530",$B$1,1,100000000)-[1]!s_stm07_bs(A14,"W15910877",$B$1,1,100000000)-[1]!s_stm07_bs_39(A14,$B$1,1,100000000)-[1]!s_stm07_bs(A14,"W17700468",$B$1,1,100000000)-[1]!s_stm07_bs(A14,"W16504296",$B$1,1,100000000)-[1]!s_stm07_bs(A14,"W13769069",$B$1,1,100000000) -> 1519.6522 | BV14: =[1]!s_stm07_bs(A14,"W15273164",$E$1,1,100000000)-[1]!s_stm07_bs(A14,"W17642530",$E$1,1,100000000)-[1]!s_stm07_bs(A14,"W15910877",$E$1,1,100000000)-[1]!s_stm07_bs_39(A14,$E$1,1,100000000)-[1]!s_stm07_bs(A14,"W17700468",$E$1,1,100000000)-[1]!s_stm07_bs(A14,"W16504296",$E$1,1,100000000)-[1]!s_stm07_bs(A14,"W13769069",$E$1,1,100000000) -> 0 | BW14: =[1]!s_stm07_bs(A14,"W15273164",$F$1,1,100000000)-[1]!s_stm07_bs(A14,"W17642530",$F$1,1,100000000)-[1]!s_stm07_bs(A14,"W15910877",$F$1,1,100000000)-[1]!s_stm07_bs_39(A14,$F$1,1,100000000)-[1]!s_stm07_bs(A14,"W17700468",$F$1,1,100000000)-[1]!s_stm07_bs(A14,"W16504296",$F$1,1,100000000)-[1]!s_stm07_bs(A14,"W13769069",$F$1,1,100000000) -> 0 | BX14: =[1]!s_stm07_bs(A14,"W15273164",$G$1,1,100000000)-[1]!s_stm07_bs(A14,"W17642530",$G$1,1,100000000)-[1]!s_stm07_bs(A14,"W15910877",$G$1,1,100000000)-[1]!s_stm07_bs_39(A14,$G$1,1,100000000)-[1]!s_stm07_bs(A14,"W17700468",$G$1,1,100000000)-[1]!s_stm07_bs(A14,"W16504296",$G$1,1,100000000)-[1]!s_stm07_bs(A14,"W13769069",$G$1,1,100000000) -> 0 | BY14: =IFERROR([1]!b_stm07_is(A14,20,$A$1,1,100000000)/AVERAGEIF(CA14:CE14,">0")*100,0) -> 2.5056382 | BZ14: =[1]!b_stm07_is(A14,20,$A$1,1,100000000) -> 39.24879 | CA14: =[1]!s_stmnote_bank_38(A14,$A$1,1,100000000) -> 1711.6179 | CB14: =[1]!s_stmnote_bank_38(A14,$B$1,1,100000000) -> 1421.2199 | CC14: =[1]!s_stmnote_bank_38(A14,$E$1,1,100000000) -> 0 | CD14: =[1]!s_stmnote_bank_38(A14,$F$1,1,100000000) -> 0 | CE14: =[1]!s_stmnote_bank_38(A14,$G$1,1,100000000) -> 0 | CF14: =IF(BP14<>0,BP14,IFERROR(IF(([1]!b_stm07_is(A14,19,$A$1,1,100000000)-[1]!b_stm07_is(A14,20,$A$1,1,100000000))/AVERAGE([1]!s_stmnote_bank_35(A14,$A$1,1,100000000),[1]!s_stmnote_bank_35(A14,$B$1,1,100000000))*100=0,"",([1]!b_stm07_is(A14,19,$A$1,1,100000000)-[1]!b_stm07_is(A14,20,$A$1,1,100000000))/AVERAGE([1]!s_stmnote_bank_35(A14,$A$1,1,100000000),[1]!s_stmnote_bank_35(A14,$B$1,1,100000000))*100),"")) -> 1.99 | CG14: =RANK(CF14,CF$5:CF$192,0)&" "&COUNTIF(CF$5:CF$192,">0") -> 94 171 | CH14: =IFERROR(CF14/100/P14,"") -> 0.84187905 | CI14: =RANK(CH14,CH$5:CH$192,0)&" "&COUNTIF(CH$5:CH$192,">0") -> 59 169 | CJ14: =[1]!s_stmnote_bank_30(A14,$A$1,1) -> 15.2869 | CP14: =[1]!b_stm07_bs($A14,141,$A$1,1,100000000) -> 117.78387 | CQ14: =[1]!b_stm07_bs($A14,141,$D$1,1,100000000) -> 0 | CR14: =IF([1]!s_fa_roic_yearly($A14,$A$1)=0,"",[1]!s_fa_roic_yearly($A14,$A$1)) -> 11.3288 | CS14: =RANK(CR14,CR$5:CR$192,0)/COUNTIF(CR$5:CR$192,">0") -> 0.21301775 | CT14: =IF([1]!s_fa_roic_yearly($A14,$D$1)=0,"",[1]!s_fa_roic_yearly($A14,$D$1)) | CU14: =RANK(CT14,CT$5:CT$192,0)/COUNTIF(CT$5:CT$192,">0") -> #VALUE! | CV14: =[1]!s_stm07_bs(A14,"W14578191",$A$1,1,100000000) -> 1032.7227 | CW14: =[1]!s_stmnote_bank_682($A14,$A$1,1,2,100000000) -> 270.36474 | CX14: =IF(CW14*CV14=0,"",CW14/CV14) -> 0.26179801
A15: 1826001.IB | B15: 大华银行(中国)有限公司 | C15: 大华银行(中国) | D15: 外资行 | E15: 有普通 | F15: AAA | H15: BB- | J15: =VLOOKUP(B15,[3]额度信息!$B:$T,19,0) -> #N/A | K15: 主要与母行协同服务集团客户，表观资产质量较好，资本安全垫充足；规模偏小，费用效率很低导致盈利很差，同时地产占比偏高，严重依赖同业资金，下调2级；集团支持提1级 | L15: =IFERROR(([1]!b_stm07_bs($A15,47,$A$1,1,100000000))/[1]!b_stm07_bs($A15,109,$A$1,1,100000000),"") -> 0.14874335 | O15: =RANK(N15,N$5:N$192,1)&" "&COUNTIF(N$5:N$192,">0") -> #N/A | P15: =IF(IFERROR(R15+AB15/100,"")=0,"",IFERROR(R15+AB15/100,"")) -> 0.0074108891 | Q15: =RANK(P15,P$5:P$192,1)&" "&COUNTIF(P$5:P$192,">0") -> 5 169 | R15: =IFERROR([1]!s_stmnote_bank($A15,"34",$A$1,100000000)/[1]!s_stmnote_bank_1n(A15,$A$1,1,100000000),"") -> 0.0042108891 | Z15: =[1]!b_stm07_bs(A15,74,$A$1,1,100000000) -> 782.20119 | AA15: =[1]!b_stm07_bs(A15,109,$A$1,1,100000000) -> 417.12748 | AB15: =[1]!s_stmnote_bank_5n(A15,$A$1,1) -> 0.32 | AC15: =IF([1]!s_stmnote_bank_23n(A15,$A$1,1)=0,"",IFERROR([1]!s_stmnote_bank_23n(A15,$A$1,1),"")) -> 796.3 | AD15: =RANK(AC15,AC$5:AC$192,1)&" "&COUNTIF(AC$5:AC$192,">0") -> 163 167 | AE15: =[1]!s_stmnote_bank_capadequacyratio(A15,$A$1,1) -> 16 | AF15: =IF([1]!s_stmnote_bank_capadequacyratio_ct1(A15,$A$1,1)=0,"",IFERROR([1]!s_stmnote_bank_capadequacyratio_ct1(A15,$A$1,1),"")) -> 13.2 | AG15: =RANK(AF15,AF$5:AF$192,1)&" "&COUNTIF(AF$5:AF$192,">0") -> 142 167 | AH15: =IF(OR([1]!s_fa_roe(A15,20201231)=0,[1]!s_fa_roe(A15,20211231)="0",[1]!s_fa_roe(A15,20221231)="0"),"",IFERROR(([1]!s_fa_roe(A15,20221231)+[1]!s_fa_roe(A15,20201231)+[1]!s_fa_roe(A15,20211231))/3,"")) -> 3.9833333 | AI15: =RANK(AH15,AH$5:AH$192,1)&" "&COUNTIF(AH$5:AH$192,">0") -> 20 173 | AJ15: =IFERROR(([1]!s_stmnote_bank_65(A15,$A$1,1,2,4,100000000)+[1]!s_stmnote_bank_65(A15,$A$1,1,2,6,100000000))/[1]!s_stmnote_bank_1n(A15,$A$1,1,100000000),"") -> 0.26142807 | AK15: =IFERROR([1]!s_stmnote_bank_614(A15,$A$1,1,2,100000000)/[1]!s_stmnote_bank_647(A15,$A$1,1,2,100000000),"") -> 0.41005917 | AL15: =IFERROR(([1]!b_stm07_bs(A15,104,$A$1,1,100000000)+[1]!b_stm07_bs(A15,106,$A$1,1,100000000)+[1]!b_stm07_bs(A15,76,$A$1,1,100000000)+[1]!b_stm07_bs(A15,108,$A$1,1,100000000)+[1]!b_stm07_bs(A15,95,$A$1,1,100000000))/[1]!b_stm07_bs(A15,128,$A$1,1,100000000),"") -> 0.33593055 | AM15: =IFERROR(([1]!s_stmnote_bank_614(A15,$A$1,1,2,100000000)+[1]!b_stm07_bs(A15,104,$A$1,1,100000000)+[1]!b_stm07_bs(A15,106,$A$1,1,100000000)+[1]!b_stm07_bs(A15,76,$A$1,1,100000000)+[1]!b_stm07_bs(A15,108,$A$1,1,100000000)+[1]!b_stm07_bs(A15,95,$A$1,1,100000000))/[1]!b_stm07_bs(A15,128,$A$1,1,100000000),"") -> 0.57764394 | AN15: =IF(Z15>#REF!,#REF!,IF(Z15>#REF!,#REF!,IF(Z15>#REF!,#REF!,IF(Z15>#REF!,#REF!,IF(Z15>#REF!,#REF!,IF(Z15>#REF!,#REF!,IF(Z15>#REF!,#REF!,#REF!))))))) -> #REF! | AO15: =IF(AA15>#REF!,#REF!,IF(AA15>#REF!,#REF!,IF(AA15>#REF!,#REF!,IF(AA15>#REF!,#REF!,IF(AA15>#REF!,#REF!,IF(AA15>#REF!,#REF!,IF(AA15>#REF!,#REF!,#REF!))))))) -> #REF! | AP15: =IF(AB15<#REF!,#REF!,IF(AB15<#REF!,#REF!,IF(AB15<#REF!,#REF!,IF(AB15<#REF!,#REF!,IF(AB15<#REF!,#REF!,IF(AB15<#REF!,#REF!,#REF!)))))) -> #REF! | AQ15: =IF(AC15>#REF!,#REF!,IF(AC15>#REF!,#REF!,IF(AC15>#REF!,#REF!,IF(AC15>#REF!,#REF!,#REF!)))) -> #REF! | AR15: =IF(AE15>#REF!,#REF!,IF(AE15>#REF!,#REF!,IF(AE15>#REF!,#REF!,IF(AE15>#REF!,#REF!,#REF!)))) -> #REF! | AS15: =IF(AF15>#REF!,#REF!,IF(AF15>#REF!,#REF!,IF(AF15>#REF!,#REF!,IF(AF15>#REF!,#REF!,#REF!)))) -> #REF! | AT15: =IF(AH15>#REF!,#REF!,IF(AH15>#REF!,#REF!,IF(AH15>#REF!,#REF!,IF(AH15>#REF!,#REF!,IF(AH15>#REF!,#REF!,#REF!))))) -> #REF! | AU15: =AN15*$AN$3+AP15*$AP$3+AQ15*$AQ$3+AR15*$AR$3+AS15*$AS$3+AT15*$AT$3+$AO$3*AO15 -> #REF! | AV15: 强 | AW15: 较低 | AX15: 好 | AY15: =IFERROR(VLOOKUP(AV15,#REF!,3,0),"") | AZ15: =IFERROR(VLOOKUP(AW15,#REF!,3,0),"") | BA15: =IFERROR(VLOOKUP(AX15,#REF!,3,0),"") | BB15: =IFERROR(AY15*#REF!+AZ15*#REF!+BA15*#REF!,"") | BC15: =IFERROR(AU15*0.6+BB15*0.4,"") | BD15: =IFERROR(VLOOKUP(BC15*10,#REF!,2,1),"") | BE15: 1 | BF15: -3 | BG15: 地产敞口-2，负债不稳-1（已压降并增资） | BH15: 大华银行有限公司 | BI15: 100 | BJ15: 上海 | BK15: 上海市 | BL15: =IF([1]!s_stmnote_bank_17n(A15,$A$1,1)="0","",[1]!s_stmnote_bank_17n(A15,$A$1,1)) -> 7.93 | BM15: =IF([1]!s_stmnote_bank_18n(A15,$A$1,1)="0","",[1]!s_stmnote_bank_18n(A15,$A$1,1)) -> 55.24 | BP15: =[1]!s_stmnote_bank_5444(A15,$A$1,1) -> 1.66 | BQ15: =[1]!s_stmnote_bank_129n($A15,$A$1,1) -> 65.7 | BR15: =IFERROR(BS15/SUMPRODUCT(BT15:BX15,$BT$4:$BX$4)*SUMIFS($BT$4:$BX$4,BT15:BX15,">0")*100,0) -> 2.662346 | BS15: =[1]!b_stm07_is(A15,19,$A$1,1,100000000) -> 20.922266 | BT15: =[1]!s_stm07_bs(A15,"W15273164",$A$1,1,100000000)-[1]!s_stm07_bs(A15,"W17642530",$A$1,1,100000000)-[1]!s_stm07_bs(A15,"W15910877",$A$1,1,100000000)-[1]!s_stm07_bs_39(A15,$A$1,1,100000000)-[1]!s_stm07_bs(A15,"W17700468",$A$1,1,100000000)-[1]!s_stm07_bs(A15,"W16504296",$A$1,1,100000000)-[1]!s_stm07_bs(A15,"W13769069",$A$1,1,100000000) -> 774.86499 | BU15: =[1]!s_stm07_bs(A15,"W15273164",$B$1,1,100000000)-[1]!s_stm07_bs(A15,"W17642530",$B$1,1,100000000)-[1]!s_stm07_bs(A15,"W15910877",$B$1,1,100000000)-[1]!s_stm07_bs_39(A15,$B$1,1,100000000)-[1]!s_stm07_bs(A15,"W17700468",$B$1,1,100000000)-[1]!s_stm07_bs(A15,"W16504296",$B$1,1,100000000)-[1]!s_stm07_bs(A15,"W13769069",$B$1,1,100000000) -> 793.10089 | BV15: =[1]!s_stm07_bs(A15,"W15273164",$E$1,1,100000000)-[1]!s_stm07_bs(A15,"W17642530",$E$1,1,100000000)-[1]!s_stm07_bs(A15,"W15910877",$E$1,1,100000000)-[1]!s_stm07_bs_39(A15,$E$1,1,100000000)-[1]!s_stm07_bs(A15,"W17700468",$E$1,1,100000000)-[1]!s_stm07_bs(A15,"W16504296",$E$1,1,100000000)-[1]!s_stm07_bs(A15,"W13769069",$E$1,1,100000000) -> 716.6388 | BW15: =[1]!s_stm07_bs(A15,"W15273164",$F$1,1,100000000)-[1]!s_stm07_bs(A15,"W17642530",$F$1,1,100000000)-[1]!s_stm07_bs(A15,"W15910877",$F$1,1,100000000)-[1]!s_stm07_bs_39(A15,$F$1,1,100000000)-[1]!s_stm07_bs(A15,"W17700468",$F$1,1,100000000)-[1]!s_stm07_bs(A15,"W16504296",$F$1,1,100000000)-[1]!s_stm07_bs(A15,"W13769069",$F$1,1,100000000) -> 783.27176 | BX15: =[1]!s_stm07_bs(A15,"W15273164",$G$1,1,100000000)-[1]!s_stm07_bs(A15,"W17642530",$G$1,1,100000000)-[1]!s_stm07_bs(A15,"W15910877",$G$1,1,100000000)-[1]!s_stm07_bs_39(A15,$G$1,1,100000000)-[1]!s_stm07_bs(A15,"W17700468",$G$1,1,100000000)-[1]!s_stm07_bs(A15,"W16504296",$G$1,1,100000000)-[1]!s_stm07_bs(A15,"W13769069",$G$1,1,100000000) -> 780.8402 | BY15: =IFERROR([1]!b_stm07_is(A15,20,$A$1,1,100000000)/AVERAGEIF(CA15:CE15,">0")*100,0) -> 1.5620831 | BZ15: =[1]!b_stm07_is(A15,20,$A$1,1,100000000) -> 9.8094336 | CA15: =[1]!s_stmnote_bank_38(A15,$A$1,1,100000000) -> 654.8466 | CB15: =[1]!s_stmnote_bank_38(A15,$B$1,1,100000000) -> 608.27888 | CC15: =[1]!s_stmnote_bank_38(A15,$E$1,1,100000000) -> 597.62062 | CD15: =[1]!s_stmnote_bank_38(A15,$F$1,1,100000000) -> 649.70195 | CE15: =[1]!s_stmnote_bank_38(A15,$G$1,1,100000000) -> 629.40853 | CF15: =IF(BP15<>0,BP15,IFERROR(IF(([1]!b_stm07_is(A15,19,$A$1,1,100000000)-[1]!b_stm07_is(A15,20,$A$1,1,100000000))/AVERAGE([1]!s_stmnote_bank_35(A15,$A$1,1,100000000),[1]!s_stmnote_bank_35(A15,$B$1,1,100000000))*100=0,"",([1]!b_stm07_is(A15,19,$A$1,1,100000000)-[1]!b_stm07_is(A15,20,$A$1,1,100000000))/AVERAGE([1]!s_stmnote_bank_35(A15,$A$1,1,100000000),[1]!s_stmnote_bank_35(A15,$B$1,1,100000000))*100),"")) -> 1.66 | CG15: =RANK(CF15,CF$5:CF$192,0)&" "&COUNTIF(CF$5:CF$192,">0") -> 142 171 | CH15: =IFERROR(CF15/100/P15,"") -> 2.2399472 | CI15: =RANK(CH15,CH$5:CH$192,0)&" "&COUNTIF(CH$5:CH$192,">0") -> 6 169 | CJ15: =[1]!s_stmnote_bank_30(A15,$A$1,1) -> 30.4379 | CP15: =[1]!b_stm07_bs($A15,141,$A$1,1,100000000) -> 74.557554 | CQ15: =[1]!b_stm07_bs($A15,141,$D$1,1,100000000) -> 97.191548 | CR15: =IF([1]!s_fa_roic_yearly($A15,$A$1)=0,"",[1]!s_fa_roic_yearly($A15,$A$1)) -> 4.5881 | CS15: =RANK(CR15,CR$5:CR$192,0)/COUNTIF(CR$5:CR$192,">0") -> 0.84023669 | CT15: =IF([1]!s_fa_roic_yearly($A15,$D$1)=0,"",[1]!s_fa_roic_yearly($A15,$D$1)) -> 6.7732 | CU15: =RANK(CT15,CT$5:CT$192,0)/COUNTIF(CT$5:CT$192,">0") -> 0.8028169 | CV15: =[1]!s_stm07_bs(A15,"W14578191",$A$1,1,100000000) -> 391.60105 | CW15: =[1]!s_stmnote_bank_682($A15,$A$1,1,2,100000000) -> 48.470079 | CX15: =IF(CW15*CV15=0,"",CW15/CV15) -> 0.12377413
A16: 111771353 | B16: 宁波鄞州农村商业银行股份有限公司 | C16: 宁波鄞州农村商业银行 | D16: 农商行 | E16: 有次级+普通 | F16: AA+ | G16: BB+ | H16: BB | J16: =VLOOKUP(B16,[3]额度信息!$B:$T,19,0) -> 0 | K16: 主要观点： 1. 该行业务主要集中在宁波市内，当地活跃的经济环境为该行提供了良好的外部发展环境。 2. 该行为全国首家农村合作银行，对宁波鄞州区城乡范围全面覆盖, 本部的存款和贷款规模在鄞州区的市场份额为12.81%和9.08%，在区内分别排名第二和第三。 3. 该行存款稳定性较好。负债端，该行吸收存款1592.79亿，是最主要的负债来源，占比81.83%，其中定期存款占总存款的70.4%，同业负债占比11.38%。 主要关注： 1.该行近年净息差处于同业较低水平。2019-2021年该行净息差分别为2.72%、2.43%、2.35%，生息资产平均收益率约为4.76%（其中近三年贷款平均收益率分别为6.6%、6.7%、6.9%）负债平均利率2.6%（主要系21年该行同业资产和投资资产规模扩张导致成本增加），略高于同业；近3年该行ROE为13.35%、11.14%、10.64%。 2.该行21年不良资产生成率2.05% 处于同业较高位置。考虑到该行整体市场较为下沉，在今年宏观背景下资产质量仍有下行压力（尚未考虑账面有85亿展期/借新还旧贷款），需持续关注未来消化不良资产对其利润和资本的侵蚀。 3. 新并表的村镇银行不良较高。21年该行桂林村行增资扩股后对其进行并表管理，并出资1亿元剥离其不良资产，致使并表村镇银行不良贷款余额大幅上升至15.82亿元（较20年末+9.42亿元），该行下属村镇银行24家，合计投资5.1亿元，处于江浙农商行中高水平 ，目前处于关注类需关注村镇银行的风险暴露情况。 4. 随着业务扩张资本，充足率呈下降态势。近3年该行资本充足率分别为17.32%/16.24%/15.72%，持续下行，但距离监管红线仍较高，且该行21年和22年均发行了15亿元永续债补充资本。 | L16: =IFERROR(([1]!b_stm07_bs($A16,47,$A$1,1,100000000))/[1]!b_stm07_bs($A16,109,$A$1,1,100000000),"") -> 0.10503518 | O16: =RANK(N16,N$5:N$192,1)&" "&COUNTIF(N$5:N$192,">0") -> #N/A | P16: =IF(IFERROR(R16+AB16/100,"")=0,"",IFERROR(R16+AB16/100,"")) -> 0.029629962 | Q16: =RANK(P16,P$5:P$192,1)&" "&COUNTIF(P$5:P$192,">0") -> 83 169 | R16: =IFERROR([1]!s_stmnote_bank($A16,"34",$A$1,100000000)/[1]!s_stmnote_bank_1n(A16,$A$1,1,100000000),"") -> 0.0091299622 | Z16: =[1]!b_stm07_bs(A16,74,$A$1,1,100000000) -> 2136.4943 | AA16: =[1]!b_stm07_bs(A16,109,$A$1,1,100000000) -> 1592.7922 | AB16: =[1]!s_stmnote_bank_5n(A16,$A$1,1) -> 2.05 | AC16: =IF([1]!s_stmnote_bank_23n(A16,$A$1,1)=0,"",IFERROR([1]!s_stmnote_bank_23n(A16,$A$1,1),"")) -> 182.73 | AD16: =RANK(AC16,AC$5:AC$192,1)&" "&COUNTIF(AC$5:AC$192,">0") -> 50 167 | AE16: =[1]!s_stmnote_bank_capadequacyratio(A16,$A$1,1) -> 15.72 | AF16: =IF([1]!s_stmnote_bank_capadequacyratio_ct1(A16,$A$1,1)=0,"",IFERROR([1]!s_stmnote_bank_capadequacyratio_ct1(A16,$A$1,1),"")) -> 12.71 | AG16: =RANK(AF16,AF$5:AF$192,1)&" "&COUNTIF(AF$5:AF$192,">0") -> 135 167 | AH16: =IF(OR([1]!s_fa_roe(A16,20201231)=0,[1]!s_fa_roe(A16,20211231)="0",[1]!s_fa_roe(A16,20221231)="0"),"",IFERROR(([1]!s_fa_roe(A16,20221231)+[1]!s_fa_roe(A16,20201231)+[1]!s_fa_roe(A16,20211231))/3,"")) -> 9.9248667 | AI16: =RANK(AH16,AH$5:AH$192,1)&" "&COUNTIF(AH$5:AH$192,">0") -> 117 173 | AJ16: =IFERROR(([1]!s_stmnote_bank_65(A16,$A$1,1,2,4,100000000)+[1]!s_stmnote_bank_65(A16,$A$1,1,2,6,100000000))/[1]!s_stmnote_bank_1n(A16,$A$1,1,100000000),"") -> 0.024011157 | AK16: =IFERROR([1]!s_stmnote_bank_614(A16,$A$1,1,2,100000000)/[1]!s_stmnote_bank_647(A16,$A$1,1,2,100000000),"") -> 0.15668491 | AL16: =IFERROR(([1]!b_stm07_bs(A16,104,$A$1,1,100000000)+[1]!b_stm07_bs(A16,106,$A$1,1,100000000)+[1]!b_stm07_bs(A16,76,$A$1,1,100000000)+[1]!b_stm07_bs(A16,108,$A$1,1,100000000)+[1]!b_stm07_bs(A16,95,$A$1,1,100000000))/[1]!b_stm07_bs(A16,128,$A$1,1,100000000),"") -> 0.11380769 | AM16: =IFERROR(([1]!s_stmnote_bank_614(A16,$A$1,1,2,100000000)+[1]!b_stm07_bs(A16,104,$A$1,1,100000000)+[1]!b_stm07_bs(A16,106,$A$1,1,100000000)+[1]!b_stm07_bs(A16,76,$A$1,1,100000000)+[1]!b_stm07_bs(A16,108,$A$1,1,100000000)+[1]!b_stm07_bs(A16,95,$A$1,1,100000000))/[1]!b_stm07_bs(A16,128,$A$1,1,100000000),"") -> 0.24145887 | AN16: =IF(Z16>#REF!,#REF!,IF(Z16>#REF!,#REF!,IF(Z16>#REF!,#REF!,IF(Z16>#REF!,#REF!,IF(Z16>#REF!,#REF!,IF(Z16>#REF!,#REF!,IF(Z16>#REF!,#REF!,#REF!))))))) -> #REF! | AO16: =IF(AA16>#REF!,#REF!,IF(AA16>#REF!,#REF!,IF(AA16>#REF!,#REF!,IF(AA16>#REF!,#REF!,IF(AA16>#REF!,#REF!,IF(AA16>#REF!,#REF!,IF(AA16>#REF!,#REF!,#REF!))))))) -> #REF! | AP16: =IF(AB16<#REF!,#REF!,IF(AB16<#REF!,#REF!,IF(AB16<#REF!,#REF!,IF(AB16<#REF!,#REF!,IF(AB16<#REF!,#REF!,IF(AB16<#REF!,#REF!,#REF!)))))) -> #REF! | AQ16: =IF(AC16>#REF!,#REF!,IF(AC16>#REF!,#REF!,IF(AC16>#REF!,#REF!,IF(AC16>#REF!,#REF!,#REF!)))) -> #REF! | AR16: =IF(AE16>#REF!,#REF!,IF(AE16>#REF!,#REF!,IF(AE16>#REF!,#REF!,IF(AE16>#REF!,#REF!,#REF!)))) -> #REF! | AS16: =IF(AF16>#REF!,#REF!,IF(AF16>#REF!,#REF!,IF(AF16>#REF!,#REF!,IF(AF16>#REF!,#REF!,#REF!)))) -> #REF! | AT16: =IF(AH16>#REF!,#REF!,IF(AH16>#REF!,#REF!,IF(AH16>#REF!,#REF!,IF(AH16>#REF!,#REF!,IF(AH16>#REF!,#REF!,#REF!))))) -> #REF! | AU16: =AN16*$AN$3+AP16*$AP$3+AQ16*$AQ$3+AR16*$AR$3+AS16*$AS$3+AT16*$AT$3+$AO$3*AO16 -> #REF! | AV16: 中 | AW16: 低 | AX16: 好 | AY16: =IFERROR(VLOOKUP(AV16,#REF!,3,0),"") | AZ16: =IFERROR(VLOOKUP(AW16,#REF!,3,0),"") | BA16: =IFERROR(VLOOKUP(AX16,#REF!,3,0),"") | BB16: =IFERROR(AY16*#REF!+AZ16*#REF!+BA16*#REF!,"") | BC16: =IFERROR(AU16*0.6+BB16*0.4,"") | BD16: =IFERROR(VLOOKUP(BC16*10,#REF!,2,1),"") | BE16: 0 | BF16: -1 | BG16: 内控负面-1 | BH16: 宁波华龙投资建设开发有限公司 | BI16: 5.5999999 | BJ16: 浙江 | BK16: 宁波市 | BL16: =IF([1]!s_stmnote_bank_17n(A16,$A$1,1)="0","",[1]!s_stmnote_bank_17n(A16,$A$1,1)) -> 2.01 | BM16: =IF([1]!s_stmnote_bank_18n(A16,$A$1,1)="0","",[1]!s_stmnote_bank_18n(A16,$A$1,1)) -> 13.79 | BP16: =[1]!s_stmnote_bank_5444(A16,$A$1,1) -> 0 | BQ16: =[1]!s_stmnote_bank_129n($A16,$A$1,1) -> 34.77 | BR16: =IFERROR(BS16/SUMPRODUCT(BT16:BX16,$BT$4:$BX$4)*SUMIFS($BT$4:$BX$4,BT16:BX16,">0")*100,0) -> 4.5588966 | BS16: =[1]!b_stm07_is(A16,19,$A$1,1,100000000) -> 79.699913 | BT16: =[1]!s_stm07_bs(A16,"W15273164",$A$1,1,100000000)-[1]!s_stm07_bs(A16,"W17642530",$A$1,1,100000000)-[1]!s_stm07_bs(A16,"W15910877",$A$1,1,100000000)-[1]!s_stm07_bs_39(A16,$A$1,1,100000000)-[1]!s_stm07_bs(A16,"W17700468",$A$1,1,100000000)-[1]!s_stm07_bs(A16,"W16504296",$A$1,1,100000000)-[1]!s_stm07_bs(A16,"W13769069",$A$1,1,100000000) -> 2113.6842 | BU16: =[1]!s_stm07_bs(A16,"W15273164",$B$1,1,100000000)-[1]!s_stm07_bs(A16,"W17642530",$B$1,1,100000000)-[1]!s_stm07_bs(A16,"W15910877",$B$1,1,100000000)-[1]!s_stm07_bs_39(A16,$B$1,1,100000000)-[1]!s_stm07_bs(A16,"W17700468",$B$1,1,100000000)-[1]!s_stm07_bs(A16,"W16504296",$B$1,1,100000000)-[1]!s_stm07_bs(A16,"W13769069",$B$1,1,100000000) -> 1697.8258 | BV16: =[1]!s_stm07_bs(A16,"W15273164",$E$1,1,100000000)-[1]!s_stm07_bs(A16,"W17642530",$E$1,1,100000000)-[1]!s_stm07_bs(A16,"W15910877",$E$1,1,100000000)-[1]!s_stm07_bs_39(A16,$E$1,1,100000000)-[1]!s_stm07_bs(A16,"W17700468",$E$1,1,100000000)-[1]!s_stm07_bs(A16,"W16504296",$E$1,1,100000000)-[1]!s_stm07_bs(A16,"W13769069",$E$1,1,100000000) -> 1805.22 | BW16: =[1]!s_stm07_bs(A16,"W15273164",$F$1,1,100000000)-[1]!s_stm07_bs(A16,"W17642530",$F$1,1,100000000)-[1]!s_stm07_bs(A16,"W15910877",$F$1,1,100000000)-[1]!s_stm07_bs_39(A16,$F$1,1,100000000)-[1]!s_stm07_bs(A16,"W17700468",$F$1,1,100000000)-[1]!s_stm07_bs(A16,"W16504296",$F$1,1,100000000)-[1]!s_stm07_bs(A16,"W13769069",$F$1,1,100000000) -> 1707.0924 | BX16: =[1]!s_stm07_bs(A16,"W15273164",$G$1,1,100000000)-[1]!s_stm07_bs(A16,"W17642530",$G$1,1,100000000)-[1]!s_stm07_bs(A16,"W15910877",$G$1,1,100000000)-[1]!s_stm07_bs_39(A16,$G$1,1,100000000)-[1]!s_stm07_bs(A16,"W17700468",$G$1,1,100000000)-[1]!s_stm07_bs(A16,"W16504296",$G$1,1,100000000)-[1]!s_stm07_bs(A16,"W13769069",$G$1,1,100000000) -> 0 | BY16: =IFERROR([1]!b_stm07_is(A16,20,$A$1,1,100000000)/AVERAGEIF(CA16:CE16,">0")*100,0) -> 2.595383 | BZ16: =[1]!b_stm07_is(A16,20,$A$1,1,100000000) -> 44.862228 | CA16: =[1]!s_stmnote_bank_38(A16,$A$1,1,100000000) -> 1938.9006 | CB16: =[1]!s_stmnote_bank_38(A16,$B$1,1,100000000) -> 1518.1789 | CC16: =[1]!s_stmnote_bank_38(A16,$E$1,1,100000000) -> 0 | CD16: =[1]!s_stmnote_bank_38(A16,$F$1,1,100000000) -> 0 | CE16: =[1]!s_stmnote_bank_38(A16,$G$1,1,100000000) -> 0 | CF16: =IF(BP16<>0,BP16,IFERROR(IF(([1]!b_stm07_is(A16,19,$A$1,1,100000000)-[1]!b_stm07_is(A16,20,$A$1,1,100000000))/AVERAGE([1]!s_stmnote_bank_35(A16,$A$1,1,100000000),[1]!s_stmnote_bank_35(A16,$B$1,1,100000000))*100=0,"",([1]!b_stm07_is(A16,19,$A$1,1,100000000)-[1]!b_stm07_is(A16,20,$A$1,1,100000000))/AVERAGE([1]!s_stmnote_bank_35(A16,$A$1,1,100000000),[1]!s_stmnote_bank_35(A16,$B$1,1,100000000))*100),"")) -> 1.8652379 | CG16: =RANK(CF16,CF$5:CF$192,0)&" "&COUNTIF(CF$5:CF$192,">0") -> 116 171 | CH16: =IFERROR(CF16/100/P16,"") -> 0.62951071 | CI16: =RANK(CH16,CH$5:CH$192,0)&" "&COUNTIF(CH$5:CH$192,">0") -> 90 169 | CJ16: =[1]!s_stmnote_bank_30(A16,$A$1,1) -> 26.1429 | CP16: =[1]!b_stm07_bs($A16,141,$A$1,1,100000000) -> 181.4282 | CQ16: =[1]!b_stm07_bs($A16,141,$D$1,1,100000000) -> 176.94 | CR16: =IF([1]!s_fa_roic_yearly($A16,$A$1)=0,"",[1]!s_fa_roic_yearly($A16,$A$1)) -> 10.5271 | CS16: =RANK(CR16,CR$5:CR$192,0)/COUNTIF(CR$5:CR$192,">0") -> 0.28402367 | CT16: =IF([1]!s_fa_roic_yearly($A16,$D$1)=0,"",[1]!s_fa_roic_yearly($A16,$D$1)) | CU16: =RANK(CT16,CT$5:CT$192,0)/COUNTIF(CT$5:CT$192,">0") -> #VALUE! | CV16: =[1]!s_stm07_bs(A16,"W14578191",$A$1,1,100000000) -> 1223.8312 | CW16: =[1]!s_stmnote_bank_682($A16,$A$1,1,2,100000000) -> 674.46152 | CX16: =IF(CW16*CV16=0,"",CW16/CV16) -> 0.55110664
A17: 1821045.IB | B17: 浙江德清农村商业银行股份有限公司 | C17: 浙江德清农商行 | D17: 农商行 | F17: AA | H17: B+ | J17: =VLOOKUP(B17,[3]额度信息!$B:$T,19,0) -> #N/A | L17: =IFERROR(([1]!b_stm07_bs($A17,47,$A$1,1,100000000))/[1]!b_stm07_bs($A17,109,$A$1,1,100000000),"") -> 0.084745404 | O17: =RANK(N17,N$5:N$192,1)&" "&COUNTIF(N$5:N$192,">0") -> #N/A | P17: =IF(IFERROR(R17+AB17/100,"")=0,"",IFERROR(R17+AB17/100,"")) -> 0.0063 | Q17: =RANK(P17,P$5:P$192,1)&" "&COUNTIF(P$5:P$192,">0") -> 3 169 | R17: =IFERROR([1]!s_stmnote_bank($A17,"34",$A$1,100000000)/[1]!s_stmnote_bank_1n(A17,$A$1,1,100000000),"") -> 0 | Z17: =[1]!b_stm07_bs(A17,74,$A$1,1,100000000) -> 671.4288 | AA17: =[1]!b_stm07_bs(A17,109,$A$1,1,100000000) -> 542.38851 | AB17: =[1]!s_stmnote_bank_5n(A17,$A$1,1) -> 0.63 | AC17: =IF([1]!s_stmnote_bank_23n(A17,$A$1,1)=0,"",IFERROR([1]!s_stmnote_bank_23n(A17,$A$1,1),"")) -> 518.98 | AD17: =RANK(AC17,AC$5:AC$192,1)&" "&COUNTIF(AC$5:AC$192,">0") -> 148 167 | AE17: =[1]!s_stmnote_bank_capadequacyratio(A17,$A$1,1) -> 15.22 | AF17: =IF([1]!s_stmnote_bank_capadequacyratio_ct1(A17,$A$1,1)=0,"",IFERROR([1]!s_stmnote_bank_capadequacyratio_ct1(A17,$A$1,1),"")) -> 12.75 | AG17: =RANK(AF17,AF$5:AF$192,1)&" "&COUNTIF(AF$5:AF$192,">0") -> 136 167 | AH17: =IF(OR([1]!s_fa_roe(A17,20201231)=0,[1]!s_fa_roe(A17,20211231)="0",[1]!s_fa_roe(A17,20221231)="0"),"",IFERROR(([1]!s_fa_roe(A17,20221231)+[1]!s_fa_roe(A17,20201231)+[1]!s_fa_roe(A17,20211231))/3,"")) -> 12.7455 | AI17: =RANK(AH17,AH$5:AH$192,1)&" "&COUNTIF(AH$5:AH$192,">0") -> 153 173 | AJ17: =IFERROR(([1]!s_stmnote_bank_65(A17,$A$1,1,2,4,100000000)+[1]!s_stmnote_bank_65(A17,$A$1,1,2,6,100000000))/[1]!s_stmnote_bank_1n(A17,$A$1,1,100000000),"") -> 0.095011118 | AK17: =IFERROR([1]!s_stmnote_bank_614(A17,$A$1,1,2,100000000)/[1]!s_stmnote_bank_647(A17,$A$1,1,2,100000000),"") -> 0.2256424 | AL17: =IFERROR(([1]!b_stm07_bs(A17,104,$A$1,1,100000000)+[1]!b_stm07_bs(A17,106,$A$1,1,100000000)+[1]!b_stm07_bs(A17,76,$A$1,1,100000000)+[1]!b_stm07_bs(A17,108,$A$1,1,100000000)+[1]!b_stm07_bs(A17,95,$A$1,1,100000000))/[1]!b_stm07_bs(A17,128,$A$1,1,100000000),"") -> 0.058229759 | AM17: =IFERROR(([1]!s_stmnote_bank_614(A17,$A$1,1,2,100000000)+[1]!b_stm07_bs(A17,104,$A$1,1,100000000)+[1]!b_stm07_bs(A17,106,$A$1,1,100000000)+[1]!b_stm07_bs(A17,76,$A$1,1,100000000)+[1]!b_stm07_bs(A17,108,$A$1,1,100000000)+[1]!b_stm07_bs(A17,95,$A$1,1,100000000))/[1]!b_stm07_bs(A17,128,$A$1,1,100000000),"") -> 0.25841758 | AN17: =IF(Z17>#REF!,#REF!,IF(Z17>#REF!,#REF!,IF(Z17>#REF!,#REF!,IF(Z17>#REF!,#REF!,IF(Z17>#REF!,#REF!,IF(Z17>#REF!,#REF!,IF(Z17>#REF!,#REF!,#REF!))))))) -> #REF! | AO17: =IF(AA17>#REF!,#REF!,IF(AA17>#REF!,#REF!,IF(AA17>#REF!,#REF!,IF(AA17>#REF!,#REF!,IF(AA17>#REF!,#REF!,IF(AA17>#REF!,#REF!,IF(AA17>#REF!,#REF!,#REF!))))))) -> #REF! | AP17: =IF(AB17<#REF!,#REF!,IF(AB17<#REF!,#REF!,IF(AB17<#REF!,#REF!,IF(AB17<#REF!,#REF!,IF(AB17<#REF!,#REF!,IF(AB17<#REF!,#REF!,#REF!)))))) -> #REF! | AQ17: =IF(AC17>#REF!,#REF!,IF(AC17>#REF!,#REF!,IF(AC17>#REF!,#REF!,IF(AC17>#REF!,#REF!,#REF!)))) -> #REF! | AR17: =IF(AE17>#REF!,#REF!,IF(AE17>#REF!,#REF!,IF(AE17>#REF!,#REF!,IF(AE17>#REF!,#REF!,#REF!)))) -> #REF! | AS17: =IF(AF17>#REF!,#REF!,IF(AF17>#REF!,#REF!,IF(AF17>#REF!,#REF!,IF(AF17>#REF!,#REF!,#REF!)))) -> #REF! | AT17: =IF(AH17>#REF!,#REF!,IF(AH17>#REF!,#REF!,IF(AH17>#REF!,#REF!,IF(AH17>#REF!,#REF!,IF(AH17>#REF!,#REF!,#REF!))))) -> #REF! | AU17: =AN17*$AN$3+AP17*$AP$3+AQ17*$AQ$3+AR17*$AR$3+AS17*$AS$3+AT17*$AT$3+$AO$3*AO17 -> #REF! | AY17: =IFERROR(VLOOKUP(AV17,#REF!,3,0),"") | AZ17: =IFERROR(VLOOKUP(AW17,#REF!,3,0),"") | BA17: =IFERROR(VLOOKUP(AX17,#REF!,3,0),"") | BB17: =IFERROR(AY17*#REF!+AZ17*#REF!+BA17*#REF!,"") | BC17: =IFERROR(AU17*0.6+BB17*0.4,"") | BD17: =IFERROR(VLOOKUP(BC17*10,#REF!,2,1),"") | BH17: 华盛达控股集团有限公司 | BI17: 4.8200002 | BJ17: 浙江 | BK17: 湖州市 | BL17: =IF([1]!s_stmnote_bank_17n(A17,$A$1,1)="0","",[1]!s_stmnote_bank_17n(A17,$A$1,1)) -> 1.71 | BM17: =IF([1]!s_stmnote_bank_18n(A17,$A$1,1)="0","",[1]!s_stmnote_bank_18n(A17,$A$1,1)) -> 11.92 | BP17: =[1]!s_stmnote_bank_5444(A17,$A$1,1) -> 0 | BQ17: =[1]!s_stmnote_bank_129n($A17,$A$1,1) -> 37.69 | BR17: =IFERROR(BS17/SUMPRODUCT(BT17:BX17,$BT$4:$BX$4)*SUMIFS($BT$4:$BX$4,BT17:BX17,">0")*100,0) -> 5.3623454 | BS17: =[1]!b_stm07_is(A17,19,$A$1,1,100000000) -> 31.077156 | BT17: =[1]!s_stm07_bs(A17,"W15273164",$A$1,1,100000000)-[1]!s_stm07_bs(A17,"W17642530",$A$1,1,100000000)-[1]!s_stm07_bs(A17,"W15910877",$A$1,1,100000000)-[1]!s_stm07_bs_39(A17,$A$1,1,100000000)-[1]!s_stm07_bs(A17,"W17700468",$A$1,1,100000000)-[1]!s_stm07_bs(A17,"W16504296",$A$1,1,100000000)-[1]!s_stm07_bs(A17,"W13769069",$A$1,1,100000000) -> 658.77502 | BU17: =[1]!s_stm07_bs(A17,"W15273164",$B$1,1,100000000)-[1]!s_stm07_bs(A17,"W17642530",$B$1,1,100000000)-[1]!s_stm07_bs(A17,"W15910877",$B$1,1,100000000)-[1]!s_stm07_bs_39(A17,$B$1,1,100000000)-[1]!s_stm07_bs(A17,"W17700468",$B$1,1,100000000)-[1]!s_stm07_bs(A17,"W16504296",$B$1,1,100000000)-[1]!s_stm07_bs(A17,"W13769069",$B$1,1,100000000) -> 554.66136 | BV17: =[1]!s_stm07_bs(A17,"W15273164",$E$1,1,100000000)-[1]!s_stm07_bs(A17,"W17642530",$E$1,1,100000000)-[1]!s_stm07_bs(A17,"W15910877",$E$1,1,100000000)-[1]!s_stm07_bs_39(A17,$E$1,1,100000000)-[1]!s_stm07_bs(A17,"W17700468",$E$1,1,100000000)-[1]!s_stm07_bs(A17,"W16504296",$E$1,1,100000000)-[1]!s_stm07_bs(A17,"W13769069",$E$1,1,100000000) -> 647.49229 | BW17: =[1]!s_stm07_bs(A17,"W15273164",$F$1,1,100000000)-[1]!s_stm07_bs(A17,"W17642530",$F$1,1,100000000)-[1]!s_stm07_bs(A17,"W15910877",$F$1,1,100000000)-[1]!s_stm07_bs_39(A17,$F$1,1,100000000)-[1]!s_stm07_bs(A17,"W17700468",$F$1,1,100000000)-[1]!s_stm07_bs(A17,"W16504296",$F$1,1,100000000)-[1]!s_stm07_bs(A17,"W13769069",$F$1,1,100000000) -> 626.18397 | BX17: =[1]!s_stm07_bs(A17,"W15273164",$G$1,1,100000000)-[1]!s_stm07_bs(A17,"W17642530",$G$1,1,100000000)-[1]!s_stm07_bs(A17,"W15910877",$G$1,1,100000000)-[1]!s_stm07_bs_39(A17,$G$1,1,100000000)-[1]!s_stm07_bs(A17,"W17700468",$G$1,1,100000000)-[1]!s_stm07_bs(A17,"W16504296",$G$1,1,100000000)-[1]!s_stm07_bs(A17,"W13769069",$G$1,1,100000000) -> 608.21262 | BY17: =IFERROR([1]!b_stm07_is(A17,20,$A$1,1,100000000)/AVERAGEIF(CA17:CE17,">0")*100,0) -> 2.2887794 | BZ17: =[1]!b_stm07_is(A17,20,$A$1,1,100000000) -> 12.895861 | CA17: =[1]!s_stmnote_bank_38(A17,$A$1,1,100000000) -> 604.1131 | CB17: =[1]!s_stmnote_bank_38(A17,$B$1,1,100000000) -> 495.64931 | CC17: =[1]!s_stmnote_bank_38(A17,$E$1,1,100000000) -> 591.89309 | CD17: =[1]!s_stmnote_bank_38(A17,$F$1,1,100000000) -> 571.81526 | CE17: =[1]!s_stmnote_bank_38(A17,$G$1,1,100000000) -> 553.72105 | CF17: =IF(BP17<>0,BP17,IFERROR(IF(([1]!b_stm07_is(A17,19,$A$1,1,100000000)-[1]!b_stm07_is(A17,20,$A$1,1,100000000))/AVERAGE([1]!s_stmnote_bank_35(A17,$A$1,1,100000000),[1]!s_stmnote_bank_35(A17,$B$1,1,100000000))*100=0,"",([1]!b_stm07_is(A17,19,$A$1,1,100000000)-[1]!b_stm07_is(A17,20,$A$1,1,100000000))/AVERAGE([1]!s_stmnote_bank_35(A17,$A$1,1,100000000),[1]!s_stmnote_bank_35(A17,$B$1,1,100000000))*100),"")) -> 3.1161561 | CG17: =RANK(CF17,CF$5:CF$192,0)&" "&COUNTIF(CF$5:CF$192,">0") -> 9 171 | CH17: =IFERROR(CF17/100/P17,"") -> 4.9462795 | CI17: =RANK(CH17,CH$5:CH$192,0)&" "&COUNTIF(CH$5:CH$192,">0") -> 1 169 | CJ17: =[1]!s_stmnote_bank_30(A17,$A$1,1) -> 7.5247 | CP17: =[1]!b_stm07_bs($A17,141,$A$1,1,100000000) -> 60.073685 | CQ17: =[1]!b_stm07_bs($A17,141,$D$1,1,100000000) -> 64.707518 | CR17: =IF([1]!s_fa_roic_yearly($A17,$A$1)=0,"",[1]!s_fa_roic_yearly($A17,$A$1)) -> 13.2061 | CS17: =RANK(CR17,CR$5:CR$192,0)/COUNTIF(CR$5:CR$192,">0") -> 0.11242604 | CT17: =IF([1]!s_fa_roic_yearly($A17,$D$1)=0,"",[1]!s_fa_roic_yearly($A17,$D$1)) -> 19.811 | CU17: =RANK(CT17,CT$5:CT$192,0)/COUNTIF(CT$5:CT$192,">0") -> 0.014084507 | CV17: =[1]!s_stm07_bs(A17,"W14578191",$A$1,1,100000000) -> 449.99732 | CW17: =[1]!s_stmnote_bank_682($A17,$A$1,1,2,100000000) -> 0 | CX17: =IF(CW17*CV17=0,"",CW17/CV17)
A18: 112283362.IB | B18: 渣打银行(中国)有限公司 | C18: 渣打银行(中国) | D18: 外资行 | E18: 有普通 | F18: AAA | G18: BBB | H18: BB+ | J18: =VLOOKUP(B18,[3]额度信息!$B:$T,19,0) -> 0 | K18: 渣打银行全资子公司 | L18: =IFERROR(([1]!b_stm07_bs($A18,47,$A$1,1,100000000))/[1]!b_stm07_bs($A18,109,$A$1,1,100000000),"") -> 0.11863282 | M18: 5.81 | N18: =IFERROR(([1]!s_stmnote_bank_26($A18,$A$1,1,100000000)-[1]!s_stmnote_bank_26($A18,$B$1,1,100000000)+M18)/[1]!s_stmnote_bank_1n($A18,$B$1,1,100000000),"") -> 0.0054993274 | O18: =RANK(N18,N$5:N$192,1)&" "&COUNTIF(N$5:N$192,">0") -> 15 50 | P18: =IF(IFERROR(R18+AB18/100,"")=0,"",IFERROR(R18+AB18/100,"")) -> 0.0061 | Q18: =RANK(P18,P$5:P$192,1)&" "&COUNTIF(P$5:P$192,">0") -> 2 169 | R18: =IFERROR([1]!s_stmnote_bank($A18,"34",$A$1,100000000)/[1]!s_stmnote_bank_1n(A18,$A$1,1,100000000),"") -> 0 | S18: 0.0554 | T18: 0.0261 | Z18: =[1]!b_stm07_bs(A18,74,$A$1,1,100000000) -> 2589.4608 | AA18: =[1]!b_stm07_bs(A18,109,$A$1,1,100000000) -> 1520.3893 | AB18: =[1]!s_stmnote_bank_5n(A18,$A$1,1) -> 0.61 | AC18: =IF([1]!s_stmnote_bank_23n(A18,$A$1,1)=0,"",IFERROR([1]!s_stmnote_bank_23n(A18,$A$1,1),"")) -> 321 | AD18: =RANK(AC18,AC$5:AC$192,1)&" "&COUNTIF(AC$5:AC$192,">0") -> 115 167 | AE18: =[1]!s_stmnote_bank_capadequacyratio(A18,$A$1,1) -> 17.3 | AF18: =IF([1]!s_stmnote_bank_capadequacyratio_ct1(A18,$A$1,1)=0,"",IFERROR([1]!s_stmnote_bank_capadequacyratio_ct1(A18,$A$1,1),"")) -> 14.5 | AG18: =RANK(AF18,AF$5:AF$192,1)&" "&COUNTIF(AF$5:AF$192,">0") -> 151 167 | AH18: =IF(OR([1]!s_fa_roe(A18,20201231)=0,[1]!s_fa_roe(A18,20211231)="0",[1]!s_fa_roe(A18,20221231)="0"),"",IFERROR(([1]!s_fa_roe(A18,20221231)+[1]!s_fa_roe(A18,20201231)+[1]!s_fa_roe(A18,20211231))/3,"")) -> 6.7186 | AI18: =RANK(AH18,AH$5:AH$192,1)&" "&COUNTIF(AH$5:AH$192,">0") -> 67 173 | AJ18: =IFERROR(([1]!s_stmnote_bank_65(A18,$A$1,1,2,4,100000000)+[1]!s_stmnote_bank_65(A18,$A$1,1,2,6,100000000))/[1]!s_stmnote_bank_1n(A18,$A$1,1,100000000),"") -> 0.11677351 | AK18: =IFERROR([1]!s_stmnote_bank_614(A18,$A$1,1,2,100000000)/[1]!s_stmnote_bank_647(A18,$A$1,1,2,100000000),"") -> 0.56742631 | AL18: =IFERROR(([1]!b_stm07_bs(A18,104,$A$1,1,100000000)+[1]!b_stm07_bs(A18,106,$A$1,1,100000000)+[1]!b_stm07_bs(A18,76,$A$1,1,100000000)+[1]!b_stm07_bs(A18,108,$A$1,1,100000000)+[1]!b_stm07_bs(A18,95,$A$1,1,100000000))/[1]!b_stm07_bs(A18,128,$A$1,1,100000000),"") -> 0.24208454 | AM18: =IFERROR(([1]!s_stmnote_bank_614(A18,$A$1,1,2,100000000)+[1]!b_stm07_bs(A18,104,$A$1,1,100000000)+[1]!b_stm07_bs(A18,106,$A$1,1,100000000)+[1]!b_stm07_bs(A18,76,$A$1,1,100000000)+[1]!b_stm07_bs(A18,108,$A$1,1,100000000)+[1]!b_stm07_bs(A18,95,$A$1,1,100000000))/[1]!b_stm07_bs(A18,128,$A$1,1,100000000),"") -> 0.63051062 | AN18: =IF(Z18>#REF!,#REF!,IF(Z18>#REF!,#REF!,IF(Z18>#REF!,#REF!,IF(Z18>#REF!,#REF!,IF(Z18>#REF!,#REF!,IF(Z18>#REF!,#REF!,IF(Z18>#REF!,#REF!,#REF!))))))) -> #REF! | AO18: =IF(AA18>#REF!,#REF!,IF(AA18>#REF!,#REF!,IF(AA18>#REF!,#REF!,IF(AA18>#REF!,#REF!,IF(AA18>#REF!,#REF!,IF(AA18>#REF!,#REF!,IF(AA18>#REF!,#REF!,#REF!))))))) -> #REF! | AP18: =IF(AB18<#REF!,#REF!,IF(AB18<#REF!,#REF!,IF(AB18<#REF!,#REF!,IF(AB18<#REF!,#REF!,IF(AB18<#REF!,#REF!,IF(AB18<#REF!,#REF!,#REF!)))))) -> #REF! | AQ18: =IF(AC18>#REF!,#REF!,IF(AC18>#REF!,#REF!,IF(AC18>#REF!,#REF!,IF(AC18>#REF!,#REF!,#REF!)))) -> #REF! | AR18: =IF(AE18>#REF!,#REF!,IF(AE18>#REF!,#REF!,IF(AE18>#REF!,#REF!,IF(AE18>#REF!,#REF!,#REF!)))) -> #REF! | AS18: =IF(AF18>#REF!,#REF!,IF(AF18>#REF!,#REF!,IF(AF18>#REF!,#REF!,IF(AF18>#REF!,#REF!,#REF!)))) -> #REF! | AT18: =IF(AH18>#REF!,#REF!,IF(AH18>#REF!,#REF!,IF(AH18>#REF!,#REF!,IF(AH18>#REF!,#REF!,IF(AH18>#REF!,#REF!,#REF!))))) -> #REF! | AU18: =AN18*$AN$3+AP18*$AP$3+AQ18*$AQ$3+AR18*$AR$3+AS18*$AS$3+AT18*$AT$3+$AO$3*AO18 -> #REF! | AV18: 中 | AW18: 中 | AX18: 好 | AY18: =IFERROR(VLOOKUP(AV18,#REF!,3,0),"") | AZ18: =IFERROR(VLOOKUP(AW18,#REF!,3,0),"") | BA18: =IFERROR(VLOOKUP(AX18,#REF!,3,0),"") | BB18: =IFERROR(AY18*#REF!+AZ18*#REF!+BA18*#REF!,"") | BC18: =IFERROR(AU18*0.6+BB18*0.4,"") | BD18: =IFERROR(VLOOKUP(BC18*10,#REF!,2,1),"") | BE18: 2 | BF18: -3 | BG18: 负债不稳-2，负面-1 | BH18: 英国渣打银行有限责任公司 | BI18: 100 | BJ18: 全国 | BL18: =IF([1]!s_stmnote_bank_17n(A18,$A$1,1)="0","",[1]!s_stmnote_bank_17n(A18,$A$1,1)) -> 0 | BM18: =IF([1]!s_stmnote_bank_18n(A18,$A$1,1)="0","",[1]!s_stmnote_bank_18n(A18,$A$1,1)) -> 0 | BN18: =IF([1]!s_stmnote_bank_58(A18,$A$1,1)="0","",[1]!s_stmnote_bank_58(A18,$A$1,1)) -> 0 | BP18: =[1]!s_stmnote_bank_5444(A18,$A$1,1) -> 1.8 | BQ18: =[1]!s_stmnote_bank_129n($A18,$A$1,1) -> 57.9 | BR18: =IFERROR(BS18/SUMPRODUCT(BT18:BX18,$BT$4:$BX$4)*SUMIFS($BT$4:$BX$4,BT18:BX18,">0")*100,0) -> 2.3809638 | BS18: =[1]!b_stm07_is(A18,19,$A$1,1,100000000) -> 65.869569 | BT18: =[1]!s_stm07_bs(A18,"W15273164",$A$1,1,100000000)-[1]!s_stm07_bs(A18,"W17642530",$A$1,1,100000000)-[1]!s_stm07_bs(A18,"W15910877",$A$1,1,100000000)-[1]!s_stm07_bs_39(A18,$A$1,1,100000000)-[1]!s_stm07_bs(A18,"W17700468",$A$1,1,100000000)-[1]!s_stm07_bs(A18,"W16504296",$A$1,1,100000000)-[1]!s_stm07_bs(A18,"W13769069",$A$1,1,100000000) -> 2471.0075 | BU18: =[1]!s_stm07_bs(A18,"W15273164",$B$1,1,100000000)-[1]!s_stm07_bs(A18,"W17642530",$B$1,1,100000000)-[1]!s_stm07_bs(A18,"W15910877",$B$1,1,100000000)-[1]!s_stm07_bs_39(A18,$B$1,1,100000000)-[1]!s_stm07_bs(A18,"W17700468",$B$1,1,100000000)-[1]!s_stm07_bs(A18,"W16504296",$B$1,1,100000000)-[1]!s_stm07_bs(A18,"W13769069",$B$1,1,100000000) -> 2808.7231 | BV18: =[1]!s_stm07_bs(A18,"W15273164",$E$1,1,100000000)-[1]!s_stm07_bs(A18,"W17642530",$E$1,1,100000000)-[1]!s_stm07_bs(A18,"W15910877",$E$1,1,100000000)-[1]!s_stm07_bs_39(A18,$E$1,1,100000000)-[1]!s_stm07_bs(A18,"W17700468",$E$1,1,100000000)-[1]!s_stm07_bs(A18,"W16504296",$E$1,1,100000000)-[1]!s_stm07_bs(A18,"W13769069",$E$1,1,100000000) -> 0 | BW18: =[1]!s_stm07_bs(A18,"W15273164",$F$1,1,100000000)-[1]!s_stm07_bs(A18,"W17642530",$F$1,1,100000000)-[1]!s_stm07_bs(A18,"W15910877",$F$1,1,100000000)-[1]!s_stm07_bs_39(A18,$F$1,1,100000000)-[1]!s_stm07_bs(A18,"W17700468",$F$1,1,100000000)-[1]!s_stm07_bs(A18,"W16504296",$F$1,1,100000000)-[1]!s_stm07_bs(A18,"W13769069",$F$1,1,100000000) -> 0 | BX18: =[1]!s_stm07_bs(A18,"W15273164",$G$1,1,100000000)-[1]!s_stm07_bs(A18,"W17642530",$G$1,1,100000000)-[1]!s_stm07_bs(A18,"W15910877",$G$1,1,100000000)-[1]!s_stm07_bs_39(A18,$G$1,1,100000000)-[1]!s_stm07_bs(A18,"W17700468",$G$1,1,100000000)-[1]!s_stm07_bs(A18,"W16504296",$G$1,1,100000000)-[1]!s_stm07_bs(A18,"W13769069",$G$1,1,100000000) -> 0 | BY18: =IFERROR([1]!b_stm07_is(A18,20,$A$1,1,100000000)/AVERAGEIF(CA18:CE18,">0")*100,0) -> 1.1458199 | BZ18: =[1]!b_stm07_is(A18,20,$A$1,1,100000000) -> 24.803828 | CA18: =[1]!s_stmnote_bank_38(A18,$A$1,1,100000000) -> 2080.8953 | CB18: =[1]!s_stmnote_bank_38(A18,$B$1,1,100000000) -> 2248.5508 | CC18: =[1]!s_stmnote_bank_38(A18,$E$1,1,100000000) -> 0 | CD18: =[1]!s_stmnote_bank_38(A18,$F$1,1,100000000) -> 0 | CE18: =[1]!s_stmnote_bank_38(A18,$G$1,1,100000000) -> 0 | CF18: =IF(BP18<>0,BP18,IFERROR(IF(([1]!b_stm07_is(A18,19,$A$1,1,100000000)-[1]!b_stm07_is(A18,20,$A$1,1,100000000))/AVERAGE([1]!s_stmnote_bank_35(A18,$A$1,1,100000000),[1]!s_stmnote_bank_35(A18,$B$1,1,100000000))*100=0,"",([1]!b_stm07_is(A18,19,$A$1,1,100000000)-[1]!b_stm07_is(A18,20,$A$1,1,100000000))/AVERAGE([1]!s_stmnote_bank_35(A18,$A$1,1,100000000),[1]!s_stmnote_bank_35(A18,$B$1,1,100000000))*100),"")) -> 1.8 | CG18: =RANK(CF18,CF$5:CF$192,0)&" "&COUNTIF(CF$5:CF$192,">0") -> 126 171 | CH18: =IFERROR(CF18/100/P18,"") -> 2.9508197 | CI18: =RANK(CH18,CH$5:CH$192,0)&" "&COUNTIF(CH$5:CH$192,">0") -> 3 169 | CJ18: =[1]!s_stmnote_bank_30(A18,$A$1,1) -> 43.5077 | CP18: =[1]!b_stm07_bs($A18,141,$A$1,1,100000000) -> 274.12894 | CQ18: =[1]!b_stm07_bs($A18,141,$D$1,1,100000000) -> 0 | CR18: =IF([1]!s_fa_roic_yearly($A18,$A$1)=0,"",[1]!s_fa_roic_yearly($A18,$A$1)) -> 8.3352 | CS18: =RANK(CR18,CR$5:CR$192,0)/COUNTIF(CR$5:CR$192,">0") -> 0.55621302 | CT18: =IF([1]!s_fa_roic_yearly($A18,$D$1)=0,"",[1]!s_fa_roic_yearly($A18,$D$1)) | CU18: =RANK(CT18,CT$5:CT$192,0)/COUNTIF(CT$5:CT$192,">0") -> #VALUE! | CV18: =[1]!s_stm07_bs(A18,"W14578191",$A$1,1,100000000) -> 994.71495 | CW18: =[1]!s_stmnote_bank_682($A18,$A$1,1,2,100000000) -> 222.09728 | CX18: =IF(CW18*CV18=0,"",CW18/CV18) -> 0.22327731
A19: 111990034.IB | B19: 宁波余姚农村商业银行股份有限公司 | C19: 宁波余姚农商行 | D19: 农商行 | F19: AA | H19: BB | J19: =VLOOKUP(B19,[3]额度信息!$B:$T,19,0) -> #N/A | L19: =IFERROR(([1]!b_stm07_bs($A19,47,$A$1,1,100000000))/[1]!b_stm07_bs($A19,109,$A$1,1,100000000),"") -> 0.083266536 | O19: =RANK(N19,N$5:N$192,1)&" "&COUNTIF(N$5:N$192,">0") -> #N/A | P19: =IF(IFERROR(R19+AB19/100,"")=0,"",IFERROR(R19+AB19/100,"")) -> 0.011063529 | Q19: =RANK(P19,P$5:P$192,1)&" "&COUNTIF(P$5:P$192,">0") -> 7 169 | R19: 0.0042635293 | Z19: =[1]!b_stm07_bs(A19,74,$A$1,1,100000000) -> 686.47567 | AA19: =[1]!b_stm07_bs(A19,109,$A$1,1,100000000) -> 570.63365 | AB19: =[1]!s_stmnote_bank_5n(A19,$A$1,1) -> 0.68 | AC19: =IF([1]!s_stmnote_bank_23n(A19,$A$1,1)=0,"",IFERROR([1]!s_stmnote_bank_23n(A19,$A$1,1),"")) -> 580.9 | AD19: =RANK(AC19,AC$5:AC$192,1)&" "&COUNTIF(AC$5:AC$192,">0") -> 154 167 | AE19: =[1]!s_stmnote_bank_capadequacyratio(A19,$A$1,1) -> 16.74 | AF19: =IF([1]!s_stmnote_bank_capadequacyratio_ct1(A19,$A$1,1)=0,"",IFERROR([1]!s_stmnote_bank_capadequacyratio_ct1(A19,$A$1,1),"")) -> 13.23 | AG19: =RANK(AF19,AF$5:AF$192,1)&" "&COUNTIF(AF$5:AF$192,">0") -> 144 167 | AH19: =IF(OR([1]!s_fa_roe(A19,20201231)=0,[1]!s_fa_roe(A19,20211231)="0",[1]!s_fa_roe(A19,20221231)="0"),"",IFERROR(([1]!s_fa_roe(A19,20221231)+[1]!s_fa_roe(A19,20201231)+[1]!s_fa_roe(A19,20211231))/3,"")) -> 10.075833 | AI19: =RANK(AH19,AH$5:AH$192,1)&" "&COUNTIF(AH$5:AH$192,">0") -> 120 173 | AJ19: =IFERROR(([1]!s_stmnote_bank_65(A19,$A$1,1,2,4,100000000)+[1]!s_stmnote_bank_65(A19,$A$1,1,2,6,100000000))/[1]!s_stmnote_bank_1n(A19,$A$1,1,100000000),"") -> 0 | AK19: =IFERROR([1]!s_stmnote_bank_614(A19,$A$1,1,2,100000000)/[1]!s_stmnote_bank_647(A19,$A$1,1,2,100000000),"") -> 0.18971306 | AL19: =IFERROR(([1]!b_stm07_bs(A19,104,$A$1,1,100000000)+[1]!b_stm07_bs(A19,106,$A$1,1,100000000)+[1]!b_stm07_bs(A19,76,$A$1,1,100000000)+[1]!b_stm07_bs(A19,108,$A$1,1,100000000)+[1]!b_stm07_bs(A19,95,$A$1,1,100000000))/[1]!b_stm07_bs(A19,128,$A$1,1,100000000),"") -> 0.02574092 | AM19: =IFERROR(([1]!s_stmnote_bank_614(A19,$A$1,1,2,100000000)+[1]!b_stm07_bs(A19,104,$A$1,1,100000000)+[1]!b_stm07_bs(A19,106,$A$1,1,100000000)+[1]!b_stm07_bs(A19,76,$A$1,1,100000000)+[1]!b_stm07_bs(A19,108,$A$1,1,100000000)+[1]!b_stm07_bs(A19,95,$A$1,1,100000000))/[1]!b_stm07_bs(A19,128,$A$1,1,100000000),"") -> 0.19714718 | AN19: =IF(Z19>#REF!,#REF!,IF(Z19>#REF!,#REF!,IF(Z19>#REF!,#REF!,IF(Z19>#REF!,#REF!,IF(Z19>#REF!,#REF!,IF(Z19>#REF!,#REF!,IF(Z19>#REF!,#REF!,#REF!))))))) -> #REF! | AO19: =IF(AA19>#REF!,#REF!,IF(AA19>#REF!,#REF!,IF(AA19>#REF!,#REF!,IF(AA19>#REF!,#REF!,IF(AA19>#REF!,#REF!,IF(AA19>#REF!,#REF!,IF(AA19>#REF!,#REF!,#REF!))))))) -> #REF! | AP19: =IF(AB19<#REF!,#REF!,IF(AB19<#REF!,#REF!,IF(AB19<#REF!,#REF!,IF(AB19<#REF!,#REF!,IF(AB19<#REF!,#REF!,IF(AB19<#REF!,#REF!,#REF!)))))) -> #REF! | AQ19: =IF(AC19>#REF!,#REF!,IF(AC19>#REF!,#REF!,IF(AC19>#REF!,#REF!,IF(AC19>#REF!,#REF!,#REF!)))) -> #REF! | AR19: =IF(AE19>#REF!,#REF!,IF(AE19>#REF!,#REF!,IF(AE19>#REF!,#REF!,IF(AE19>#REF!,#REF!,#REF!)))) -> #REF! | AS19: =IF(AF19>#REF!,#REF!,IF(AF19>#REF!,#REF!,IF(AF19>#REF!,#REF!,IF(AF19>#REF!,#REF!,#REF!)))) -> #REF! | AT19: =IF(AH19>#REF!,#REF!,IF(AH19>#REF!,#REF!,IF(AH19>#REF!,#REF!,IF(AH19>#REF!,#REF!,IF(AH19>#REF!,#REF!,#REF!))))) -> #REF! | AU19: =AN19*$AN$3+AP19*$AP$3+AQ19*$AQ$3+AR19*$AR$3+AS19*$AS$3+AT19*$AT$3+$AO$3*AO19 -> #REF! | AY19: =IFERROR(VLOOKUP(AV19,#REF!,3,0),"") | AZ19: =IFERROR(VLOOKUP(AW19,#REF!,3,0),"") | BA19: =IFERROR(VLOOKUP(AX19,#REF!,3,0),"") | BB19: =IFERROR(AY19*#REF!+AZ19*#REF!+BA19*#REF!,"") | BC19: =IFERROR(AU19*0.6+BB19*0.4,"") | BD19: =IFERROR(VLOOKUP(BC19*10,#REF!,2,1),"") | BH19: 宁波更大集团有限公司 | BI19: 7.4000001 | BK19: 宁波市 | BL19: =IF([1]!s_stmnote_bank_17n(A19,$A$1,1)="0","",[1]!s_stmnote_bank_17n(A19,$A$1,1)) -> 2.77 | BM19: =IF([1]!s_stmnote_bank_18n(A19,$A$1,1)="0","",[1]!s_stmnote_bank_18n(A19,$A$1,1)) -> 0 | BP19: =[1]!s_stmnote_bank_5444(A19,$A$1,1) -> 0 | BQ19: =[1]!s_stmnote_bank_129n($A19,$A$1,1) -> 32.19 | BR19: =IFERROR(BS19/SUMPRODUCT(BT19:BX19,$BT$4:$BX$4)*SUMIFS($BT$4:$BX$4,BT19:BX19,">0")*100,0) -> 4.2243479 | BS19: =[1]!b_stm07_is(A19,19,$A$1,1,100000000) -> 24.913285 | BT19: =[1]!s_stm07_bs(A19,"W15273164",$A$1,1,100000000)-[1]!s_stm07_bs(A19,"W17642530",$A$1,1,100000000)-[1]!s_stm07_bs(A19,"W15910877",$A$1,1,100000000)-[1]!s_stm07_bs_39(A19,$A$1,1,100000000)-[1]!s_stm07_bs(A19,"W17700468",$A$1,1,100000000)-[1]!s_stm07_bs(A19,"W16504296",$A$1,1,100000000)-[1]!s_stm07_bs(A19,"W13769069",$A$1,1,100000000) -> 681.04895 | BU19: =[1]!s_stm07_bs(A19,"W15273164",$B$1,1,100000000)-[1]!s_stm07_bs(A19,"W17642530",$B$1,1,100000000)-[1]!s_stm07_bs(A19,"W15910877",$B$1,1,100000000)-[1]!s_stm07_bs_39(A19,$B$1,1,100000000)-[1]!s_stm07_bs(A19,"W17700468",$B$1,1,100000000)-[1]!s_stm07_bs(A19,"W16504296",$B$1,1,100000000)-[1]!s_stm07_bs(A19,"W13769069",$B$1,1,100000000) -> 572.48068 | BV19: =[1]!s_stm07_bs(A19,"W15273164",$E$1,1,100000000)-[1]!s_stm07_bs(A19,"W17642530",$E$1,1,100000000)-[1]!s_stm07_bs(A19,"W15910877",$E$1,1,100000000)-[1]!s_stm07_bs_39(A19,$E$1,1,100000000)-[1]!s_stm07_bs(A19,"W17700468",$E$1,1,100000000)-[1]!s_stm07_bs(A19,"W16504296",$E$1,1,100000000)-[1]!s_stm07_bs(A19,"W13769069",$E$1,1,100000000) -> 649.0004 | BW19: =[1]!s_stm07_bs(A19,"W15273164",$F$1,1,100000000)-[1]!s_stm07_bs(A19,"W17642530",$F$1,1,100000000)-[1]!s_stm07_bs(A19,"W15910877",$F$1,1,100000000)-[1]!s_stm07_bs_39(A19,$F$1,1,100000000)-[1]!s_stm07_bs(A19,"W17700468",$F$1,1,100000000)-[1]!s_stm07_bs(A19,"W16504296",$F$1,1,100000000)-[1]!s_stm07_bs(A19,"W13769069",$F$1,1,100000000) -> 0 | BX19: =[1]!s_stm07_bs(A19,"W15273164",$G$1,1,100000000)-[1]!s_stm07_bs(A19,"W17642530",$G$1,1,100000000)-[1]!s_stm07_bs(A19,"W15910877",$G$1,1,100000000)-[1]!s_stm07_bs_39(A19,$G$1,1,100000000)-[1]!s_stm07_bs(A19,"W17700468",$G$1,1,100000000)-[1]!s_stm07_bs(A19,"W16504296",$G$1,1,100000000)-[1]!s_stm07_bs(A19,"W13769069",$G$1,1,100000000) -> 0 | BY19: =IFERROR([1]!b_stm07_is(A19,20,$A$1,1,100000000)/AVERAGEIF(CA19:CE19,">0")*100,0) -> 2.2984652 | BZ19: =[1]!b_stm07_is(A19,20,$A$1,1,100000000) -> 13.133256 | CA19: =[1]!s_stmnote_bank_38(A19,$A$1,1,100000000) -> 621.73269 | CB19: =[1]!s_stmnote_bank_38(A19,$B$1,1,100000000) -> 503.85496 | CC19: =[1]!s_stmnote_bank_38(A19,$E$1,1,100000000) -> 588.58962 | CD19: =[1]!s_stmnote_bank_38(A19,$F$1,1,100000000) -> 0 | CE19: =[1]!s_stmnote_bank_38(A19,$G$1,1,100000000) -> 0 | CF19: =IF(BP19<>0,BP19,IFERROR(IF(([1]!b_stm07_is(A19,19,$A$1,1,100000000)-[1]!b_stm07_is(A19,20,$A$1,1,100000000))/AVERAGE([1]!s_stmnote_bank_35(A19,$A$1,1,100000000),[1]!s_stmnote_bank_35(A19,$B$1,1,100000000))*100=0,"",([1]!b_stm07_is(A19,19,$A$1,1,100000000)-[1]!b_stm07_is(A19,20,$A$1,1,100000000))/AVERAGE([1]!s_stmnote_bank_35(A19,$A$1,1,100000000),[1]!s_stmnote_bank_35(A19,$B$1,1,100000000))*100),"")) -> 1.8933476 | CG19: =RANK(CF19,CF$5:CF$192,0)&" "&COUNTIF(CF$5:CF$192,">0") -> 112 171 | CH19: =IFERROR(CF19/100/P19,"") -> 1.7113415 | CI19: =RANK(CH19,CH$5:CH$192,0)&" "&COUNTIF(CH$5:CH$192,">0") -> 18 169 | CJ19: =[1]!s_stmnote_bank_30(A19,$A$1,1) -> 14.7119 | CP19: =[1]!b_stm07_bs($A19,141,$A$1,1,100000000) -> 54.896309 | CQ19: =[1]!b_stm07_bs($A19,141,$D$1,1,100000000) -> 57.829531 | CR19: =IF([1]!s_fa_roic_yearly($A19,$A$1)=0,"",[1]!s_fa_roic_yearly($A19,$A$1)) -> 10.2707 | CS19: =RANK(CR19,CR$5:CR$192,0)/COUNTIF(CR$5:CR$192,">0") -> 0.31360947 | CT19: =IF([1]!s_fa_roic_yearly($A19,$D$1)=0,"",[1]!s_fa_roic_yearly($A19,$D$1)) -> 7.4224 | CU19: =RANK(CT19,CT$5:CT$192,0)/COUNTIF(CT$5:CT$192,">0") -> 0.74647887 | CV19: =[1]!s_stm07_bs(A19,"W14578191",$A$1,1,100000000) -> 393.30221 | CW19: =[1]!s_stmnote_bank_682($A19,$A$1,1,2,100000000) -> 0 | CX19: =IF(CW19*CV19=0,"",CW19/CV19)
A20: 111870098.IB | B20: 湖州银行股份有限公司 | C20: 湖州银行 | D20: 城商行 | F20: AA+ | H20: BB | J20: =VLOOKUP(B20,[3]额度信息!$B:$T,19,0) -> #N/A | L20: =IFERROR(([1]!b_stm07_bs($A20,47,$A$1,1,100000000))/[1]!b_stm07_bs($A20,109,$A$1,1,100000000),"") -> 0.090094381 | O20: =RANK(N20,N$5:N$192,1)&" "&COUNTIF(N$5:N$192,">0") -> #N/A | P20: =IF(IFERROR(R20+AB20/100,"")=0,"",IFERROR(R20+AB20/100,"")) -> 0.013407331 | Q20: =RANK(P20,P$5:P$192,1)&" "&COUNTIF(P$5:P$192,">0") -> 14 169 | R20: =IFERROR([1]!s_stmnote_bank($A20,"34",$A$1,100000000)/[1]!s_stmnote_bank_1n(A20,$A$1,1,100000000),"") -> 0.0056073308 | Z20: =[1]!b_stm07_bs(A20,74,$A$1,1,100000000) -> 1013.9856 | AA20: =[1]!b_stm07_bs(A20,109,$A$1,1,100000000) -> 712.75683 | AB20: =[1]!s_stmnote_bank_5n(A20,$A$1,1) -> 0.78 | AC20: =IF([1]!s_stmnote_bank_23n(A20,$A$1,1)=0,"",IFERROR([1]!s_stmnote_bank_23n(A20,$A$1,1),"")) -> 424.94 | AD20: =RANK(AC20,AC$5:AC$192,1)&" "&COUNTIF(AC$5:AC$192,">0") -> 137 167 | AE20: =[1]!s_stmnote_bank_capadequacyratio(A20,$A$1,1) -> 13.44 | AF20: =IF([1]!s_stmnote_bank_capadequacyratio_ct1(A20,$A$1,1)=0,"",IFERROR([1]!s_stmnote_bank_capadequacyratio_ct1(A20,$A$1,1),"")) -> 8.8 | AG20: =RANK(AF20,AF$5:AF$192,1)&" "&COUNTIF(AF$5:AF$192,">0") -> 38 167 | AH20: =IF(OR([1]!s_fa_roe(A20,20201231)=0,[1]!s_fa_roe(A20,20211231)="0",[1]!s_fa_roe(A20,20221231)="0"),"",IFERROR(([1]!s_fa_roe(A20,20221231)+[1]!s_fa_roe(A20,20201231)+[1]!s_fa_roe(A20,20211231))/3,"")) -> 12.8021 | AI20: =RANK(AH20,AH$5:AH$192,1)&" "&COUNTIF(AH$5:AH$192,">0") -> 155 173 | AJ20: =IFERROR(([1]!s_stmnote_bank_65(A20,$A$1,1,2,4,100000000)+[1]!s_stmnote_bank_65(A20,$A$1,1,2,6,100000000))/[1]!s_stmnote_bank_1n(A20,$A$1,1,100000000),"") -> 0.068770036 | AK20: =IFERROR([1]!s_stmnote_bank_614(A20,$A$1,1,2,100000000)/[1]!s_stmnote_bank_647(A20,$A$1,1,2,100000000),"") -> 0.29835688 | AL20: =IFERROR(([1]!b_stm07_bs(A20,104,$A$1,1,100000000)+[1]!b_stm07_bs(A20,106,$A$1,1,100000000)+[1]!b_stm07_bs(A20,76,$A$1,1,100000000)+[1]!b_stm07_bs(A20,108,$A$1,1,100000000)+[1]!b_stm07_bs(A20,95,$A$1,1,100000000))/[1]!b_stm07_bs(A20,128,$A$1,1,100000000),"") -> 0.18125587 | AM20: =IFERROR(([1]!s_stmnote_bank_614(A20,$A$1,1,2,100000000)+[1]!b_stm07_bs(A20,104,$A$1,1,100000000)+[1]!b_stm07_bs(A20,106,$A$1,1,100000000)+[1]!b_stm07_bs(A20,76,$A$1,1,100000000)+[1]!b_stm07_bs(A20,108,$A$1,1,100000000)+[1]!b_stm07_bs(A20,95,$A$1,1,100000000))/[1]!b_stm07_bs(A20,128,$A$1,1,100000000),"") -> 0.40129217 | AN20: =IF(Z20>#REF!,#REF!,IF(Z20>#REF!,#REF!,IF(Z20>#REF!,#REF!,IF(Z20>#REF!,#REF!,IF(Z20>#REF!,#REF!,IF(Z20>#REF!,#REF!,IF(Z20>#REF!,#REF!,#REF!))))))) -> #REF! | AO20: =IF(AA20>#REF!,#REF!,IF(AA20>#REF!,#REF!,IF(AA20>#REF!,#REF!,IF(AA20>#REF!,#REF!,IF(AA20>#REF!,#REF!,IF(AA20>#REF!,#REF!,IF(AA20>#REF!,#REF!,#REF!))))))) -> #REF! | AP20: =IF(AB20<#REF!,#REF!,IF(AB20<#REF!,#REF!,IF(AB20<#REF!,#REF!,IF(AB20<#REF!,#REF!,IF(AB20<#REF!,#REF!,IF(AB20<#REF!,#REF!,#REF!)))))) -> #REF! | AQ20: =IF(AC20>#REF!,#REF!,IF(AC20>#REF!,#REF!,IF(AC20>#REF!,#REF!,IF(AC20>#REF!,#REF!,#REF!)))) -> #REF! | AR20: =IF(AE20>#REF!,#REF!,IF(AE20>#REF!,#REF!,IF(AE20>#REF!,#REF!,IF(AE20>#REF!,#REF!,#REF!)))) -> #REF! | AS20: =IF(AF20>#REF!,#REF!,IF(AF20>#REF!,#REF!,IF(AF20>#REF!,#REF!,IF(AF20>#REF!,#REF!,#REF!)))) -> #REF! | AT20: =IF(AH20>#REF!,#REF!,IF(AH20>#REF!,#REF!,IF(AH20>#REF!,#REF!,IF(AH20>#REF!,#REF!,IF(AH20>#REF!,#REF!,#REF!))))) -> #REF! | AU20: =AN20*$AN$3+AP20*$AP$3+AQ20*$AQ$3+AR20*$AR$3+AS20*$AS$3+AT20*$AT$3+$AO$3*AO20 -> #REF! | AY20: =IFERROR(VLOOKUP(AV20,#REF!,3,0),"") | AZ20: =IFERROR(VLOOKUP(AW20,#REF!,3,0),"") | BA20: =IFERROR(VLOOKUP(AX20,#REF!,3,0),"") | BB20: =IFERROR(AY20*#REF!+AZ20*#REF!+BA20*#REF!,"") | BC20: =IFERROR(AU20*0.6+BB20*0.4,"") | BD20: =IFERROR(VLOOKUP(BC20*10,#REF!,2,1),"") | BH20: 湖州市城市投资发展集团有限公司 | BI20: 17.9 | BJ20: 浙江 | BK20: 湖州市 | BL20: =IF([1]!s_stmnote_bank_17n(A20,$A$1,1)="0","",[1]!s_stmnote_bank_17n(A20,$A$1,1)) -> 3.46 | BM20: =IF([1]!s_stmnote_bank_18n(A20,$A$1,1)="0","",[1]!s_stmnote_bank_18n(A20,$A$1,1)) -> 25.25 | BP20: =[1]!s_stmnote_bank_5444(A20,$A$1,1) -> 2.39 | BQ20: =[1]!s_stmnote_bank_129n($A20,$A$1,1) -> 36.93 | BR20: =IFERROR(BS20/SUMPRODUCT(BT20:BX20,$BT$4:$BX$4)*SUMIFS($BT$4:$BX$4,BT20:BX20,">0")*100,0) -> 4.7821407 | BS20: =[1]!b_stm07_is(A20,19,$A$1,1,100000000) -> 41.692586 | BT20: =[1]!s_stm07_bs(A20,"W15273164",$A$1,1,100000000)-[1]!s_stm07_bs(A20,"W17642530",$A$1,1,100000000)-[1]!s_stm07_bs(A20,"W15910877",$A$1,1,100000000)-[1]!s_stm07_bs_39(A20,$A$1,1,100000000)-[1]!s_stm07_bs(A20,"W17700468",$A$1,1,100000000)-[1]!s_stm07_bs(A20,"W16504296",$A$1,1,100000000)-[1]!s_stm07_bs(A20,"W13769069",$A$1,1,100000000) -> 998.46171 | BU20: =[1]!s_stm07_bs(A20,"W15273164",$B$1,1,100000000)-[1]!s_stm07_bs(A20,"W17642530",$B$1,1,100000000)-[1]!s_stm07_bs(A20,"W15910877",$B$1,1,100000000)-[1]!s_stm07_bs_39(A20,$B$1,1,100000000)-[1]!s_stm07_bs(A20,"W17700468",$B$1,1,100000000)-[1]!s_stm07_bs(A20,"W16504296",$B$1,1,100000000)-[1]!s_stm07_bs(A20,"W13769069",$B$1,1,100000000) -> 838.7552 | BV20: =[1]!s_stm07_bs(A20,"W15273164",$E$1,1,100000000)-[1]!s_stm07_bs(A20,"W17642530",$E$1,1,100000000)-[1]!s_stm07_bs(A20,"W15910877",$E$1,1,100000000)-[1]!s_stm07_bs_39(A20,$E$1,1,100000000)-[1]!s_stm07_bs(A20,"W17700468",$E$1,1,100000000)-[1]!s_stm07_bs(A20,"W16504296",$E$1,1,100000000)-[1]!s_stm07_bs(A20,"W13769069",$E$1,1,100000000) -> 954.53821 | BW20: =[1]!s_stm07_bs(A20,"W15273164",$F$1,1,100000000)-[1]!s_stm07_bs(A20,"W17642530",$F$1,1,100000000)-[1]!s_stm07_bs(A20,"W15910877",$F$1,1,100000000)-[1]!s_stm07_bs_39(A20,$F$1,1,100000000)-[1]!s_stm07_bs(A20,"W17700468",$F$1,1,100000000)-[1]!s_stm07_bs(A20,"W16504296",$F$1,1,100000000)-[1]!s_stm07_bs(A20,"W13769069",$F$1,1,100000000) -> 925.04906 | BX20: =[1]!s_stm07_bs(A20,"W15273164",$G$1,1,100000000)-[1]!s_stm07_bs(A20,"W17642530",$G$1,1,100000000)-[1]!s_stm07_bs(A20,"W15910877",$G$1,1,100000000)-[1]!s_stm07_bs_39(A20,$G$1,1,100000000)-[1]!s_stm07_bs(A20,"W17700468",$G$1,1,100000000)-[1]!s_stm07_bs(A20,"W16504296",$G$1,1,100000000)-[1]!s_stm07_bs(A20,"W13769069",$G$1,1,100000000) -> 892.65537 | BY20: =IFERROR([1]!b_stm07_is(A20,20,$A$1,1,100000000)/AVERAGEIF(CA20:CE20,">0")*100,0) -> 2.3902511 | BZ20: =[1]!b_stm07_is(A20,20,$A$1,1,100000000) -> 20.579197 | CA20: =[1]!s_stmnote_bank_38(A20,$A$1,1,100000000) -> 935.54794 | CB20: =[1]!s_stmnote_bank_38(A20,$B$1,1,100000000) -> 786.36523 | CC20: =[1]!s_stmnote_bank_38(A20,$E$1,1,100000000) -> 895.7558 | CD20: =[1]!s_stmnote_bank_38(A20,$F$1,1,100000000) -> 869.8299 | CE20: =[1]!s_stmnote_bank_38(A20,$G$1,1,100000000) -> 817.32013 | CF20: =IF(BP20<>0,BP20,IFERROR(IF(([1]!b_stm07_is(A20,19,$A$1,1,100000000)-[1]!b_stm07_is(A20,20,$A$1,1,100000000))/AVERAGE([1]!s_stmnote_bank_35(A20,$A$1,1,100000000),[1]!s_stmnote_bank_35(A20,$B$1,1,100000000))*100=0,"",([1]!b_stm07_is(A20,19,$A$1,1,100000000)-[1]!b_stm07_is(A20,20,$A$1,1,100000000))/AVERAGE([1]!s_stmnote_bank_35(A20,$A$1,1,100000000),[1]!s_stmnote_bank_35(A20,$B$1,1,100000000))*100),"")) -> 2.39 | CG20: =RANK(CF20,CF$5:CF$192,0)&" "&COUNTIF(CF$5:CF$192,">0") -> 39 171 | CH20: =IFERROR(CF20/100/P20,"") -> 1.7826069 | CI20: =RANK(CH20,CH$5:CH$192,0)&" "&COUNTIF(CH$5:CH$192,">0") -> 14 169 | CJ20: =[1]!s_stmnote_bank_30(A20,$A$1,1) -> 6.9101 | CP20: =[1]!b_stm07_bs($A20,141,$A$1,1,100000000) -> 68.928066 | CQ20: =[1]!b_stm07_bs($A20,141,$D$1,1,100000000) -> 71.950955 | CR20: =IF([1]!s_fa_roic_yearly($A20,$A$1)=0,"",[1]!s_fa_roic_yearly($A20,$A$1)) -> 12.9288 | CS20: =RANK(CR20,CR$5:CR$192,0)/COUNTIF(CR$5:CR$192,">0") -> 0.13017751 | CT20: =IF([1]!s_fa_roic_yearly($A20,$D$1)=0,"",[1]!s_fa_roic_yearly($A20,$D$1)) -> 13.1462 | CU20: =RANK(CT20,CT$5:CT$192,0)/COUNTIF(CT$5:CT$192,">0") -> 0.17605634 | CV20: =[1]!s_stm07_bs(A20,"W14578191",$A$1,1,100000000) -> 517.73765 | CW20: =[1]!s_stmnote_bank_682($A20,$A$1,1,2,100000000) -> 167.46809 | CX20: =IF(CW20*CV20=0,"",CW20/CV20) -> 0.3234613
A21: 111771527 | B21: 无锡农村商业银行股份有限公司 | C21: 无锡农村商业银行 | D21: 农商行 | E21: 有次级+普通 | F21: AA+ | G21: BBB- | H21: BB | J21: =VLOOKUP(B21,[3]额度信息!$B:$T,19,0) -> 0 | K21: 主要观点： 1、 该行前身为无锡市城郊农村信用合作联社，主要机构及业务分布在经济较为发达的无锡地区，股权结构分散，截至2021年末，其中第1和第4大股东均由无锡国资委实控，合计持股13.07%，无锡国资控股企业在董事会5人中派驻2名，影响力尚可。 2、 2021年，该行资产总额为2017.7亿元，其中，其中，发放贷款及垫款为1127.42亿元，占比55.88%，贷款增速17.51%，保持增长；2019-2021年，无锡农商行银行分别实现营业收入35.4亿、38.96亿、43.49亿，同比增速分别为10.89%、10.07%、11.63%；22H1营业收入23.36亿，同比增长6.7%；中间业务收入主要来自代理业务和银行卡业务，19-21年末占比分别为2.60%、4.52%、4.21%，2021年手续费及佣金净收入1.83亿，由于银行卡手续费收入下降增速放缓；2021年实现投资收益5.59亿，对收入贡献较大。 3、 公司信贷资产质量处于同业较好水平，21年末该行不良贷款率0.93%，拨备覆盖率477%，贷款拨备充足。 4、 负债端吸收存款1618.11亿，是最主要的负债来源，占比87%，同业负债占比7.43%；吸收存款中储蓄存款占比44.6%，定期存款占比64.41%，存款稳定性较好。 主要关注： 1、无锡市经济发展水平高，主要竞争对手国有大行在抢夺存量市场份额和优质客户存在定价等方面优势，公司区域竞争力偏弱，市场份额不高，存在一定同业竞争压力。截至2021年末，无锡农商银行在无锡市（含江阴市和宜兴市）存贷款市场份额分别为6.88%和5.14%，占比较低，竞争力偏弱，存贷款市场份额在无锡市银行业金融机构排名均为第6名。 2、该行盈利能力偏弱，主要由于生息资产平均收益偏低，负债成本略高于同业，21年有小幅改善。2019-2021年该行息差：1.79%、1.72%、1.73%，处于行业中等水平，在城商行中相对偏低，从息差结构来看，该行生息资产平均收益率约4.17%，相对偏低，负债平均利率2.44%，略高于同业；近3年该行ROE为11.22%、10.84%、11.41%，2021年有所提升。 3、2019-2021年资本充足率15.85%、15.21%、14.35%，趋于下行，目前仍处于合意水平；核心一级资本充足率10.20%、9.03%、8.74%，持续下降，存在一定资本补充压力；公司正在推进非公开发行A股，拟募资20亿，目前正待发行批复，如发行成功预计将带来核心一级资本充足率1.5%的提升，需关注后续资本补充效果。 | L21: =IFERROR(([1]!b_stm07_bs($A21,47,$A$1,1,100000000))/[1]!b_stm07_bs($A21,109,$A$1,1,100000000),"") -> 0.073689354 | M21: 4.83 | N21: =IFERROR(([1]!s_stmnote_bank_26($A21,$A$1,1,100000000)-[1]!s_stmnote_bank_26($A21,$B$1,1,100000000)+M21)/[1]!s_stmnote_bank_1n($A21,$B$1,1,100000000),"") -> 0.0048649433 | O21: =RANK(N21,N$5:N$192,1)&" "&COUNTIF(N$5:N$192,">0") -> 12 50 | P21: =IF(IFERROR(R21+AB21/100,"")=0,"",IFERROR(R21+AB21/100,"")) -> 0.012440343 | Q21: =RANK(P21,P$5:P$192,1)&" "&COUNTIF(P$5:P$192,">0") -> 9 169 | R21: 0.0031403431 | S21: 0.0036622576 | T21: 0.0085685942 | Z21: =[1]!b_stm07_bs(A21,74,$A$1,1,100000000) -> 2017.6986 | AA21: =[1]!b_stm07_bs(A21,109,$A$1,1,100000000) -> 1618.1108 | AB21: =[1]!s_stmnote_bank_5n(A21,$A$1,1) -> 0.93 | AC21: =IF([1]!s_stmnote_bank_23n(A21,$A$1,1)=0,"",IFERROR([1]!s_stmnote_bank_23n(A21,$A$1,1),"")) -> 477.19 | AD21: =RANK(AC21,AC$5:AC$192,1)&" "&COUNTIF(AC$5:AC$192,">0") -> 144 167 | AE21: =[1]!s_stmnote_bank_capadequacyratio(A21,$A$1,1) -> 14.35 | AF21: =IF([1]!s_stmnote_bank_capadequacyratio_ct1(A21,$A$1,1)=0,"",IFERROR([1]!s_stmnote_bank_capadequacyratio_ct1(A21,$A$1,1),"")) -> 8.74 | AG21: =RANK(AF21,AF$5:AF$192,1)&" "&COUNTIF(AF$5:AF$192,">0") -> 35 167 | AH21: =IF(OR([1]!s_fa_roe(A21,20201231)=0,[1]!s_fa_roe(A21,20211231)="0",[1]!s_fa_roe(A21,20221231)="0"),"",IFERROR(([1]!s_fa_roe(A21,20221231)+[1]!s_fa_roe(A21,20201231)+[1]!s_fa_roe(A21,20211231))/3,"")) -> 10.7421 | AI21: =RANK(AH21,AH$5:AH$192,1)&" "&COUNTIF(AH$5:AH$192,">0") -> 133 173 | AJ21: =IFERROR(([1]!s_stmnote_bank_65(A21,$A$1,1,2,4,100000000)+[1]!s_stmnote_bank_65(A21,$A$1,1,2,6,100000000))/[1]!s_stmnote_bank_1n(A21,$A$1,1,100000000),"") -> 0.033447284 | AK21: =IFERROR([1]!s_stmnote_bank_614(A21,$A$1,1,2,100000000)/[1]!s_stmnote_bank_647(A21,$A$1,1,2,100000000),"") -> 0.20916252 | AL21: =IFERROR(([1]!b_stm07_bs(A21,104,$A$1,1,100000000)+[1]!b_stm07_bs(A21,106,$A$1,1,100000000)+[1]!b_stm07_bs(A21,76,$A$1,1,100000000)+[1]!b_stm07_bs(A21,108,$A$1,1,100000000)+[1]!b_stm07_bs(A21,95,$A$1,1,100000000))/[1]!b_stm07_bs(A21,128,$A$1,1,100000000),"") -> 0.074318038 | AM21: =IFERROR(([1]!s_stmnote_bank_614(A21,$A$1,1,2,100000000)+[1]!b_stm07_bs(A21,104,$A$1,1,100000000)+[1]!b_stm07_bs(A21,106,$A$1,1,100000000)+[1]!b_stm07_bs(A21,76,$A$1,1,100000000)+[1]!b_stm07_bs(A21,108,$A$1,1,100000000)+[1]!b_stm07_bs(A21,95,$A$1,1,100000000))/[1]!b_stm07_bs(A21,128,$A$1,1,100000000),"") -> 0.25077246 | AN21: =IF(Z21>#REF!,#REF!,IF(Z21>#REF!,#REF!,IF(Z21>#REF!,#REF!,IF(Z21>#REF!,#REF!,IF(Z21>#REF!,#REF!,IF(Z21>#REF!,#REF!,IF(Z21>#REF!,#REF!,#REF!))))))) -> #REF! | AO21: =IF(AA21>#REF!,#REF!,IF(AA21>#REF!,#REF!,IF(AA21>#REF!,#REF!,IF(AA21>#REF!,#REF!,IF(AA21>#REF!,#REF!,IF(AA21>#REF!,#REF!,IF(AA21>#REF!,#REF!,#REF!))))))) -> #REF! | AP21: =IF(AB21<#REF!,#REF!,IF(AB21<#REF!,#REF!,IF(AB21<#REF!,#REF!,IF(AB21<#REF!,#REF!,IF(AB21<#REF!,#REF!,IF(AB21<#REF!,#REF!,#REF!)))))) -> #REF! | AQ21: =IF(AC21>#REF!,#REF!,IF(AC21>#REF!,#REF!,IF(AC21>#REF!,#REF!,IF(AC21>#REF!,#REF!,#REF!)))) -> #REF! | AR21: =IF(AE21>#REF!,#REF!,IF(AE21>#REF!,#REF!,IF(AE21>#REF!,#REF!,IF(AE21>#REF!,#REF!,#REF!)))) -> #REF! | AS21: =IF(AF21>#REF!,#REF!,IF(AF21>#REF!,#REF!,IF(AF21>#REF!,#REF!,IF(AF21>#REF!,#REF!,#REF!)))) -> #REF! | AT21: =IF(AH21>#REF!,#REF!,IF(AH21>#REF!,#REF!,IF(AH21>#REF!,#REF!,IF(AH21>#REF!,#REF!,IF(AH21>#REF!,#REF!,#REF!))))) -> #REF! | AU21: =AN21*$AN$3+AP21*$AP$3+AQ21*$AQ$3+AR21*$AR$3+AS21*$AS$3+AT21*$AT$3+$AO$3*AO21 -> #REF! | AV21: 强 | AW21: 较低 | AX21: 较好 | AY21: =IFERROR(VLOOKUP(AV21,#REF!,3,0),"") | AZ21: =IFERROR(VLOOKUP(AW21,#REF!,3,0),"") | BA21: =IFERROR(VLOOKUP(AX21,#REF!,3,0),"") | BB21: =IFERROR(AY21*#REF!+AZ21*#REF!+BA21*#REF!,"") | BC21: =IFERROR(AU21*0.6+BB21*0.4,"") | BD21: =IFERROR(VLOOKUP(BC21*10,#REF!,2,1),"") | BE21: 0 | BF21: -1 | BG21: 现金不足 | BH21: 无锡市太湖新城资产经营管理有限公司 | BI21: 9.0799999 | BJ21: 江苏 | BK21: 无锡市 | BL21: =IF([1]!s_stmnote_bank_17n(A21,$A$1,1)="0","",[1]!s_stmnote_bank_17n(A21,$A$1,1)) -> 0 | BM21: =IF([1]!s_stmnote_bank_18n(A21,$A$1,1)="0","",[1]!s_stmnote_bank_18n(A21,$A$1,1)) -> 21.31 | BP21: =[1]!s_stmnote_bank_5444(A21,$A$1,1) -> 1.95 | BQ21: =[1]!s_stmnote_bank_129n($A21,$A$1,1) -> 28.77 | BR21: =IFERROR(BS21/SUMPRODUCT(BT21:BX21,$BT$4:$BX$4)*SUMIFS($BT$4:$BX$4,BT21:BX21,">0")*100,0) -> 4.2428365 | BS21: =[1]!b_stm07_is(A21,19,$A$1,1,100000000) -> 77.7295 | BT21: =[1]!s_stm07_bs(A21,"W15273164",$A$1,1,100000000)-[1]!s_stm07_bs(A21,"W17642530",$A$1,1,100000000)-[1]!s_stm07_bs(A21,"W15910877",$A$1,1,100000000)-[1]!s_stm07_bs_39(A21,$A$1,1,100000000)-[1]!s_stm07_bs(A21,"W17700468",$A$1,1,100000000)-[1]!s_stm07_bs(A21,"W16504296",$A$1,1,100000000)-[1]!s_stm07_bs(A21,"W13769069",$A$1,1,100000000) -> 1991.8497 | BU21: =[1]!s_stm07_bs(A21,"W15273164",$B$1,1,100000000)-[1]!s_stm07_bs(A21,"W17642530",$B$1,1,100000000)-[1]!s_stm07_bs(A21,"W15910877",$B$1,1,100000000)-[1]!s_stm07_bs_39(A21,$B$1,1,100000000)-[1]!s_stm07_bs(A21,"W17700468",$B$1,1,100000000)-[1]!s_stm07_bs(A21,"W16504296",$B$1,1,100000000)-[1]!s_stm07_bs(A21,"W13769069",$B$1,1,100000000) -> 1775.9518 | BV21: =[1]!s_stm07_bs(A21,"W15273164",$E$1,1,100000000)-[1]!s_stm07_bs(A21,"W17642530",$E$1,1,100000000)-[1]!s_stm07_bs(A21,"W15910877",$E$1,1,100000000)-[1]!s_stm07_bs_39(A21,$E$1,1,100000000)-[1]!s_stm07_bs(A21,"W17700468",$E$1,1,100000000)-[1]!s_stm07_bs(A21,"W16504296",$E$1,1,100000000)-[1]!s_stm07_bs(A21,"W13769069",$E$1,1,100000000) -> 2008.3362 | BW21: =[1]!s_stm07_bs(A21,"W15273164",$F$1,1,100000000)-[1]!s_stm07_bs(A21,"W17642530",$F$1,1,100000000)-[1]!s_stm07_bs(A21,"W15910877",$F$1,1,100000000)-[1]!s_stm07_bs_39(A21,$F$1,1,100000000)-[1]!s_stm07_bs(A21,"W17700468",$F$1,1,100000000)-[1]!s_stm07_bs(A21,"W16504296",$F$1,1,100000000)-[1]!s_stm07_bs(A21,"W13769069",$F$1,1,100000000) -> 1949.1692 | BX21: =[1]!s_stm07_bs(A21,"W15273164",$G$1,1,100000000)-[1]!s_stm07_bs(A21,"W17642530",$G$1,1,100000000)-[1]!s_stm07_bs(A21,"W15910877",$G$1,1,100000000)-[1]!s_stm07_bs_39(A21,$G$1,1,100000000)-[1]!s_stm07_bs(A21,"W17700468",$G$1,1,100000000)-[1]!s_stm07_bs(A21,"W16504296",$G$1,1,100000000)-[1]!s_stm07_bs(A21,"W13769069",$G$1,1,100000000) -> 1886.648 | BY21: =IFERROR([1]!b_stm07_is(A21,20,$A$1,1,100000000)/AVERAGEIF(CA21:CE21,">0")*100,0) -> 2.3888513 | BZ21: =[1]!b_stm07_is(A21,20,$A$1,1,100000000) -> 42.68873 | CA21: =[1]!s_stmnote_bank_38(A21,$A$1,1,100000000) -> 1852.2879 | CB21: =[1]!s_stmnote_bank_38(A21,$B$1,1,100000000) -> 1643.0247 | CC21: =[1]!s_stmnote_bank_38(A21,$E$1,1,100000000) -> 1868.0773 | CD21: =[1]!s_stmnote_bank_38(A21,$F$1,1,100000000) -> 1814.0886 | CE21: =[1]!s_stmnote_bank_38(A21,$G$1,1,100000000) -> 1757.5124 | CF21: =IF(BP21<>0,BP21,IFERROR(IF(([1]!b_stm07_is(A21,19,$A$1,1,100000000)-[1]!b_stm07_is(A21,20,$A$1,1,100000000))/AVERAGE([1]!s_stmnote_bank_35(A21,$A$1,1,100000000),[1]!s_stmnote_bank_35(A21,$B$1,1,100000000))*100=0,"",([1]!b_stm07_is(A21,19,$A$1,1,100000000)-[1]!b_stm07_is(A21,20,$A$1,1,100000000))/AVERAGE([1]!s_stmnote_bank_35(A21,$A$1,1,100000000),[1]!s_stmnote_bank_35(A21,$B$1,1,100000000))*100),"")) -> 1.95 | CG21: =RANK(CF21,CF$5:CF$192,0)&" "&COUNTIF(CF$5:CF$192,">0") -> 101 171 | CH21: =IFERROR(CF21/100/P21,"") -> 1.5674809 | CI21: =RANK(CH21,CH$5:CH$192,0)&" "&COUNTIF(CH$5:CH$192,">0") -> 22 169 | CJ21: =[1]!s_stmnote_bank_30(A21,$A$1,1) -> 19.433 | CP21: =[1]!b_stm07_bs($A21,141,$A$1,1,100000000) -> 159.24161 | CQ21: =[1]!b_stm07_bs($A21,141,$D$1,1,100000000) -> 169.18601 | CR21: =IF([1]!s_fa_roic_yearly($A21,$A$1)=0,"",[1]!s_fa_roic_yearly($A21,$A$1)) -> 10.6135 | CS21: =RANK(CR21,CR$5:CR$192,0)/COUNTIF(CR$5:CR$192,">0") -> 0.27218935 | CT21: =IF([1]!s_fa_roic_yearly($A21,$D$1)=0,"",[1]!s_fa_roic_yearly($A21,$D$1)) -> 12.5218 | CU21: =RANK(CT21,CT$5:CT$192,0)/COUNTIF(CT$5:CT$192,">0") -> 0.22535211 | CV21: =[1]!s_stm07_bs(A21,"W14578191",$A$1,1,100000000) -> 1127.4155 | CW21: =[1]!s_stmnote_bank_682($A21,$A$1,1,2,100000000) -> 251.22822 | CX21: =IF(CW21*CV21=0,"",CW21/CV21) -> 0.22283553
A22: 111615195 | B22: 中国民生银行股份有限公司 | C22: 中国民生银行 | D22: 股份行 | E22: 有 | F22: AAA | G22: BBB+ | H22: A- | J22: =VLOOKUP(B22,[3]额度信息!$B:$T,19,0) -> 0 | K22: 一、 主要优势 1、全国十二家股份制银行之一，业务规模在股份制商业银行中位居前列，市场地位显著。该行21年实现营业收入1688亿，同比-15%，归母净利润343.8亿，同比+0.2%，仍处于业务调整阵痛期。 2、对公业务和零售业务客群基础较好，投行业务和金融市场业务等保持前列。 二、 主要关注 1、2019-21年，该行加权平均ROE分别为12.40%、6.81%、6.59%，由于持续计提大额信用减值损失，ROE属于同业较低水平。整体来看，21年经营情况较20年有所改善，但幅度不及预期，后续盈利和资产质量情况需要保持关注。 2、2019-21年，公司计提信用减值损失628.1、929.9、774.0亿，近年来不良贷款风险有所暴露，主要与房地产业务敞口较大（21年末4734亿，较20年下降1169亿）、民企客户多、原先不良贷款认定标准较宽松等因素有关。截至21年末，关不良率1.79%，同比减少0.03个百分点；关注类贷款2.85%，同比下降0.14个百分点。 3、该行对同业负债依赖度较高，负债的稳定性有待提高。20、21年该行业绩表现均不及预期，同业负债和客户存款的稳定性可能受到负面冲击，后续需保持关注。 | L22: =IFERROR(([1]!b_stm07_bs($A22,47,$A$1,1,100000000))/[1]!b_stm07_bs($A22,109,$A$1,1,100000000),"") -> 0.094440929 | M22: 840.76 | N22: =IFERROR(([1]!s_stmnote_bank_26($A22,$A$1,1,100000000)-[1]!s_stmnote_bank_26($A22,$B$1,1,100000000)+M22)/[1]!s_stmnote_bank_1n($A22,$B$1,1,100000000),"") -> 0.022409586 | O22: =RANK(N22,N$5:N$192,1)&" "&COUNTIF(N$5:N$192,">0") -> 45 50 | P22: =IF(IFERROR(R22+AB22/100,"")=0,"",IFERROR(R22+AB22/100,"")) -> 0.046809886 | Q22: =RANK(P22,P$5:P$192,1)&" "&COUNTIF(P$5:P$192,">0") -> 128 169 | R22: 0.028909886 | S22: 0.052497329 | T22: 0.01911042 | U22: 0.010761235 | W22: 0.011150777 | X22: 0.018216543 | Y22: 0.27953403 | Z22: =[1]!b_stm07_bs(A22,74,$A$1,1,100000000) -> 69527.86 | AA22: =[1]!b_stm07_bs(A22,109,$A$1,1,100000000) -> 38256.93 | AB22: =[1]!s_stmnote_bank_5n(A22,$A$1,1) -> 1.79 | AC22: =IF([1]!s_stmnote_bank_23n(A22,$A$1,1)=0,"",IFERROR([1]!s_stmnote_bank_23n(A22,$A$1,1),"")) -> 145.3 | AD22: =RANK(AC22,AC$5:AC$192,1)&" "&COUNTIF(AC$5:AC$192,">0") -> 16 167 | AE22: =[1]!s_stmnote_bank_capadequacyratio(A22,$A$1,1) -> 13.64 | AF22: =IF([1]!s_stmnote_bank_capadequacyratio_ct1(A22,$A$1,1)=0,"",IFERROR([1]!s_stmnote_bank_capadequacyratio_ct1(A22,$A$1,1),"")) -> 9.04 | AG22: =RANK(AF22,AF$5:AF$192,0)&" "&COUNTIF(AF$5:AF$192,">0") -> 123 167 | AH22: =IF(OR([1]!s_fa_roe(A22,20201231)=0,[1]!s_fa_roe(A22,20211231)="0",[1]!s_fa_roe(A22,20221231)="0"),"",IFERROR(([1]!s_fa_roe(A22,20221231)+[1]!s_fa_roe(A22,20201231)+[1]!s_fa_roe(A22,20211231))/3,"")) -> 6.2606333 | AI22: =RANK(AH22,AH$5:AH$192,1)&" "&COUNTIF(AH$5:AH$192,">0") -> 60 173 | AJ22: =IFERROR(([1]!s_stmnote_bank_65(A22,$A$1,1,2,4,100000000)+[1]!s_stmnote_bank_65(A22,$A$1,1,2,6,100000000))/[1]!s_stmnote_bank_1n(A22,$A$1,1,100000000),"") -> 0.11695824 | AK22: =IFERROR([1]!s_stmnote_bank_614(A22,$A$1,1,2,100000000)/[1]!s_stmnote_bank_647(A22,$A$1,1,2,100000000),"") -> 0.32185273 | AL22: =IFERROR(([1]!b_stm07_bs(A22,104,$A$1,1,100000000)+[1]!b_stm07_bs(A22,106,$A$1,1,100000000)+[1]!b_stm07_bs(A22,76,$A$1,1,100000000)+[1]!b_stm07_bs(A22,108,$A$1,1,100000000)+[1]!b_stm07_bs(A22,95,$A$1,1,100000000))/[1]!b_stm07_bs(A22,128,$A$1,1,100000000),"") -> 0.32118185 | AM22: =IFERROR(([1]!s_stmnote_bank_614(A22,$A$1,1,2,100000000)+[1]!b_stm07_bs(A22,104,$A$1,1,100000000)+[1]!b_stm07_bs(A22,106,$A$1,1,100000000)+[1]!b_stm07_bs(A22,76,$A$1,1,100000000)+[1]!b_stm07_bs(A22,108,$A$1,1,100000000)+[1]!b_stm07_bs(A22,95,$A$1,1,100000000))/[1]!b_stm07_bs(A22,128,$A$1,1,100000000),"") -> 0.51206967 | AN22: =IF(Z22>#REF!,#REF!,IF(Z22>#REF!,#REF!,IF(Z22>#REF!,#REF!,IF(Z22>#REF!,#REF!,IF(Z22>#REF!,#REF!,IF(Z22>#REF!,#REF!,IF(Z22>#REF!,#REF!,#REF!))))))) -> #REF! | AO22: =IF(AA22>#REF!,#REF!,IF(AA22>#REF!,#REF!,IF(AA22>#REF!,#REF!,IF(AA22>#REF!,#REF!,IF(AA22>#REF!,#REF!,IF(AA22>#REF!,#REF!,IF(AA22>#REF!,#REF!,#REF!))))))) -> #REF! | AP22: =IF(AB22<#REF!,#REF!,IF(AB22<#REF!,#REF!,IF(AB22<#REF!,#REF!,IF(AB22<#REF!,#REF!,IF(AB22<#REF!,#REF!,IF(AB22<#REF!,#REF!,#REF!)))))) -> #REF! | AQ22: =IF(AC22>#REF!,#REF!,IF(AC22>#REF!,#REF!,IF(AC22>#REF!,#REF!,IF(AC22>#REF!,#REF!,#REF!)))) -> #REF! | AR22: =IF(AE22>#REF!,#REF!,IF(AE22>#REF!,#REF!,IF(AE22>#REF!,#REF!,IF(AE22>#REF!,#REF!,#REF!)))) -> #REF! | AS22: =IF(AF22>#REF!,#REF!,IF(AF22>#REF!,#REF!,IF(AF22>#REF!,#REF!,IF(AF22>#REF!,#REF!,#REF!)))) -> #REF! | AT22: =IF(AH22>#REF!,#REF!,IF(AH22>#REF!,#REF!,IF(AH22>#REF!,#REF!,IF(AH22>#REF!,#REF!,IF(AH22>#REF!,#REF!,#REF!))))) -> #REF! | AU22: =AN22*$AN$3+AP22*$AP$3+AQ22*$AQ$3+AR22*$AR$3+AS22*$AS$3+AT22*$AT$3+$AO$3*AO22 -> #REF! | AV22: 很强 | AW22: 高 | AX22: 中 | AY22: =IFERROR(VLOOKUP(AV22,#REF!,3,0),"") | AZ22: =IFERROR(VLOOKUP(AW22,#REF!,3,0),"") | BA22: =IFERROR(VLOOKUP(AX22,#REF!,3,0),"") | BB22: =IFERROR(AY22*#REF!+AZ22*#REF!+BA22*#REF!,"") | BC22: =IFERROR(AU22*0.6+BB22*0.4,"") | BD22: =IFERROR(VLOOKUP(BC22*10,#REF!,2,1),"") | BE22: 2 | BF22: -1 | BG22: 公司治理负面，负债不稳，地产负面 | BH22: 香港中央结算(代理人)有限公司 | BI22: 18.92 | BJ22: 全国 | BK22: - | BL22: =IF([1]!s_stmnote_bank_17n(A22,$A$1,1)="0","",[1]!s_stmnote_bank_17n(A22,$A$1,1)) -> 1.57 | BM22: =IF([1]!s_stmnote_bank_18n(A22,$A$1,1)="0","",[1]!s_stmnote_bank_18n(A22,$A$1,1)) -> 9.76 | BN22: 3.91 | BO22: 2.4 | BP22: =[1]!s_stmnote_bank_5444(A22,$A$1,1) -> 1.91 | BQ22: =[1]!s_stmnote_bank_129n($A22,$A$1,1) -> 29.17 | BR22: =IFERROR(BS22/SUMPRODUCT(BT22:BX22,$BT$4:$BX$4)*SUMIFS($BT$4:$BX$4,BT22:BX22,">0")*100,0) -> 4.0776682 | BS22: =[1]!b_stm07_is(A22,19,$A$1,1,100000000) -> 2776.79 | BT22: =[1]!s_stm07_bs(A22,"W15273164",$A$1,1,100000000)-[1]!s_stm07_bs(A22,"W17642530",$A$1,1,100000000)-[1]!s_stm07_bs(A22,"W15910877",$A$1,1,100000000)-[1]!s_stm07_bs_39(A22,$A$1,1,100000000)-[1]!s_stm07_bs(A22,"W17700468",$A$1,1,100000000)-[1]!s_stm07_bs(A22,"W16504296",$A$1,1,100000000)-[1]!s_stm07_bs(A22,"W13769069",$A$1,1,100000000) -> 67901.94 | BU22: =[1]!s_stm07_bs(A22,"W15273164",$B$1,1,100000000)-[1]!s_stm07_bs(A22,"W17642530",$B$1,1,100000000)-[1]!s_stm07_bs(A22,"W15910877",$B$1,1,100000000)-[1]!s_stm07_bs_39(A22,$B$1,1,100000000)-[1]!s_stm07_bs(A22,"W17700468",$B$1,1,100000000)-[1]!s_stm07_bs(A22,"W16504296",$B$1,1,100000000)-[1]!s_stm07_bs(A22,"W13769069",$B$1,1,100000000) -> 67876.99 | BV22: =[1]!s_stm07_bs(A22,"W15273164",$E$1,1,100000000)-[1]!s_stm07_bs(A22,"W17642530",$E$1,1,100000000)-[1]!s_stm07_bs(A22,"W15910877",$E$1,1,100000000)-[1]!s_stm07_bs_39(A22,$E$1,1,100000000)-[1]!s_stm07_bs(A22,"W17700468",$E$1,1,100000000)-[1]!s_stm07_bs(A22,"W16504296",$E$1,1,100000000)-[1]!s_stm07_bs(A22,"W13769069",$E$1,1,100000000) -> 68595.93 | BW22: =[1]!s_stm07_bs(A22,"W15273164",$F$1,1,100000000)-[1]!s_stm07_bs(A22,"W17642530",$F$1,1,100000000)-[1]!s_stm07_bs(A22,"W15910877",$F$1,1,100000000)-[1]!s_stm07_bs_39(A22,$F$1,1,100000000)-[1]!s_stm07_bs(A22,"W17700468",$F$1,1,100000000)-[1]!s_stm07_bs(A22,"W16504296",$F$1,1,100000000)-[1]!s_stm07_bs(A22,"W13769069",$F$1,1,100000000) -> 69136.05 | BX22: =[1]!s_stm07_bs(A22,"W15273164",$G$1,1,100000000)-[1]!s_stm07_bs(A22,"W17642530",$G$1,1,100000000)-[1]!s_stm07_bs(A22,"W15910877",$G$1,1,100000000)-[1]!s_stm07_bs_39(A22,$G$1,1,100000000)-[1]!s_stm07_bs(A22,"W17700468",$G$1,1,100000000)-[1]!s_stm07_bs(A22,"W16504296",$G$1,1,100000000)-[1]!s_stm07_bs(A22,"W13769069",$G$1,1,100000000) -> 69000.17 | BY22: =IFERROR([1]!b_stm07_is(A22,20,$A$1,1,100000000)/AVERAGEIF(CA22:CE22,">0")*100,0) -> 2.4507752 | BZ22: =[1]!b_stm07_is(A22,20,$A$1,1,100000000) -> 1519.04 | CA22: =[1]!s_stmnote_bank_38(A22,$A$1,1,100000000) -> 61502.03 | CB22: =[1]!s_stmnote_bank_38(A22,$B$1,1,100000000) -> 61567.15 | CC22: =[1]!s_stmnote_bank_38(A22,$E$1,1,100000000) -> 61923.73 | CD22: =[1]!s_stmnote_bank_38(A22,$F$1,1,100000000) -> 62383.14 | CE22: =[1]!s_stmnote_bank_38(A22,$G$1,1,100000000) -> 62534.06 | CF22: =IF(BP22<>0,BP22,IFERROR(IF(([1]!b_stm07_is(A22,19,$A$1,1,100000000)-[1]!b_stm07_is(A22,20,$A$1,1,100000000))/AVERAGE([1]!s_stmnote_bank_35(A22,$A$1,1,100000000),[1]!s_stmnote_bank_35(A22,$B$1,1,100000000))*100=0,"",([1]!b_stm07_is(A22,19,$A$1,1,100000000)-[1]!b_stm07_is(A22,20,$A$1,1,100000000))/AVERAGE([1]!s_stmnote_bank_35(A22,$A$1,1,100000000),[1]!s_stmnote_bank_35(A22,$B$1,1,100000000))*100),"")) -> 1.91 | CG22: =RANK(CF22,CF$5:CF$192,0)&" "&COUNTIF(CF$5:CF$192,">0") -> 107 171 | CH22: =IFERROR(CF22/100/P22,"") -> 0.40803347 | CI22: =RANK(CH22,CH$5:CH$192,0)&" "&COUNTIF(CH$5:CH$192,">0") -> 131 169 | CJ22: =[1]!s_stmnote_bank_30(A22,$A$1,1) -> 25.4905 | CK22: 1863.86 | CL22: 564.47 | CM22: =CK22/(5/8*[1]!s_stmnote_bank_1n($A22,$A$1,1,100000000)+[1]!s_stmnote_bank_1n($A22,$B$1,1,100000000)*3/8) -> 0.046903936 | CP22: =[1]!b_stm07_bs($A22,141,$A$1,1,100000000) -> 5865.39 | CQ22: =[1]!b_stm07_bs($A22,141,$D$1,1,100000000) -> 6027.11 | CR22: =IF([1]!s_fa_roic_yearly($A22,$A$1)=0,"",[1]!s_fa_roic_yearly($A22,$A$1)) -> 6.2295 | CS22: =RANK(CR22,CR$5:CR$192,1)&" "&COUNTIF(CR$5:CR$192,">0") -> 50 169 | CT22: =IF([1]!s_fa_roic_yearly($A22,$D$1)=0,"",[1]!s_fa_roic_yearly($A22,$D$1)) -> 8.4634 | CU22: =RANK(CT22,CT$5:CT$192,1)&" "&COUNTIF(CT$5:CT$192,">0") -> 47 142 | CV22: =[1]!s_stm07_bs(A22,"W14578191",$A$1,1,100000000) -> 39676.79 | CW22: =[1]!s_stmnote_bank_682($A22,$A$1,1,2,100000000) -> 17413.31 | CX22: =IF(CW22*CV22=0,"",CW22/CV22) -> 0.438879
A23: 111770083 | B23: 浙江民泰商业银行股份有限公司 | C23: 浙江民泰商业银行 | D23: 城商行 | F23: AA+ | H23: BB- | J23: =VLOOKUP(B23,[3]额度信息!$B:$T,19,0) -> #N/A | L23: =IFERROR(([1]!b_stm07_bs($A23,47,$A$1,1,100000000))/[1]!b_stm07_bs($A23,109,$A$1,1,100000000),"") -> 0.10476362 | O23: =RANK(N23,N$5:N$192,1)&" "&COUNTIF(N$5:N$192,">0") -> #N/A | P23: =IF(IFERROR(R23+AB23/100,"")=0,"",IFERROR(R23+AB23/100,"")) -> 0.021770111 | Q23: =RANK(P23,P$5:P$192,1)&" "&COUNTIF(P$5:P$192,">0") -> 46 169 | R23: =IFERROR([1]!s_stmnote_bank($A23,"34",$A$1,100000000)/[1]!s_stmnote_bank_1n(A23,$A$1,1,100000000),"") -> 0.0082701112 | Z23: =[1]!b_stm07_bs(A23,74,$A$1,1,100000000) -> 2032.7239 | AA23: =[1]!b_stm07_bs(A23,109,$A$1,1,100000000) -> 1527.3355 | AB23: =[1]!s_stmnote_bank_5n(A23,$A$1,1) -> 1.35 | AC23: =IF([1]!s_stmnote_bank_23n(A23,$A$1,1)=0,"",IFERROR([1]!s_stmnote_bank_23n(A23,$A$1,1),"")) -> 170.74 | AD23: =RANK(AC23,AC$5:AC$192,1)&" "&COUNTIF(AC$5:AC$192,">0") -> 40 167 | AE23: =[1]!s_stmnote_bank_capadequacyratio(A23,$A$1,1) -> 11.68 | AF23: =IF([1]!s_stmnote_bank_capadequacyratio_ct1(A23,$A$1,1)=0,"",IFERROR([1]!s_stmnote_bank_capadequacyratio_ct1(A23,$A$1,1),"")) -> 8.73 | AG23: =RANK(AF23,AF$5:AF$192,1)&" "&COUNTIF(AF$5:AF$192,">0") -> 34 167 | AH23: =IF(OR([1]!s_fa_roe(A23,20201231)=0,[1]!s_fa_roe(A23,20211231)="0",[1]!s_fa_roe(A23,20221231)="0"),"",IFERROR(([1]!s_fa_roe(A23,20221231)+[1]!s_fa_roe(A23,20201231)+[1]!s_fa_roe(A23,20211231))/3,"")) -> 7.6311333 | AI23: =RANK(AH23,AH$5:AH$192,1)&" "&COUNTIF(AH$5:AH$192,">0") -> 72 173 | AJ23: =IFERROR(([1]!s_stmnote_bank_65(A23,$A$1,1,2,4,100000000)+[1]!s_stmnote_bank_65(A23,$A$1,1,2,6,100000000))/[1]!s_stmnote_bank_1n(A23,$A$1,1,100000000),"") -> 0.11368371 | AK23: =IFERROR([1]!s_stmnote_bank_614(A23,$A$1,1,2,100000000)/[1]!s_stmnote_bank_647(A23,$A$1,1,2,100000000),"") -> 0.22564926 | AL23: =IFERROR(([1]!b_stm07_bs(A23,104,$A$1,1,100000000)+[1]!b_stm07_bs(A23,106,$A$1,1,100000000)+[1]!b_stm07_bs(A23,76,$A$1,1,100000000)+[1]!b_stm07_bs(A23,108,$A$1,1,100000000)+[1]!b_stm07_bs(A23,95,$A$1,1,100000000))/[1]!b_stm07_bs(A23,128,$A$1,1,100000000),"") -> 0.15160872 | AM23: =IFERROR(([1]!s_stmnote_bank_614(A23,$A$1,1,2,100000000)+[1]!b_stm07_bs(A23,104,$A$1,1,100000000)+[1]!b_stm07_bs(A23,106,$A$1,1,100000000)+[1]!b_stm07_bs(A23,76,$A$1,1,100000000)+[1]!b_stm07_bs(A23,108,$A$1,1,100000000)+[1]!b_stm07_bs(A23,95,$A$1,1,100000000))/[1]!b_stm07_bs(A23,128,$A$1,1,100000000),"") -> 0.33353029 | AN23: =IF(Z23>#REF!,#REF!,IF(Z23>#REF!,#REF!,IF(Z23>#REF!,#REF!,IF(Z23>#REF!,#REF!,IF(Z23>#REF!,#REF!,IF(Z23>#REF!,#REF!,IF(Z23>#REF!,#REF!,#REF!))))))) -> #REF! | AO23: =IF(AA23>#REF!,#REF!,IF(AA23>#REF!,#REF!,IF(AA23>#REF!,#REF!,IF(AA23>#REF!,#REF!,IF(AA23>#REF!,#REF!,IF(AA23>#REF!,#REF!,IF(AA23>#REF!,#REF!,#REF!))))))) -> #REF! | AP23: =IF(AB23<#REF!,#REF!,IF(AB23<#REF!,#REF!,IF(AB23<#REF!,#REF!,IF(AB23<#REF!,#REF!,IF(AB23<#REF!,#REF!,IF(AB23<#REF!,#REF!,#REF!)))))) -> #REF! | AQ23: =IF(AC23>#REF!,#REF!,IF(AC23>#REF!,#REF!,IF(AC23>#REF!,#REF!,IF(AC23>#REF!,#REF!,#REF!)))) -> #REF! | AR23: =IF(AE23>#REF!,#REF!,IF(AE23>#REF!,#REF!,IF(AE23>#REF!,#REF!,IF(AE23>#REF!,#REF!,#REF!)))) -> #REF! | AS23: =IF(AF23>#REF!,#REF!,IF(AF23>#REF!,#REF!,IF(AF23>#REF!,#REF!,IF(AF23>#REF!,#REF!,#REF!)))) -> #REF! | AT23: =IF(AH23>#REF!,#REF!,IF(AH23>#REF!,#REF!,IF(AH23>#REF!,#REF!,IF(AH23>#REF!,#REF!,IF(AH23>#REF!,#REF!,#REF!))))) -> #REF! | AU23: =AN23*$AN$3+AP23*$AP$3+AQ23*$AQ$3+AR23*$AR$3+AS23*$AS$3+AT23*$AT$3+$AO$3*AO23 -> #REF! | AV23: 中 | AW23: 低 | AX23: 好 | AY23: =IFERROR(VLOOKUP(AV23,#REF!,3,0),"") | AZ23: =IFERROR(VLOOKUP(AW23,#REF!,3,0),"") | BA23: =IFERROR(VLOOKUP(AX23,#REF!,3,0),"") | BB23: =IFERROR(AY23*#REF!+AZ23*#REF!+BA23*#REF!,"") | BC23: =IFERROR(AU23*0.6+BB23*0.4,"") | BD23: =IFERROR(VLOOKUP(BC23*10,#REF!,2,1),"") | BH23: 温岭市国有资产经营有限公司 | BI23: 8.2299995 | BJ23: 浙江 | BK23: 温岭市 | BL23: =IF([1]!s_stmnote_bank_17n(A23,$A$1,1)="0","",[1]!s_stmnote_bank_17n(A23,$A$1,1)) -> 3.94 | BM23: =IF([1]!s_stmnote_bank_18n(A23,$A$1,1)="0","",[1]!s_stmnote_bank_18n(A23,$A$1,1)) -> 28.55 | BP23: =[1]!s_stmnote_bank_5444(A23,$A$1,1) -> 0 | BQ23: =[1]!s_stmnote_bank_129n($A23,$A$1,1) -> 50.95 | BR23: =IFERROR(BS23/SUMPRODUCT(BT23:BX23,$BT$4:$BX$4)*SUMIFS($BT$4:$BX$4,BT23:BX23,">0")*100,0) -> 6.2699053 | BS23: =[1]!b_stm07_is(A23,19,$A$1,1,100000000) -> 112.84562 | BT23: =[1]!s_stm07_bs(A23,"W15273164",$A$1,1,100000000)-[1]!s_stm07_bs(A23,"W17642530",$A$1,1,100000000)-[1]!s_stm07_bs(A23,"W15910877",$A$1,1,100000000)-[1]!s_stm07_bs_39(A23,$A$1,1,100000000)-[1]!s_stm07_bs(A23,"W17700468",$A$1,1,100000000)-[1]!s_stm07_bs(A23,"W16504296",$A$1,1,100000000)-[1]!s_stm07_bs(A23,"W13769069",$A$1,1,100000000) -> 1942.2421 | BU23: =[1]!s_stm07_bs(A23,"W15273164",$B$1,1,100000000)-[1]!s_stm07_bs(A23,"W17642530",$B$1,1,100000000)-[1]!s_stm07_bs(A23,"W15910877",$B$1,1,100000000)-[1]!s_stm07_bs_39(A23,$B$1,1,100000000)-[1]!s_stm07_bs(A23,"W17700468",$B$1,1,100000000)-[1]!s_stm07_bs(A23,"W16504296",$B$1,1,100000000)-[1]!s_stm07_bs(A23,"W13769069",$B$1,1,100000000) -> 1770.5279 | BV23: =[1]!s_stm07_bs(A23,"W15273164",$E$1,1,100000000)-[1]!s_stm07_bs(A23,"W17642530",$E$1,1,100000000)-[1]!s_stm07_bs(A23,"W15910877",$E$1,1,100000000)-[1]!s_stm07_bs_39(A23,$E$1,1,100000000)-[1]!s_stm07_bs(A23,"W17700468",$E$1,1,100000000)-[1]!s_stm07_bs(A23,"W16504296",$E$1,1,100000000)-[1]!s_stm07_bs(A23,"W13769069",$E$1,1,100000000) -> 1897.3626 | BW23: =[1]!s_stm07_bs(A23,"W15273164",$F$1,1,100000000)-[1]!s_stm07_bs(A23,"W17642530",$F$1,1,100000000)-[1]!s_stm07_bs(A23,"W15910877",$F$1,1,100000000)-[1]!s_stm07_bs_39(A23,$F$1,1,100000000)-[1]!s_stm07_bs(A23,"W17700468",$F$1,1,100000000)-[1]!s_stm07_bs(A23,"W16504296",$F$1,1,100000000)-[1]!s_stm07_bs(A23,"W13769069",$F$1,1,100000000) -> 1834.3253 | BX23: =[1]!s_stm07_bs(A23,"W15273164",$G$1,1,100000000)-[1]!s_stm07_bs(A23,"W17642530",$G$1,1,100000000)-[1]!s_stm07_bs(A23,"W15910877",$G$1,1,100000000)-[1]!s_stm07_bs_39(A23,$G$1,1,100000000)-[1]!s_stm07_bs(A23,"W17700468",$G$1,1,100000000)-[1]!s_stm07_bs(A23,"W16504296",$G$1,1,100000000)-[1]!s_stm07_bs(A23,"W13769069",$G$1,1,100000000) -> 1758.0698 | BY23: =IFERROR([1]!b_stm07_is(A23,20,$A$1,1,100000000)/AVERAGEIF(CA23:CE23,">0")*100,0) -> 3.5936928 | BZ23: =[1]!b_stm07_is(A23,20,$A$1,1,100000000) -> 62.608811 | CA23: =[1]!s_stmnote_bank_38(A23,$A$1,1,100000000) -> 1866.7662 | CB23: =[1]!s_stmnote_bank_38(A23,$B$1,1,100000000) -> 1674.7019 | CC23: =[1]!s_stmnote_bank_38(A23,$E$1,1,100000000) -> 1783.6153 | CD23: =[1]!s_stmnote_bank_38(A23,$F$1,1,100000000) -> 1723.1057 | CE23: =[1]!s_stmnote_bank_38(A23,$G$1,1,100000000) -> 1662.7406 | CF23: =IF(BP23<>0,BP23,IFERROR(IF(([1]!b_stm07_is(A23,19,$A$1,1,100000000)-[1]!b_stm07_is(A23,20,$A$1,1,100000000))/AVERAGE([1]!s_stmnote_bank_35(A23,$A$1,1,100000000),[1]!s_stmnote_bank_35(A23,$B$1,1,100000000))*100=0,"",([1]!b_stm07_is(A23,19,$A$1,1,100000000)-[1]!b_stm07_is(A23,20,$A$1,1,100000000))/AVERAGE([1]!s_stmnote_bank_35(A23,$A$1,1,100000000),[1]!s_stmnote_bank_35(A23,$B$1,1,100000000))*100),"")) -> 3.0015816 | CG23: =RANK(CF23,CF$5:CF$192,0)&" "&COUNTIF(CF$5:CF$192,">0") -> 13 171 | CH23: =IFERROR(CF23/100/P23,"") -> 1.3787626 | CI23: =RANK(CH23,CH$5:CH$192,0)&" "&COUNTIF(CH$5:CH$192,">0") -> 28 169 | CJ23: =[1]!s_stmnote_bank_30(A23,$A$1,1) -> 12.6472 | CP23: =[1]!b_stm07_bs($A23,141,$A$1,1,100000000) -> 138.26953 | CQ23: =[1]!b_stm07_bs($A23,141,$D$1,1,100000000) -> 153.97528 | CR23: =IF([1]!s_fa_roic_yearly($A23,$A$1)=0,"",[1]!s_fa_roic_yearly($A23,$A$1)) -> 8.3635 | CS23: =RANK(CR23,CR$5:CR$192,0)/COUNTIF(CR$5:CR$192,">0") -> 0.55029586 | CT23: =IF([1]!s_fa_roic_yearly($A23,$D$1)=0,"",[1]!s_fa_roic_yearly($A23,$D$1)) -> 7.813 | CU23: =RANK(CT23,CT$5:CT$192,0)/COUNTIF(CT$5:CT$192,">0") -> 0.71126761 | CV23: =[1]!s_stm07_bs(A23,"W14578191",$A$1,1,100000000) -> 1381.1919 | CW23: =[1]!s_stmnote_bank_682($A23,$A$1,1,2,100000000) -> 736.50669 | CX23: =IF(CW23*CV23=0,"",CW23/CV23) -> 0.53323994
